Workbook

Sheet Read Me
A1: NAPOR: Risk Assessment - Iran-US War
A2: NAPOR is the underlying engine (event log, credibility, chains, phases, forecasts). NAPOR: Risk Assessment applies it to lay out the options and the risks and pros of each one. It does not pick an option. Built by Sidd.
A4: What this is
A5: A structured, dated log of US/Israel-Iran war events from Feb 28, 2026 to Oct 26, 2026, built for computing base rates (how often does X follow Y, and how fast) rather than for narrative reading.
A7: Sheets
A8: Event Log - every event, one row each, with a Trigger ID column pointing to the row that caused it, where reporting says so. Columns N-O count the reports behind each event and how many different independent or official outlets they come from.
A9: Credibility (0-1) - every report gets a weight = source score x fit score. Source score: credible outlet or official statement 0.80, other outlet 0.60, Iranian state media 0.30 (it can only show what Iran claims). Fit score (how sure we are the story is about this event): read in full 1.00, headline only 0.80, outlet named but story not saved 0.65. Reports under 0.30 do not count. An event combines its reports, each outlet counted once, as 1 - (1-w1)(1-w2)..., the chance that not every outlet got it wrong: one full-text credible story = 0.80, two different outlets = 0.96. Partly verified rows are multiplied by 0.8; Not supported rows are capped at 0.20. RULE: only events at 0.50 or above are used in the statistics; 0.50-0.65 is used but flagged 'use with caution'. The Confidence column (High 0.80+, Medium 0.50-0.80, Low under 0.50) now comes from this score. This is a scoring rule, not a statistical confidence interval.
A10: Chains & Phases - every event is tagged with the war phase it happened in (open war, fragile ceasefire, low-intensity war, holding pattern) and, if it is part of a back-and-forth, a chain ID (T01...). The sheet shows reply rates by phase and how long back-and-forths usually last.
A11: War intensity - a 0-and-up points gauge of how hot the war was in the 14 days before any date (2 per direct strike, 1 per shipping/blockade act, +2 if deadly), banded Quiet/Low/Medium/High. Shown in the Event Log and on Chains & Phases. It did not improve the backtest, so it is a gauge, not an input to the numbers.
A12: Forecast Log - the report card. Predictions are written down before the outcome is known, then resolved and scored (Brier score).
A13: Reports - the ID system. Every news story or official statement gets its own report ID (R0001...) and points to exactly one event ID. Three outlets covering one attack = three reports, one event. Merged duplicates: #76 into #75, #49 into #50, #29 into #28; their reports now point to the surviving event.
A14: Review Queue - pairs of events that might be the same event logged twice, plus new stories waiting for a human to confirm which event they belong to. The matcher is right only about half the time on headlines, so a person makes the call.
... A38: Compiled: 2026-10-28. Sources are cited per row; see Event Log column J. Rows 83-86 were added by a live scanner test (Sept 27-29). Rows 90-105 were added on Oct 11 from credible-outlet research covering Oct 2-11 (no US/Israeli strike on Iran and no Iranian strike on a US base was found in that window; the two Houthi rows are context from the separate Saudi-Houthi front). Rows 106-115 were added by the weekly agent on Oct 19 (Oct 12-18 news, plus catch-up rows for Oct 6 and Oct 8); again no US strike on Iranian territory and no Iranian strike on US forces was found, while attacks on shipping hit a record. Rows 87-89 were added by a live matcher test on genuinely new Oct 1 news - the matcher correctly classified the sanctions and diplomatic-statement rows; it fell back to a generic 'Military/Property' guess on the naval force-posture row since that's a troop deployment, not a strike, and the keyword rules don't have a dedicated bucket for that yet. Source audit: 2 events are still Pending credible sourcing and 4 are Not supported as logged (including #76, a confirmed duplicate of #75); treat those rows, and the Partly verified rows that rest on one side's claims, as leads, not findings.

Sheet Event Log
A1: ID | B1: Date | C1: Actor | D1: Action Type | E1: Target | F1: Detail | G1: Trigger ID | H1: Severity / Casualties | I1: Confidence | J1: Source (credible outlets only) | K1: Source Check | L1: Audit note | M1: Kind of act | N1: Reports | O1: Different outlets (independent + official) | P1: Credibility (0-1) | Q1: Used in stats? | R1: War phase | S1: Chain (thread ID) | T1: War intensity (14 days before)
A2: 1 | B2: 46080 | C2: US | D2: Authorization | E2: Iran | F2: Trump authorizes Operation Epic Fury aboard Air Force One | H2: n/a | I2: High | J2: AP 2026-03-02 | K2: Verified | M2: Diplomatic | N2: 2 | O2: 1 | P2: 0.8 | Q2: Yes | R2: Pre-war standoff | T2: Quiet (0 pts)
A3: 2 | B3: 46081 | C3: US/Israel | D3: Strike (war start) | E3: Iran | F3: Operation Epic Fury opens: Pentagon says 1,000+ targets hit in the first 24 hours; Khamenei and ~40 senior officials killed; a strike near Minab hits a girls' school | H3: Khamenei + ~40 senior officials killed (AP). Minab school: Iranian authorities say at least 175 killed (AP); Minab mayor says 168 (NBC) - Iranian figures; no nation has claimed the strike (AP) | I3: High | J3: AP 2026-03-02; AP 2026-03-04; NBC News 2026-03-03 | K3: Corrected | L3: School toll is 168-175 (Iranian figures), not 148-168. '~900 strikes in 12 hrs' was a US-only figure from an unnamed official (via Fox), so it was dropped for the Pentagon's 1,000+ in 24 hrs. | M3: Kinetic | N3: 3 | O3: 2 | P3: 0.96 | Q3: Yes | R3: Open war | S3: T01 | T3: Quiet (0 pts)
A4: 3 | B4: 46081 | C4: US | D4: Strike | E4: Iran | F4: US strikes hit Iran's navy from the first hours: drone carrier Shahid Bagheri attacked (CENTCOM); Bayandor and Naghdi reported sunk at Konarak (The War Zone) | G4: 2 | H4: Only Shahid Bagheri confirmed hit by CENTCOM; Bayandor/Naghdi sinking per The War Zone, undated; Trump and CENTCOM claimed larger totals | I4: High | J4: USNI News 2026-03-02; The War Zone 2026-03-02; Defense News 2026-03-01 | K4: Corrected | L4: First draft said three ships sunk Feb 28. Credible outlets support 'struck', with only some sinkings reported. | M4: Kinetic | N4: 3 | O4: 3 | P4: 0.99 | Q4: Yes | R4: Open war | S4: T01 | T4: Quiet (0 pts)
A5: 4 | B5: 46081 | C5: Iran | D5: Blockade (de facto) | E5: Strait of Hormuz | F5: IRGC radios ships on VHF that 'no ship is allowed to pass'; Iran does not formally confirm a closure order (Reuters, citing UKMTO and EU Aspides); IRGC-linked Tasnim says the Strait is shut | G5: 2 | H5: Reuters/Kpler: only 105 crossings Mar 1-18 vs ~120/day normal (>95% drop) | I5: High | J5: Reuters 2026-02-28; Reuters 2026-03-19 | K5: Corrected | L5: No formal IRGC declaration found; the '~70% drop' figure was not found and was replaced with Reuters/Kpler data. | M5: Maritime | N5: 2 | O5: 1 | P5: 0.8 | Q5: Yes | R5: Open war | S5: T01 | T5: Quiet (0 pts)
A6: 5 | B6: 46081 | C6: Iran | D6: Retaliation strike | E6: Israel/Gulf | F6: Iran fires missiles at Israel, Kuwait and other Gulf targets; a missile hits a residential block in Tel Aviv; Kuwait International Airport is hit by a drone | G6: 2 | H6: Tel Aviv: 1 killed, 27 injured (Times of Israel); Kuwait airport: minor injuries to staff | I6: Medium | J6: Times of Israel 2026-03-01; Al Jazeera 2026-02-28 | K6: Partly verified | L6: Tel Aviv casualty figures confirmed by Times of Israel (an Israeli outlet; its own pieces vary between 20 and 27 injured). The operation name 'True Promise IV' and the '49 intercepted over Jordan' detail were not found in any allowed outlet and were dropped from the wording. | M6: Kinetic | N6: 3 | O6: 2 | P6: 0.77 | Q6: Yes | R6: Open war | S6: T01 | T6: Quiet (0 pts)
A7: 6 | B7: 46082 | C7: Iran | D7: Retaliation strike | E7: Jordan/Gulf | F7: Iranian strikes on US/allied radar and base sites across the Gulf and Jordan; one THAAD AN/TPY-2 radar in Jordan 'apparently destroyed'; strikes on Manama, Kuwait airport, Abu Dhabi airport and Erbil reported the same day | G7: 2 | H7: One radar (Jordan) apparently destroyed per CNN satellite-image analysis; The War Zone says it 'appears' destroyed; no US confirmation. UAE and Saudi radar damage unclear | I7: Medium | J7: CNN n.d.; The War Zone 2026-03-07; Al Jazeera 2026-03-01 | K7: Partly verified | L7: 'Destroyed' applies to one radar only and rests on imagery analysis, not a US statement. Manama, Kuwait airport, Abu Dhabi airport and Erbil are confirmed by Al Jazeera; Riyadh was not found in the sources read. | M7: Kinetic | N7: 3 | O7: 3 | P7: 0.79 | Q7: Yes | R7: Open war | S7: T01 | T7: High (13 pts)
A8: 7 | B8: 46082 | C8: Iran | D8: Retaliation strike | E8: Kuwait | F8: Strike on a makeshift operations center at the port of Shuaiba, Kuwait | H8: 6 US killed - the first US combat deaths of the war (CENTCOM, AP, CNN) | I8: High | J8: CNN 2026-03-02; AP 2026-03-02 | K8: Corrected | L8: 'Camp Arifjan' is not supported by the retrieved reporting and was dropped. | M8: Kinetic | N8: 2 | O8: 2 | P8: 0.96 | Q8: Yes | R8: Open war | T8: High (13 pts)
A9: 8 | B9: 46081 | C9: US | D9: Strike | E9: Iran | F9: CENTCOM says the Iranian frigate Jamaran was struck at Chabahar at the start of Epic Fury and is 'sinking'; Makran struck at Bandar Abbas (USNI imagery), sinking not confirmed | H9: 1 frigate sinking per CENTCOM; 1 damaged | I9: High | J9: AFP 2026-03-01; USNI News 2026-03-02; The War Zone 2026-03-02 | K9: Corrected | L9: Mar 1 was the CENTCOM report date; the Jamaran strike was Feb 28. Makran sinking is unconfirmed. | M9: Kinetic | N9: 3 | O9: 3 | P9: 0.99 | Q9: Yes | R9: Open war | T9: Quiet (0 pts)
A10: 9 | B10: 46083 | C10: Iran | D10: Retaliation strike | E10: Bahrain/Kuwait | F10: Tanker Stena Imperative hit by suspected Iranian projectiles at a Bahrain port; smoke near the US embassy in Kuwait reported by a witness | H10: USNI: 1 shipyard worker killed and 2 injured ashore at the Bahrain port; crew unhurt. A strike on the Kuwait embassy itself is not confirmed | I10: Medium | J10: USNI News 2026-03-02; Al Jazeera 2026-03-02 | K10: Partly verified | L10: The '1 killed, 2 injured' figure belongs to the Bahrain port incident only. Attribution is 'suspected' Iranian (USNI). 'US embassy Kuwait struck' rested on a witness seeing smoke. | M10: Kinetic | N10: 2 | O10: 2 | P10: 0.77 | Q10: Yes | R10: Open war | T10: High (19 pts)
A11: 10 | B11: 46084 | C11: Israel (IDF) | D11: Strike | E11: Iran | F11: IDF says it struck Iran's Supreme National Security Council complex in Tehran (Mar 2-3) and destroyed a secret underground site on Tehran's outskirts where Iran moved its nuclear work (IDF claim) | H11: n/a - all details are IDF claims; site name spelled 'Minzadehei' by Times of Israel | I11: Medium | J11: Times of Israel 2026-03-04 | K11: Partly verified | L11: Attributed to Israel, not the US. The IDF claims come via Times of Israel. The Expediency Council building appears only in Iran International (not an allowed outlet), so it is not claimed here. | M11: Kinetic | N11: 1 | O11: 1 | P11: 0.64 | Q11: Yes - use with caution | R11: Open war | S11: T02 | T11: High (23 pts)
A12: 11 | B12: 46084 | C12: Iran | D12: Retaliation strike | E12: Saudi Arabia | F12: Two Iranian drones hit the US embassy in Riyadh; limited fire and minor damage per Saudi Defense Ministry (AP) | G12: 10 | H12: No casualties reported | I12: High | J12: AP 2026-03-03 | K12: Corrected | L12: 'CIA annex' is not in the AP reporting and was dropped. Exact date unconfirmed (AP page dated Mar 2-3). | M12: Kinetic | N12: 1 | O12: 1 | P12: 0.8 | Q12: Yes | R12: Open war | S12: T02 | T12: High (23 pts)
A13: 12 | B13: 46084 | C13: Iran | D13: Retaliation strike | E13: Qatar/Saudi | F13: Iranian missile hits the US base at Al Udeid, Qatar (Mar 3); separately a drone attack on Saudi Aramco's Ras Tanura refinery causes a precautionary shutdown (Mar 2, Iran-attributed) | H13: Al Udeid: 2 missiles launched, 1 intercepted, 1 struck the base, no casualties (Qatar Defense Ministry). Ras Tanura: fire from drone-interception debris, some operations halted, no injuries (Saudi energy ministry / SPA) | I13: High | J13: Times of Israel 2026-03-03; AFP 2026-03-02 | K13: Corrected | L13: The first draft lumped two events onto Mar 4. Al Udeid was hit Mar 3; Ras Tanura Mar 2. Iran has denied attacking Aramco, so that attribution rests on Gulf-state sources. | M13: Kinetic | N13: 2 | O13: 2 | P13: 0.93 | Q13: Yes | R13: Open war | T13: High (23 pts)
A14: 13 | B14: 46085 | C14: US | D14: Strike | E14: Iran | F14: A US submarine sinks IRIS Dena ~40nm off Sri Lanka (reported as USS Charlotte by CBS citing unnamed officials; the Pentagon did not name it) | H14: Sri Lankan navy: 87 bodies recovered, 32 rescued (Al Jazeera). Iran's army later claimed 104 killed (Reuters, Mar 8) - a claim | I14: High | J14: Al Jazeera 2026-03-04; Reuters 2026-03-08; Stars and Stripes 2026-07-22 | K14: Corrected | L14: '104 killed, 32 wounded' is an Iranian claim; Sri Lanka reported 87 bodies and 32 rescued. | M14: Kinetic | N14: 3 | O14: 3 | P14: 0.99 | Q14: Yes | R14: Open war | T14: High (29 pts)
A15: 14 | B15: 46091 | C15: Iran | D15: Blockade escalation (mine-laying alleged) | E15: Strait of Hormuz | F15: CENTCOM says US forces destroyed 16 Iranian minelayers near Hormuz on Mar 10; Trump said the US had 'no reports' of mines being laid. Pentagon: Iranian ballistic-missile launches down ~90%, drones ~83% | H15: 16 minelayers claimed destroyed by CENTCOM the same day | I15: High | J15: Reuters 2026-03-11; PBS NewsHour 2026-03-10; CBS News 2026-03-23 | K15: Corrected | L15: Minelayers were claimed destroyed the same day, not later. The '~92%' figure looks like Israel's interception rate, not the fall in Iranian launches. | M15: Maritime | N15: 3 | O15: 3 | P15: 0.99 | Q15: Yes | R15: Open war | T15: High (33 pts)
A16: 15 | B16: 46102 | C16: US | D16: Strike | E16: Strait of Hormuz | F16: CENTCOM (Adm. Cooper, Mar 21) says the US has struck 8,000+ targets, including 130 Iranian vessels, since Feb 28. Iran's Tasnim says at least 16 cargo vessels burned at Bandar Lengeh/Kong after a US-Israeli attack (Mar 20) | H16: 8,000 targets / 130 vessels are CENTCOM claims for the whole war to date; the 16 burned boats are an Iranian claim and Iran calls them civilian cargo boats | I16: High | J16: Stars and Stripes 2026-03-21; AFP 2026-03-20 | K16: Corrected | L16: This was not a campaign that 'began Mar 19': the figures cover the war so far. Re-dated to the Mar 21 CENTCOM briefing. | M16: Kinetic | N16: 2 | O16: 2 | P16: 0.96 | Q16: Yes | R16: Open war | T16: Low (1 pts)
A17: 16 | B17: 46102 | C17: US/Israel (alleged) | D17: Strike (alleged) | E17: Iran | F17: Iran reports an attack on Natanz and blames the US and Israel; the Israeli military denied involvement and the IAEA saw no rise in off-site radiation | H17: n/a - no casualty or damage figures from credible outlets | I17: High | J17: AFP 2026-03-21; AP 2026-03-21; Al Arabiya 2026-03-21 | K17: Corrected | L17: No allowed outlet says this was a US bunker-buster strike; it is confirmed only as Iran's report. Pair 3 rests on Iran treating it as the trigger. | M17: Kinetic | N17: 3 | O17: 3 | P17: 0.98 | Q17: Yes | R17: Open war | S17: T03 | T17: Low (1 pts)
A18: 17 | B18: 46102 | C18: Iran | D18: Retaliation strike | E18: Israel | F18: Iran strikes toward Dimona and Arad and calls it a 'response' to Natanz; Iran did not claim to target the Negev research center | G18: 16 | H18: No deaths; at least 180 wounded (Israel's Health Ministry, via Al Jazeera) | I18: High | J18: AFP 2026-03-21; Al Jazeera 2026-03-21; Euronews 2026-03-22 | K18: Corrected | L18: Wounded count is at least 180, not 175; Iran framed it as a response to Natanz, not as an attack on the research center. | M18: Kinetic | N18: 3 | O18: 3 | P18: 0.98 | Q18: Yes | R18: Open war | S18: T03 | T18: Low (1 pts)
A19: 18 | B19: 46102 | C19: US | D19: Ultimatum | E19: Iran | F19: Trump: 48-hour ultimatum to reopen Strait or face power-plant strikes | H19: n/a | I19: High | J19: Al Jazeera 2026-03-22; Axios 2026-03-22 | K19: Verified | M19: Diplomatic | N19: 2 | O19: 2 | P19: 0.96 | Q19: Yes | R19: Open war | T19: Low (1 pts)
A20: 19 | B20: 46105 | C20: US | D20: Diplomatic proposal | E20: Iran | F20: US 15-point ceasefire plan is passed to Iran through Pakistani intermediaries (AP) | H20: Iran rejected it and offered a counter-plan (AP) | I20: High | J20: AP 2026-03-25; Al Jazeera 2026-04-06 | K20: Corrected | L20: Delivered via Pakistan on or before Mar 24; Mar 25 was the AP publication date. | M20: Diplomatic | N20: 2 | O20: 2 | P20: 0.96 | Q20: Yes | R20: Open war | T20: Medium (7 pts)
A21: 20 | B21: 46107 | C21: Israel | D21: Assassination strike | E21: Iran | F21: Israel says it killed IRGC Navy commander Tangsiri and the IRGC Navy's intelligence chief Rezaei in Bandar Abbas (Israeli claim, Mar 26); Iran confirmed Tangsiri's death on Mar 30 | H21: Tangsiri's death confirmed by the IRGC Mar 30; no Iranian confirmation of Rezaei found (Al Jazeera, AFP, AP) | I21: High | J21: Al Jazeera 2026-03-26; AFP 2026-03-26; AP 2026-03-30 | K21: Corrected | L21: Rezaei is the IRGC Navy's intelligence chief, not Iran's national intelligence chief. 'Blockade architect' label dropped as unverified. | M21: Kinetic | N21: 3 | O21: 3 | P21: 0.99 | Q21: Yes | R21: Open war | S21: T04 | T21: Medium (6 pts)
A22: 21 | B22: 46108 | C22: Iran | D22: Retaliation strike | E22: Saudi Arabia | F22: Strikes Prince Sultan Air Base | G22: 20 | H22: At least 15 US troops wounded, 5 seriously (AP, NPR, Al Jazeera); multiple KC-135 tankers damaged; E-3 AWACS damaged per unnamed sources (WSJ via Al Jazeera) | I22: High | J22: AP 2026-03-27; NPR 2026-03-28; Al Jazeera 2026-03-29 | K22: Corrected | L22: Credible outlets say at least 15 wounded; '29' looks like a cumulative count. | M22: Kinetic | N22: 3 | O22: 3 | P22: 0.99 | Q22: Yes | R22: Open war | S22: T04 | T22: Medium (8 pts)
A23: 22 | B23: 46108 | C23: Iran | D23: Blockade escalation | E23: Strait of Hormuz | F23: IRGC statement bans shipping to/from ports of countries aligned with the US/Israel (reported via Iranian state media; not confirmed by an allowed outlet). Al Jazeera says the Strait was already declared closed on Mar 2 | H23: The '20,000 mariners / 2,000 ships' figure is an IMO number from Mar 25, before this date | I23: Low | J23: Al Jazeera 2026-03-16 | K23: Not supported | L23: Not a new 'total closure': Al Jazeera (Mar 16) says the Strait was declared closed Mar 2. The Mar 27 statement is sourced only to Iranian state media via non-allowed outlets. | M23: Maritime | N23: 1 | O23: 1 | P23: 0.2 | Q23: No - credibility below 0.50 | R23: Open war | T23: Medium (8 pts)
A24: 23 | B24: 46112 | C24: US | D24: Strike | E24: Iran | F24: Joint Chiefs Chairman Caine announces the first overland B-52 missions (NYT, Mar 31); strikes on an Isfahan ammunition depot reported separately by the WSJ (not read directly) | H24: n/a | I24: High | J24: The New York Times 2026-03-31 | K24: Corrected | L24: Mar 31 is the announcement date. No outlet read ties the B-52s to Isfahan or says when the flights began. | M24: Kinetic | N24: 1 | O24: 1 | P24: 0.8 | Q24: Yes | R24: Open war | T24: Medium (10 pts)
A25: 24 | B25: 46112 | C25: Pakistan/China | D25: Diplomatic proposal | E25: Iran/US | F25: China-Pakistan '5-point initiative' ceasefire proposal | H25: n/a | I25: High | J25: Axios 2026-03-31 | K25: Verified | M25: Diplomatic | N25: 1 | O25: 1 | P25: 0.8 | Q25: Yes | R25: Open war | T25: Medium (10 pts)
A26: 25 | B26: 46114 | C26: US | D26: Strike | E26: Iran | F26: Destroys B1 bridge (Tehran-Karaj) during a family holiday gathering below | H26: 8 killed, 95 wounded per Iran's Alborz deputy governor (AFP; not independently verified); Iranian state TV first reported 2 (Al Jazeera headline: 2 killed) | I26: High | J26: The War Zone 2026-04-02; AFP 2026-04-03; Al Jazeera 2026-04-06 | K26: Verified | L26: Casualty figures are Iranian claims and vary by outlet. | M26: Kinetic | N26: 3 | O26: 3 | P26: 0.99 | Q26: Yes | R26: Open war | T26: High (12 pts)
A27: 26 | B27: 46115 | C27: Iran | D27: Air defense | E27: US | F27: Iran shoots down a US F-15E over Iran (ABC); an A-10 is hit separately and crashes in an allied country, its pilot rescued | H27: F-15E: one crew member rescued, the other's status unknown when ABC reported on Apr 4; two rescue helicopters hit but landed safely | I27: High | J27: ABC News 2026-04-04 | K27: Corrected | L27: 'Both crews rescued' is not confirmed by an allowed outlet; the A-10 did not go down over Iran. | M27: Kinetic | N27: 1 | O27: 1 | P27: 0.8 | Q27: Yes | R27: Open war | T27: High (16 pts)
A28: 27 | B28: 46118 | C28: Pakistan | D28: Diplomatic proposal | E28: Iran/US | F28: Pakistan-mediated 45-day ceasefire framework; Iran says it will not reopen the Strait for a temporary ceasefire and sends a 10-point response (Al Jazeera, Reuters) | H28: Iran did not accept; counter-proposal sent | I28: High | J28: Al Jazeera 2026-04-06; Reuters 2026-04-06 | K28: Corrected | L28: Date is Apr 6, not Apr 5. Iran did not flatly reject talks. | M28: Diplomatic | N28: 3 | O28: 2 | P28: 0.96 | Q28: Yes | R28: Open war | T28: High (12 pts)
A29: 28 | B29: 46119 | C29: US/Iran | D29: Ceasefire announcement | E29: - | F29: Trump announces a two-week ceasefire on Truth Social after Pakistan's PM Sharif asks him to extend his deadline; Iran's Supreme National Security Council accepts (Reuters, AP). Apr 7 US time / Apr 8 Gulf time | H29: n/a | I29: High | J29: Reuters 2026-04-07; AP 2026-04-07; AP 2026-04-08 | K29: Corrected | L29: No credible outlet names VP Vance as the channel; Pakistan's leaders are named. | M29: Diplomatic | N29: 6 | O29: 2 | P29: 0.96 | Q29: Yes | R29: Open war | S29: T05 | T29: High (12 pts)
A30: 29 | B30: 46120 | C30: US/Iran/Pakistan | D30: Ceasefire signed | E30: - | F30: UNSUPPORTED AS LOGGED: no credible outlet reports a formally signed ceasefire with these terms. AP describes the Apr 7-8 ceasefire as built on a disputed 10-point Iranian plan with differing Farsi and English versions. Likely a duplicate of #28 | H30: n/a | I30: Merged | J30: AP 2026-04-07; AP 2026-04-08; Reuters 2026-04-07 | K30: Not supported | L30: Searched; AP and Reuters report no signed document and none of the listed terms (sanctions relief, frozen-asset release). Row kept only because other rows point to it. Merged into #28 (same Apr 7-8 ceasefire; no signed document or listed terms were ever reported). | M30: Diplomatic | N30: 0 | O30: 0 | Q30: No - merged duplicate | R30: Fragile ceasefire | T30: High (12 pts)
A31: 30 | B31: 46120 | C31: Israel | D31: Ceasefire violation | E31: Lebanon | F31: Israel strikes 100+ targets across Beirut, southern Lebanon and the Bekaa in about 10 minutes, within hours of the ceasefire (AP) | G31: 28 | H31: Lebanon's health ministry: at least 112 killed in the first count, later 182 (AP) | I31: High | J31: AP 2026-04-08; Reuters 2026-04-09; Al Jazeera 2026-04-08 | K31: Verified | L31: 'Operation Eternal Darkness' name appears only in Israeli outlets (ynet, i24), not in allowed ones, so it was dropped. | M31: Kinetic | N31: 3 | O31: 3 | P31: 0.99 | Q31: Yes | R31: Fragile ceasefire | S31: T05 | T31: High (12 pts)
A32: 31 | B32: 46120 | C32: Iran | D32: Blockade re-escalation | E32: Strait of Hormuz | F32: Iran restricts/resumes blockade, citing the Lebanon strikes as a ceasefire violation | G32: 30 | H32: n/a | I32: High | J32: AP 2026-04-08; The War Zone 2026-04-09; Reuters 2026-04-09 | K32: Verified | M32: Maritime | N32: 3 | O32: 3 | P32: 0.99 | Q32: Yes | R32: Fragile ceasefire | S32: T05 | T32: High (12 pts)
A33: 32 | B33: 46120 | C33: UAE | D33: Strike (covert) | E33: Iran | F33: UAE strikes Lavan Island oil refinery (only revealed later via WSJ/Bloomberg, May 11) | H33: Major fire at the refinery; WSJ reportedly said a significant part of capacity was knocked out for several months (seen via a secondary summary only) | I33: Medium | J33: Times of Israel 2026-04-08; Times of Israel 2026-05-12; Times of Israel 2026-05-30 | K33: Partly verified | L33: Event confirmed; details revealed May 11-12 (WSJ/Bloomberg). 'Crippled for months' is stronger than what could be read. | M33: Kinetic | N33: 4 | O33: 1 | P33: 0.64 | Q33: Yes - use with caution | R33: Fragile ceasefire | T33: High (12 pts)
A34: 33 | B34: 46123 | C34: US | D34: Blockade-adjacent action | E34: Strait of Hormuz | F34: US Navy destroyers transit the Strait for the first time since the war began (mine-clearance framing) | H34: Iran calls it a ceasefire violation | I34: High | J34: USNI News 2026-04-11; Axios 2026-04-11 | K34: Verified | M34: Maritime | N34: 2 | O34: 2 | P34: 0.96 | Q34: Yes | R34: Fragile ceasefire | T34: High (15 pts)
A35: 34 | B35: 46123 | C35: US/Iran/Pakistan | D35: Diplomatic talks | E35: - | F35: Islamabad Talks: 21 hours of negotiation, collapse without agreement | H35: Failed - Araghchi: 'inches away' but accused US of moving goalposts | I35: High | J35: AP 2026-04-11; Axios 2026-04-12; Times of Israel 2026-04-12 | K35: Verified | M35: Diplomatic | N35: 3 | O35: 3 | P35: 0.99 | Q35: Yes | R35: Fragile ceasefire | S35: T06 | T35: High (15 pts)
A36: 35 | B36: 46125 | C36: US | D36: Blockade start | E36: Iran | F36: US naval blockade of Iran begins | G36: 34 | H36: n/a | I36: High | J36: USNI News 2026-04-11; Axios 2026-04-12; Al Jazeera 2026-04-13 | K36: Verified | M36: Maritime | N36: 3 | O36: 3 | P36: 0.99 | Q36: Yes | R36: Fragile ceasefire | S36: T06 | T36: High (16 pts)
A37: 36 | B37: 46130 | C37: Iran | D37: Blockade re-escalation | E37: Strait of Hormuz | F37: Iran announces the Strait closed again, citing continuation of the US blockade | G37: 35 | H37: n/a | I37: High | J37: AP 2026-04-18 | K37: Verified | M37: Maritime | N37: 1 | O37: 1 | P37: 0.8 | Q37: Yes | R37: Fragile ceasefire | S37: T06 | T37: Medium (9 pts)
A38: 37 | B38: 46131 | C38: US | D38: Seizure | E38: Iranian shipping | F38: US disables the Iranian container ship Touska with gunfire from USS Spruance (Apr 19, USNI); tankers Tifani and Majestic X interdicted in the Indian Ocean around Apr 22-24 (dates not confirmed by an allowed outlet) | H38: 3 vessels | I38: High | J38: USNI News 2026-04-19 | K38: Corrected | L38: Touska is a container ship, not a tanker. Tifani/Majestic X dates conflict across outlets (Apr 22-24). | M38: Maritime | N38: 1 | O38: 1 | P38: 0.8 | Q38: Yes | R38: Fragile ceasefire | S38: T07 | T38: Medium (10 pts)
A39: 38 | B39: 46134 | C39: Iran | D39: Seizure (retaliation) | E39: Shipping | F39: IRGC seizes container ships MSC Epaminondas and MSC Francesca | G39: 37 | H39: No casualties (AFP, Reuters) | I39: High | J39: AFP 2026-04-22; Reuters 2026-04-23 | K39: Verified | L39: Reuters ties it to the US seizure of the Touska; the IRGC's own stated reasons were blockade and permit violations. | M39: Maritime | N39: 2 | O39: 2 | P39: 0.96 | Q39: Yes | R39: Fragile ceasefire | S39: T07 | T39: Medium (11 pts)
A40: 39 | B40: 46143 | C40: Iran | D40: Incursion | E40: Kuwait | F40: Bubiyan Island raid attempt: 6 IRGC troops by fishing boat, 4 detained, 2 escape; Kuwait announced it on May 12 | H40: 1 injured: a 'security official' (AP) or 'service member' (Al Jazeera); Iran says it was a navigation error | I40: High | J40: Al Jazeera 2026-05-12; AP 2026-05-12 | K40: Verified | L40: Incident May 1, announced May 12. Injured person is described differently by AP and Al Jazeera. | M40: Kinetic | N40: 2 | O40: 2 | P40: 0.96 | Q40: Yes | R40: Fragile ceasefire | T40: Low (3 pts)
A41: 40 | B41: 46146 | C41: US | D41: Operation | E41: Strait of Hormuz | F41: Operation Project Freedom: announced May 3, began May 4; Navy escort mission for stranded ships; US says six boats sunk (Trump said seven); pause announced May 5 US time (May 6 Gulf time) | H41: n/a | I41: High | J41: Al Jazeera 2026-05-03; Reuters 2026-05-04; Al Jazeera 2026-05-06 | K41: Corrected | L41: Operations began May 4 (announced May 3); pause announced May 5 US time. US says six boats sunk, Trump said seven. | M41: Kinetic | N41: 3 | O41: 2 | P41: 0.96 | Q41: Yes | R41: Fragile ceasefire | T41: Low (3 pts)
A42: 41 | B42: 46149 | C42: Iran | D42: Strike | E42: US Navy | F42: Missiles, drones and small boats attack 3 US destroyers transiting the Strait | H42: No casualties; none of the 3 destroyers (Truxtun, Rafael Peralta, Mason) was struck (CENTCOM) | I42: High | J42: CNN 2026-05-07; The War Zone 2026-05-07 | K42: Verified | L42: Confirmed. US vs Gulf time can put this on May 7 or 8. | M42: Kinetic | N42: 2 | O42: 2 | P42: 0.96 | Q42: Yes | R42: Fragile ceasefire | S42: T08 | T42: Low (4 pts)
A43: 42 | B43: 46149 | C43: US | D43: Retaliation strike | E43: Iran | F43: US strikes sites near Bandar Abbas and Qeshm Island (CENTCOM did not name the IRGC) | G43: 41 | H43: n/a | I43: High | J43: CNN 2026-05-07; The War Zone 2026-05-07 | K43: Verified | L43: Confirmed; the 'IRGC facilities and missile sites' wording was not supported. | M43: Kinetic | N43: 2 | O43: 2 | P43: 0.96 | Q43: Yes | R43: Fragile ceasefire | S43: T08 | T43: Low (4 pts)
A44: 43 | B44: 46181 | C44: US/Iran | D44: Ceasefire (restored) | E44: - | F44: Iran agrees to halt attacks on Israel after the two traded fire on Jun 6-7, the first exchange since the April ceasefire | H44: n/a | I44: High | J44: NPR 2026-06-08 | K44: Corrected | L44: Corrected (NPR, Jun 8): the old text said Israel and Iran 'had not exchanged fire since'; in fact they traded fire Jun 6-7 and Iran then agreed to stop. | M44: Diplomatic | N44: 1 | O44: 1 | P44: 0.8 | Q44: Yes | R44: Fragile ceasefire | S44: T09 | T44: Low (2 pts)
A45: 44 | B45: 46181 | C45: Israel | D45: Strike (ceasefire violation) | E45: Iran | F45: Strikes kill members of Iran's air-defense units | G45: 43 | H45: 2+ killed | I45: High | J45: AFP 2026-06-09 | K45: Corrected | L45: Date corrected to Jun 8 (AFP via Al Arabiya, published Jun 9): the Israeli strikes were overnight into Monday Jun 8; Iranian state TV (a claim) said at least 2 air-defense personnel were killed (re-sourced Oct 28). | M45: Kinetic | N45: 1 | O45: 1 | P45: 0.8 | Q45: Yes | R45: Fragile ceasefire | S45: T09 | T45: Low (2 pts)
A46: 45 | B46: 46181 | C46: Iran | D46: Retaliation | E46: US | F46: Downs a US Apache helicopter over the Strait (US says a Shahed drone did it) | G46: 44 | H46: Both crew rescued | I46: High | J46: CBS News 2026-06-09 | K46: Corrected | L46: Date corrected to Jun 8 (CBS, updated Jun 9): the Apache went down Monday Jun 8 and both crew were rescued about two hours later by an unmanned surface drone; CBS sources say a Shahed drone (re-sourced Oct 28). | M46: Kinetic | N46: 1 | O46: 1 | P46: 0.8 | Q46: Yes | R46: Fragile ceasefire | S46: T09 | T46: Low (2 pts)
A47: 46 | B47: 46182 | C47: US | D47: Retaliation strike | E47: Iran | F47: US strikes Iranian air-defense, ground-control and surveillance radar sites near the Strait after Iran downs a US Apache (CENTCOM: 'proportional response') | G47: 45 | H47: No casualties reported | I47: High | J47: NPR 2026-06-09; CENTCOM 2026-06-09 | K47: Corrected | L47: Corrected (NPR, CENTCOM): the named towns (Qeshm, Sirik, Jask, Bandar Abbas) are not in the Jun 9 reports; Al Jazeera's Jun 10 live page puts the next day's strikes at Sirik, Bandar Abbas and Qeshm. | M47: Kinetic | N47: 2 | O47: 2 | P47: 0.93 | Q47: Yes | R47: Fragile ceasefire | S47: T09 | T47: Medium (8 pts)
A48: 47 | B48: 46183 | C48: Iran | D48: Retaliation strike | E48: Jordan/Kuwait/Bahrain | F48: Strikes Muwaffaq Salti AB plus bases in Kuwait and Bahrain | G48: 46 | H48: AP: Jordan shot down 5 missiles aimed at Muwaffaq Salti AB. Axios: a US official counted at least 4 ballistic missiles plus drones across the three countries. IRGC claim of 21 targets is unverified | I48: High | J48: AP 2026-06-10; Axios (Barak Ravid), as summarised on Iran International page 2026-06-10; Petra 2026-06-11 | K48: Verified | L48: Rows 47 and 48 are separate waves, not an overlap. IRGC target claim is unverified. | M48: Kinetic | N48: 3 | O48: 3 | P48: 0.99 | Q48: Yes | R48: Fragile ceasefire | S48: T09 | T48: Medium (10 pts)
A49: 48 | B49: 46184 | C49: Iran | D49: Retaliation strike | E49: Jordan | F49: Iranian missile wave at a Jordan base near Azraq; Jordan says it intercepted all 20 incoming missiles | G49: 47 | H49: Jordan (official statement): 20 missiles intercepted; the IRGC's own claim of 12 is not cited | I49: High | J49: Petra 2026-06-11; AFP 2026-07-09 | K49: Corrected | L49: Only allowed source is Jordan's official statement; the '12 missiles' figure was an IRGC claim. | M49: Kinetic | N49: 2 | O49: 2 | P49: 0.96 | Q49: Yes | R49: Fragile ceasefire | S49: T09 | T49: High (12 pts)
A50: 49 | B50: 46190 | C50: US/Iran | D50: Ceasefire (interim MOU signed) | E50: - | F50: Pakistan's PM announces agreed text of a US-Iran memorandum on Jun 12; Trump and Pezeshkian sign the 14-point interim deal digitally on Jun 17, extending the ceasefire by 60 days (Reuters) | H50: n/a - Iran later said (Aug 12, via Reuters) the interim deal never took effect | I50: Merged | J50: Reuters 2026-06-12; Reuters 2026-06-17; Axios 2026-06-11 | K50: Corrected | L50: 'Terms agreed Jun 12' was only partly right: Jun 12 is when Pakistan announced the text; signing was Jun 17. This overlaps with event #50 (the same deal). Kept separate for now. Merged into #50 (same Jun 17 signing; Jun 12 was only Pakistan's announcement that the text was agreed). | M50: Diplomatic | N50: 0 | O50: 0 | Q50: No - merged duplicate | R50: Fragile ceasefire | T50: High (14 pts)
A51: 50 | B51: 46190 | C51: US/Iran | D51: Ceasefire (interim MOU signed) | E51: - | F51: Trump and Pezeshkian sign a 14-point interim memorandum electronically on Jun 17 (Iran's foreign ministry calls it the 'Islamabad Memorandum of Understanding'): fighting stops on all fronts incl. Lebanon; 60 days to negotiate; the US starts lifting the blockade at once and ends it within 30 days; Iran makes 'best efforts' for free passage through Hormuz; oil-sanctions waivers now, full relief only in a final deal | H51: n/a | I51: High | J51: Al Jazeera 2026-06-17; Al Jazeera 2026-06-18; NPR 2026-06-17; NPR 2026-06-19 | K51: Corrected | L51: Confirmed by Reuters, Al Jazeera and NPR. Earlier wording said it 'ended the blockade and reopened the Strait' outright; it was phased. Iran later said (Aug 12) the deal never took effect. Also covers former row #49: Pakistan announced the agreed text on Jun 12. | M51: Diplomatic | N51: 7 | O51: 4 | P51: 0.99 | Q51: Yes | R51: Fragile ceasefire | S51: T10 | T51: High (14 pts)
A52: 51 | B52: 46191 | C52: US | D52: Blockade end | E52: Iran | F52: US naval blockade of Iran officially ends | G52: 50 | H52: n/a | I52: High | J52: Al Jazeera 2026-06-18 | K52: Verified | M52: Maritime | N52: 1 | O52: 1 | P52: 0.8 | Q52: Yes | R52: Fragile ceasefire | S52: T10 | T52: High (14 pts)
A53: 52 | B53: 46193 | C53: Israel | D53: Ceasefire violation | E53: Lebanon | F53: Israeli strikes in Lebanon continue overnight after an Israel-Hezbollah ceasefire took effect Jun 19 (Reuters, AFP) | H53: 20+ killed (Reuters); AFP: 16 in Nabatieh and 7 near Sidon | I53: High | J53: Reuters 2026-06-20; Reuters 2026-06-19; AFP 2026-06-20 | K53: Corrected | L53: Strikes came overnight into Saturday Jun 20, not Jun 19. | M53: Kinetic | N53: 3 | O53: 2 | P53: 0.96 | Q53: Yes | R53: Fragile ceasefire | S53: T11 | T53: High (15 pts)
A54: 53 | B54: 46193 | C54: Iran | D54: Blockade re-escalation | E54: Strait of Hormuz | F54: Iran claims the Strait closed again, citing Israeli ceasefire violations in Lebanon | G54: 52 | H54: n/a | I54: High | J54: AFP 2026-06-20; Al Jazeera 2026-06-20 | K54: Verified | M54: Maritime | N54: 2 | O54: 2 | P54: 0.93 | Q54: Yes | R54: Fragile ceasefire | S54: T11 | T54: High (15 pts)
A55: 54 | B55: 46198 | C55: Iran | D55: MOU violation | E55: Shipping | F55: Iranian drones attack the container ship Ever Lovely near Oman in the Strait; Trump calls it a 'foolish violation' of the Jun 17 memorandum | H55: No injuries | I55: High | J55: Al Jazeera 2026-06-26 | K55: Verified | L55: Confirmed (Al Jazeera, Jun 26): four one-way attack drones per Trump, one hit the upper deck; no crew hurt. | M55: Maritime | N55: 1 | O55: 1 | P55: 0.8 | Q55: Yes | R55: Fragile ceasefire | S55: T12 | T55: Medium (8 pts)
A56: 55 | B56: 46199 | C56: US | D56: Retaliation strike | E56: Iran | F56: ~1 hour of retaliatory strikes on missile/drone sites and coastal radar | G56: 54 | H56: n/a | I56: High | J56: NPR 2026-06-27; Al Jazeera 2026-06-28; CENTCOM 2026-06-27 | K56: Verified | L56: Date confirmed: NPR (AP) and Al Jazeera put the roughly one-hour US strike on Fri Jun 26, after a projectile hit a container ship off Oman on Jun 25. A separate, larger CENTCOM round of about 10 targets followed on Jun 27 after the tanker Kiku was hit. | M56: Kinetic | N56: 3 | O56: 3 | P56: 0.99 | Q56: Yes | R56: Fragile ceasefire | S56: T12 | T56: Medium (7 pts)
A57: 56 | B57: 46200 | C57: Iran | D57: Retaliation strike | E57: Bahrain/Kuwait | F57: Tanker Kiku hit by a one-way drone near Hormuz (Jun 27, per CENTCOM; Iran has not confirmed); overnight Jun 27-28 the IRGC fires drones and missiles at Kuwait (intercepted) and Bahrain | G57: 55 | H57: Kuwait: intercepted. Bahrain: AP gives only its condemnation. No casualties found | I57: High | J57: AP 2026-06-28; Al Jazeera 2026-06-28; CENTCOM 2026-06-27 | K57: Corrected | L57: Split into tanker (Jun 27) and Gulf fire (overnight Jun 27-28). A pause afterwards is single-source: Axios (Jun 29) says both sides agreed to halt attacks, while AP's Jun 28 report mentions no pause and says the exchange strained the interim deal. | M57: Kinetic | N57: 4 | O57: 3 | P57: 0.99 | Q57: Yes | R57: Fragile ceasefire | S57: T12 | T57: Medium (9 pts)
A58: 57 | B58: 46210 | C58: Iran | D58: MOU violation (major) | E58: Shipping | F58: Strikes three vessels in the Strait - second, larger MOU violation | H58: Significant damage, no casualties (US official via Axios); no one claimed the attacks (Reuters) | I58: High | J58: Axios 2026-07-07; Reuters 2026-07-07 | K58: Corrected | L58: Confirmed (Axios, Reuters): at least three commercial ships hit Jul 6-7. The old '49 to 25 vessels a day' traffic figure was not found in an allowed outlet and was dropped. | M58: Maritime | N58: 2 | O58: 2 | P58: 0.96 | Q58: Yes | R58: Fragile ceasefire | S58: T13 | T58: Low (5 pts)
A59: 58 | B59: 46210 | C59: US | D59: Sanctions response | E59: Iran | F59: Treasury withdraws the general license allowing Iranian oil sales (wind-down to Jul 17) after the tanker attacks | G59: 57 | H59: n/a | I59: High | J59: Reuters 2026-07-07 | K59: Verified | L59: Confirmed (Reuters via Honolulu Star-Advertiser, Jul 7). | M59: Sanctions | N59: 1 | O59: 1 | P59: 0.8 | Q59: Yes | R59: Fragile ceasefire | S59: T13 | T59: Low (5 pts)
A60: 59 | B60: 46210 | C60: US | D60: Ceasefire declared over | E60: - | F60: Trump declares the ceasefire 'over' at the NATO summit | G60: 57 | H60: n/a | I60: High | J60: NPR 2026-07-08 | K60: Verified | L60: Confirmed (NPR, published Jul 8): NPR dates Trump's remark to Tuesday, Jul 7, so the row date was moved from Jul 8 to Jul 7 (review, Oct 22). | M60: Diplomatic | N60: 1 | O60: 1 | P60: 0.8 | Q60: Yes | R60: Fragile ceasefire | S60: T13 | T60: Low (5 pts)
A61: 60 | B61: 46211 | C61: US | D61: Strike (major escalation) | E61: Iran | F61: About 90 targets along Iran's coast (air defenses, coastal surveillance, missile and drone storage, naval and logistics sites), the second night in a row after ~80 on Jul 7 (CENTCOM) | G61: 59 | H61: n/a | I61: High | J61: CENTCOM 2026-07-08; Bloomberg 2026-07-09 | K61: Corrected | L61: Corrected (CENTCOM, Bloomberg): no allowed outlet puts bridges among the Jul 8 targets. The bridge strikes (two bridges in Hormozgan, 3 killed per Iranian state TV) were on Jul 16-17 (AFP), inside the nightly campaign that is excluded from the census. | M61: Kinetic | N61: 2 | O61: 2 | P61: 0.96 | Q61: Yes | R61: Open war | S61: T13 | T61: Medium (6 pts)
A62: 61 | B62: 46212 | C62: Iran | D62: Retaliation strike | E62: Jordan | F62: Iran's IRGC says it fired 10 ballistic missiles at the Azraq base in Jordan (Muwaffaq Salti AB is at Azraq); Jordan says it intercepted 8 | G62: 60 | H62: Jordan: 8 intercepted, falling fragments only, no casualties or material damage (the other 2 are not accounted for) | I62: High | J62: AFP 2026-07-09; Reuters 2026-07-09 | K62: Verified | L62: Confirmed by AFP and Reuters. Neither names Muwaffaq Salti, but it is the air base at Azraq. | M62: Kinetic | N62: 2 | O62: 2 | P62: 0.96 | Q62: Yes | R62: Open war | S62: T13 | T62: Medium (8 pts)
A63: 62 | B63: 46215 | C63: Iran | D63: Retaliation strike (5 countries) | E63: Oman/Qatar/Kuwait/Bahrain/Jordan | F63: Simultaneous strikes framed as retaliation for a '3rd round of US strikes within a week' (~140 sites) | G63: 60 | H63: Qatar: 3 wounded incl. a child | I63: High | J63: Al Jazeera 2026-07-12 | K63: Verified | M63: Kinetic | N63: 1 | O63: 1 | P63: 0.8 | Q63: Yes | R63: Open war | S63: T13 | T63: Low (5 pts)
A64: 63 | B64: 46215 | C64: Iran | D64: Blockade re-escalation | E64: Strait of Hormuz | F64: Declares the Strait 'closed until the end of US interference' | G64: 62 | H64: n/a | I64: High | J64: Al Jazeera 2026-07-12 | K64: Verified | M64: Maritime | N64: 1 | O64: 1 | P64: 0.8 | Q64: Yes | R64: Open war | S64: T13 | T64: Low (5 pts)
A65: 64 | B65: 46217 | C65: Iran | D65: Retaliation strike | E65: Bahrain | F65: IRGC claims strikes on US sites at Juffair, Bahrain (Jul 13) and says it destroyed a Patriot radar and other radars (Jul 14) | H65: IRGC claim only; no US or Bahraini confirmation or damage assessment found | I65: Low | J65: Tasnim 2026-07-14 | K65: Partly verified | L65: Everything about damage is an Iranian claim (Tasnim). Not confirmed by AP, Reuters, AFP or CNN in what was read. | M65: Kinetic | N65: 1 | O65: 0 | P65: 0 | Q65: No - credibility below 0.50 | R65: Open war | T65: Medium (8 pts)
A66: 65 | B66: 46220 | C66: Iran | D66: Retaliation strike | E66: Jordan | F66: Attack on Muwaffaq Salti AB - deadliest Jordan-strike day of the war | H66: 3 US dead: 2 killed in action plus 1 missing, later declared believed killed in action (Army/DoD, Jul 22); 4 medically evacuated | I66: High | J66: AP 2026-07-18; Army.mil 2026-07-22; Stars and Stripes 2026-07-20 | K66: Corrected | L66: Toll is 3 dead, not '2 KIA + 1 missing'. The attack was Fri Jul 17; some outlets say Jul 18. | M66: Kinetic | N66: 3 | O66: 3 | P66: 0.99 | Q66: Yes | R66: Open war | T66: Medium (8 pts)
A67: 66 | B67: 46222 | C67: Iran | D67: Retaliation strike | E67: Jordan | F67: IRGC says ballistic missiles hit US aircraft at Aqaba airport (Jul 19); Jordan says it shot down 3 missiles and a 4th fell in open ground | H67: Damage is an IRGC claim only. Jordan and Israel report no damage or injuries (AFP) | I67: Medium | J67: Times of Israel 2026-07-20; AFP 2026-07-19 | K67: Partly verified | L67: Strike confirmed by AFP. 'King Hussein International Airport' appears in the sources only as 'Aqaba airport'. The US embassy said Aqaba was evacuated over a 'credible threat'; Jordan denied any evacuation. | M67: Kinetic | N67: 3 | O67: 2 | P67: 0.77 | Q67: Yes | R67: Open war | T67: High (12 pts)
A68: 67 | B68: 46223 | C68: Iran | D68: Retaliation strike | E68: Jordan | F68: IRGC claims it destroyed a missile-defense radar and an F-15 at a US base in Jordan (Jul 21). No US or Jordanian confirmation | H68: IRGC claim only | I68: Low | J68: No credible source found (see audit note) | K68: Not supported | L68: The claim exists only in non-allowed relays (Middle East Eye, APA citing Al Jazeera), so nothing here is verified. A different, later claim (Jul 23, AFP) names other equipment; do not conflate. | M68: Kinetic | N68: 0 | O68: 0 | P68: 0 | Q68: No - credibility below 0.50 | R68: Open war | T68: High (14 pts)
A69: 68 | B69: 46253 | C69: Analyst | D69: Strategic assessment | E69: - | F69: Trita Parsi assessment: Iran now believes it holds the military advantage, considers shifting from reaction to offense | H69: Analysis, not an event | I69: High | J69: CNN 2026-08-19 | K69: Verified | L69: Confirmed as published and attributed: Trita Parsi is quoted in a CNN analysis by Tim Lister (Aug 19). It is an opinion, not an event, and was read through a credited republication. | M69: Other | N69: 1 | O69: 1 | P69: 0.8 | Q69: Yes | R69: Low-intensity war | T69: Quiet (0 pts)
A70: 69 | B70: 46259 | C70: US | D70: Mine-clearance | E70: Strait of Hormuz | F70: Mine clearance of the Traffic Separation Scheme; 100+ suspected mines found and removed (Axios: by private contractors; CENTCOM credits Navy divers, SEALs and air power) | H70: n/a | I70: High | J70: Axios 2026-08-25 | K70: Corrected | L70: Axios says private contractors did the removal, not the Navy alone. | M70: Maritime | N70: 1 | O70: 1 | P70: 0.8 | Q70: Yes | R70: Low-intensity war | T70: Quiet (0 pts)
A71: 70 | B71: 46264 | C71: US | D71: Strike | E71: Iran | F71: Strikes 2 IRGC rocket launchers on Larak Island, said to be preparing sea mines | H71: Iranian state media (IRNA, a claim): at least 2 killed and several wounded; no US-confirmed casualty figure (CNN) | I71: High | J71: CNN 2026-08-30 | K71: Corrected | L71: Casualty figure is an Iranian claim. | M71: Kinetic | N71: 1 | O71: 1 | P71: 0.8 | Q71: Yes | R71: Low-intensity war | S71: T14 | T71: Low (1 pts)
A72: 71 | B72: 46265 | C72: Iran | D72: Retaliation strike | E72: Jordan | F72: 'Punishment of the Aggressor': strikes King Hussein AB and Al Azraq AB | G72: 70 | H72: 8 intercepted per Jordan, no injuries (disputed) | I72: High | J72: Al Jazeera 2026-08-30; CBS News None | K72: Verified | M72: Kinetic | N72: 2 | O72: 2 | P72: 0.96 | Q72: Yes | R72: Low-intensity war | S72: T14 | T72: Low (5 pts)
A73: 72 | B73: 46265 | C73: Disputed | D73: Tanker attack (cause disputed) | E73: Strait of Hormuz | F73: Saudi (Bahri) tanker Sidr hit late Aug 31; a second tanker, Senegal Prosperity, reported hit by 3 projectiles the same night. IRGC says mines; CENTCOM calls that false; Saudi Arabia blames Iran; Iran denies | H73: 2 Filipino crew killed (Bahri) | I73: High | J73: CBS News None; Bloomberg 2026-09-01; AFP 2026-09-02 | K73: Corrected | L73: First draft framed this as an accident that undercut the mine-clearance claim and listed '1 tanker damaged'. Credible outlets show a disputed attack with 2 killed. | M73: Maritime | N73: 3 | O73: 3 | P73: 0.99 | Q73: Yes | R73: Low-intensity war | T73: Low (5 pts)
A74: 73 | B74: 46266 | C74: US | D74: Strike | E74: Iran | F74: New strike wave: Kenerak, Bandar Abbas, Qeshm Island | G74: 71 | H74: n/a - trigger: ongoing mine-laying/shipping attacks | I74: High | J74: CENTCOM 2026-09-01; Al Jazeera 2026-09-01; CBS News 2026-09-02 | K74: Verified | M74: Kinetic | N74: 3 | O74: 3 | P74: 0.99 | Q74: Yes | R74: Low-intensity war | S74: T14 | T74: Medium (10 pts)
A75: 74 | B75: 46266 | C75: US | D75: Strike (controversial) | E75: Iran | F75: Kuhestak/Sirik wedding strike, part of the same wave as #73 | G75: 73 | H75: 4-5 killed incl. 2 children, 50+ wounded | I75: High | J75: Al Jazeera 2026-09-02; CBS News 2026-09-02; AFP 2026-09-02 | K75: Verified | M75: Kinetic | N75: 3 | O75: 3 | P75: 0.99 | Q75: Yes | R75: Low-intensity war | S75: T14 | T75: Medium (10 pts)
A76: 75 | B76: 46266 | C76: Iran | D76: Retaliation strike | E76: Jordan | F76: Strikes Camp Titin and Prince Hassan AB | G76: 74 | H76: 'Several aircraft' destroyed, claimed | I76: High | J76: Al Jazeera 2026-09-01; Al Jazeera 2026-09-02; Times of Israel 2026-09-02 | K76: Corrected | L76: Jordan reported the attack early Sep 2 local time (Sep 1 evening US time); date left as logged. The 'several aircraft destroyed' item is an IRGC claim that the US and Jordan denied. Event #76 is a duplicate of this event (two outlets describe one exchange). | M76: Kinetic | N76: 6 | O76: 2 | P76: 0.96 | Q76: Yes | R76: Low-intensity war | S76: T14 | T76: Medium (10 pts)
A77: 76 | B77: 46267 | C77: Iran | D77: Retaliation strike (major) | E77: Jordan | F77: DUPLICATE OF #75: Al Jazeera's Sep 1 and Sep 2 stories describe one Iranian response (Jordan intercepted 10 of 13 missiles). No allowed outlet reports a separate, larger wave on Sep 2 | G77: 75 | H77: n/a | I77: Merged | J77: Al Jazeera 2026-09-01; Al Jazeera 2026-09-02; Times of Israel 2026-09-02 | K77: Not supported | L77: Confirmed duplicate by two independent checks. The 'most extensive since the ceasefire' wording comes from a Persian-language outlet that fails the source standard. Excluded from all statistics. Pair 21 is permanently held out. Merged into #75 (same Sep 1-2 attack on Jordan, reported over two days). | M77: Kinetic | N77: 0 | O77: 0 | Q77: No - merged duplicate | R77: Low-intensity war | T77: High (18 pts)
A78: 77 | B78: 46270 | C78: US | D78: Strike | E78: Iranian shipping | F78: Strikes 3 Iranian crude tankers (MT Kylo and others) | H78: 3 tankers disabled - trigger: IRGC missiles at US warships | I78: High | J78: CENTCOM 2026-09-05 | K78: Verified | M78: Kinetic | N78: 1 | O78: 1 | P78: 0.8 | Q78: Yes | R78: Low-intensity war | T78: High (18 pts)
A79: 78 | B79: 46273 | C79: Iran | D79: Strike | E79: US Navy | F79: IRGC fires ballistic missiles at a US warship for the second time in two days | H79: Evaded, no casualties | I79: High | J79: CENTCOM 2026-09-08; Al Jazeera 2026-09-09; Reuters 2026-09-09 | K79: Verified | L79: Confirmed by CENTCOM's Sep 8 release: the IRGC targeted a US warship with ballistic missiles twice over the previous two days; it evaded both, no one hurt. Exact launch times are not published. | M79: Kinetic | N79: 3 | O79: 3 | P79: 0.99 | Q79: Yes | R79: Low-intensity war | S79: T15 | T79: High (20 pts)
A80: 79 | B80: 46273 | C80: US | D80: Retaliation strike | E80: Iranian shipping | F80: CENTCOM destroys five IRGC crude oil carriers (four in the Gulf of Oman, one near Kharg Island) after the IRGC's missile attempts on a US warship | G80: 78 | H80: 5 tankers destroyed | I80: High | J80: CENTCOM 2026-09-08; Reuters 2026-09-09; Al Jazeera 2026-09-09; CBS News 2026-09-09 | K80: Corrected | L80: Date corrected from Sep 9 to Sep 8 (CENTCOM release, Reuters dateline, Al Jazeera 'late Tuesday'). The 'tanker for tanker' label was not found; Secretary of State Rubio said Iran 'is going to lose tankers'. | M80: Kinetic | N80: 4 | O80: 4 | P80: 0.99 | Q80: Yes | R80: Low-intensity war | S80: T15 | T80: High (20 pts)
A81: 80 | B81: 46274 | C81: Iran | D81: Retaliation strike | E81: Jordan | F81: Strikes Muwaffaq Salti AB: 1 A-10 loses a wing, ~8 F-15s lightly damaged | G81: 79 | H81: 1 A-10 lost a wing, ~8 F-15s lightly damaged (CBS, anonymous US sources; CENTCOM had not confirmed). More than 30 Patriot interceptors fired per CBS; 'roughly 30' per a US official (Reuters/AAP). Jordan: 18 of 20 missiles intercepted | I81: High | J81: CBS News 2026-09-10; CBS News 2026-09-09; Times of Israel 2026-09-10; AAP (report by Idrees Ali, Reuters) via Newcastle Herald 2026-09-11; Al Jazeera 2026-09-09 | K81: Corrected | L81: Sep 9 is right for Jordan local time (overnight Sep 8-9); in US time it began the evening of Sep 8. Damage details rest on anonymous US sources. The AAP/Reuters piece also cites CSIS: fewer than 850 Patriot interceptors left. | M81: Kinetic | N81: 5 | O81: 4 | P81: 0.99 | Q81: Yes | R81: Low-intensity war | S81: T15 | T81: High (23 pts)
A82: 81 | B82: 46288 | C82: Iran | D82: Diplomatic proposal | E82: US | F82: FM Araghchi's 7-day roadmap at UNGA: ceasefire, blockade lift, Strait reopens on day 7 | H82: Pending at time of writing | I82: High | J82: Al Jazeera 2026-09-26 | K82: Verified | M82: Diplomatic | N82: 1 | O82: 1 | P82: 0.8 | Q82: Yes | R82: Holding pattern | S82: T16 | T82: Low (2 pts)
A83: 82 | B83: 46291 | C83: US | D83: Diplomatic rejection | E83: Iran | F83: Trump rejects the proposal; officials say he expects to resume bombing after the November midterms | G83: 81 | H83: n/a | I83: High | J83: Al Jazeera 2026-09-26; Times of Israel 2026-09-26 | K83: Verified | M83: Diplomatic | N83: 2 | O83: 2 | P83: 0.96 | Q83: Yes | R83: Holding pattern | S83: T16 | T83: Quiet (0 pts)
A84: 83 | B84: 46292 | C84: Iran (suspected)/UK | D84: Terror plot (foiled) | E84: United Kingdom | F84: 5 men in their 20s are arrested on Sep 27 on suspicion of explosives offences after three suspicious vehicles head toward RAF Fairford (a base used for US bombers); Rubio says it 'clearly involves the hands of a foreign actor', Trump says it 'might be' linked to Iran, and UK PM Burnham says there are 'strong indications that Iran played a part' (Iran denies) | H84: No casualties - plot reportedly disrupted before execution; suspects later released on bail, which Trump publicly criticized the UK over | I84: High | J84: Stars and Stripes 2026-09-30 | K84: Verified | L84: Wording corrected (Stars and Stripes, Sep 30): the source does not say the men planned to do 'big damage'; it says they are suspected of planning a terrorist attack near the base. They were released on bail Sep 28 and Trump questioned the bail (re-sourced Oct 28). | M84: Other | N84: 1 | O84: 1 | P84: 0.8 | Q84: Yes | R84: Holding pattern | S84: T17 | T84: Quiet (0 pts)
A85: 84 | B85: 46293 | C85: Iran (unclear/disputed) | D85: Strike (shipping) | E85: Strait of Hormuz | F85: At least 3 commercial vessels struck by projectiles in the Hormuz region; IRGC says 'military conflict' continues there daily | H85: No casualties reported | I85: Medium | J85: Al Jazeera liveblog, Sept 30 | K85: Not re-checked | L85: Caution (Oct 11 check): trade press says one ship was hit the evening of Sep 28 and three tankers on Sep 29, so this row may merge two days. Not yet checked against UKMTO. | M85: Maritime | N85: 1 | O85: 1 | P85: 0.52 | Q85: Yes - use with caution | R85: Holding pattern | T85: Quiet (0 pts)
A86: 85 | B86: 46294 | C86: US | D86: Sanctions response | E86: Iran | F86: Treasury imposes new sanctions on 10 individuals/entities for supporting Iran's military supply chain | H86: n/a | I86: High | J86: Al Jazeera 2026-09-29; AP 2026-09-29 | K86: Corrected | L86: Date corrected to Sep 29 (Al Jazeera; AP via PBS): Treasury announced the sanctions on Tuesday, Sep 29, not Sep 28. | M86: Sanctions | N86: 2 | O86: 2 | P86: 0.96 | Q86: Yes | R86: Holding pattern | T86: Low (1 pts)
A87: 86 | B87: 46294 | C87: US | D87: Diplomatic proposal (counter-offer) | E87: Iran | F87: US sends a formal counter-proposal via Qatari mediators responding to Iran's 7-day roadmap; US insists nuclear talks be included | G87: 82 | H87: Pending Iranian review as of Sept 30 | I87: Medium | J87: Al Jazeera liveblog / CBS News liveblog | K87: Not re-checked | M87: Diplomatic | N87: 2 | O87: 2 | P87: 0.77 | Q87: Yes | R87: Holding pattern | S87: T16 | T87: Low (1 pts)
A88: 87 | B88: 46296 | C88: US | D88: Sanctions response | E88: Iran | F88: Treasury sanctions Iran's automotive and rail sectors and a shadow banking network, calling the targets 'some of the last significant elements of Iran's failing industrial infrastructure' | H88: n/a | I88: High | J88: Treasury 2026-10-01 | K88: Verified | L88: Wording corrected (Treasury press release, Oct 1): Treasury says 'failing industrial infrastructure', not 'IRGC-linked industrial base', and its release does not tie the banking network to Russia, so the Russia claim was dropped (re-sourced Oct 28). | M88: Sanctions | N88: 1 | O88: 1 | P88: 0.8 | Q88: Yes | R88: Holding pattern | T88: Low (1 pts)
A89: 88 | B89: 46296 | C89: US | D89: Diplomatic statement | E89: Iran | F89: Trump tells TIME Iran is 'ready to fold up'; says military action could resume after the Nov midterms if talks fail; says he doesn't believe lasting peace with Iran is possible | H89: n/a - rhetoric, not a formal proposal/action | I89: Medium | J89: CBS News / TIME interview, Oct 1 (matcher live test) | K89: Not re-checked | M89: Diplomatic | N89: 2 | O89: 2 | P89: 0.77 | Q89: Yes | R89: Holding pattern | T89: Low (1 pts)
A90: 89 | B90: 46296 | C90: US | D90: Force posture | E90: Middle East region | F90: 3 ships carrying 7,000+ sailors and 2,000 Marines deploy to the region; projected to push US presence above 20,000 personnel plus hundreds of aircraft by month's end | H90: n/a - posture change, not a strike | I90: Medium | J90: CBS News live updates, Oct 1 (matcher live test) | K90: Not re-checked | M90: Posture | N90: 1 | O90: 1 | P90: 0.52 | Q90: Yes - use with caution | R90: Holding pattern | T90: Low (1 pts)
A91: 90 | B91: 46297 | C91: Iran (suspected) | D91: Strike (shipping) | E91: Strait of Hormuz | F91: Cluster of projectile and drone attacks on tankers in and near Hormuz, Oct 2-5; Reuters' maritime security sources counted at least 12 tanker attacks in Sep 28-Oct 5, the most of any week of the war | H91: No deaths reported; damage not itemised (Reuters, USNI) | I91: High | J91: Reuters 2026-10-07; USNI News 2026-10-09 | K91: Verified | M91: Maritime | N91: 2 | O91: 2 | P91: 0.96 | Q91: Yes | R91: Holding pattern | T91: Low (1 pts)
A92: 91 | B92: 46299 | C92: US | D92: Force posture (withdrawal) | E92: RAF Fairford, UK | F92: Pentagon confirms all US bombers at RAF Fairford have returned to home bases; US officials told Reuters it was over a suspected Iranian drone-attack plot | G92: 83 | H92: n/a | I92: High | J92: Reuters 2026-10-06 | K92: Verified | M92: Posture | N92: 1 | O92: 1 | P92: 0.8 | Q92: Yes | R92: Holding pattern | S92: T17 | T92: Low (2 pts)
A93: 92 | B93: 46299 | C93: US | D93: Force posture (withdrawal) | E93: Middle East region | F93: Carrier George H.W. Bush leaves CENTCOM for the Pacific (port call in Phuket Oct 4), leaving the George Washington as the only US carrier in the Middle East | H93: n/a | I93: High | J93: The War Zone 2026-10-06 | K93: Verified | M93: Posture | N93: 1 | O93: 1 | P93: 0.8 | Q93: Yes | R93: Holding pattern | T93: Low (2 pts)
A94: 93 | B94: 46300 | C94: Iran | D94: Diplomatic rejection | E94: US | F94: President Pezeshkian calls negotiations with Washington 'futile', saying the US attacked Iran three times after talks | G94: 86 | H94: n/a | I94: High | J94: Al Jazeera 2026-10-07; Al Jazeera 2026-10-09 | K94: Verified | M94: Diplomatic | N94: 2 | O94: 1 | P94: 0.8 | Q94: Yes | R94: Holding pattern | S94: T16 | T94: Low (2 pts)
A95: 94 | B95: 46301 | C95: Unknown (Iran suspected) | D95: Strike (shipping) | E95: Strait of Hormuz | F95: Panama-flagged tanker On Peace hit by a projectile while crossing the strait; India condemns the attack (possibly Oct 5) | H95: 12 crew injured, 11 of them Indian (India's foreign ministry, via AFP and Al Jazeera) | I95: High | J95: AFP 2026-10-06; Al Jazeera 2026-10-07; Reuters 2026-10-07 | K95: Verified | M95: Maritime | N95: 3 | O95: 3 | P95: 0.99 | Q95: Yes | R95: Holding pattern | T95: Low (2 pts)
A96: 95 | B96: 46301 | C96: US | D96: Diplomatic demand | E96: Iran | F96: VP Vance tells Reuters Iran must make a 'meaningful' cut to uranium enrichment to end the war - read by analysts as possibly softer than the earlier zero-enrichment demand | H96: n/a | I96: High | J96: Al Jazeera 2026-10-07; Al Jazeera 2026-10-09 | K96: Verified | M96: Diplomatic | N96: 2 | O96: 1 | P96: 0.8 | Q96: Yes | R96: Holding pattern | T96: Low (2 pts)
A97: 96 | B97: 46302 | C97: Unknown | D97: Strike (shipping) | E97: Qatar (inside the Gulf) | F97: UKMTO reports a tanker struck off northern Qatar, well west of the strait | H97: Not stated by allowed sources | I97: High | J97: USNI News 2026-10-09; Reuters 2026-10-09 | K97: Verified | M97: Maritime | N97: 2 | O97: 2 | P97: 0.96 | Q97: Yes | R97: Holding pattern | T97: Low (5 pts)
A98: 97 | B98: 46303 | C98: US | D98: Ceasefire statement | E98: Iran | F98: Trump says on Truth Social the US 'will not be attacking Iran at any time prior to the Midterm Elections' (Nov 3), citing 'productive discussions' | H98: n/a | I98: High | J98: AP 2026-10-08; Al Jazeera 2026-10-09 | K98: Verified | M98: Diplomatic | N98: 2 | O98: 2 | P98: 0.96 | Q98: Yes | R98: Holding pattern | S98: T18 | T98: Medium (6 pts)
A99: 98 | B99: 46303 | C99: Houthis (Iran-backed) | D99: Strike (proxy front) | E99: Saudi Arabia | F99: Houthis fire a ballistic missile at Riyadh's King Khalid airport, citing Saudi strikes on Sanaa and Hodeidah; part of the separate Saudi-Houthi front | H99: 3 killed, several wounded (Saudi aviation authority, via Al Jazeera) | I99: High | J99: Al Jazeera 2026-10-09 | K99: Verified | L99: Context row: Saudi-Houthi front, not a direct Iran-US act. Kept because an American was killed on Oct 10 and Trump said he is weighing a response. | M99: Kinetic | N99: 1 | O99: 1 | P99: 0.8 | Q99: Yes | R99: Holding pattern | S99: T19 | T99: Medium (6 pts)
A100: 99 | B100: 46304 | C100: Iran | D100: Diplomatic response pending | E100: US | F100: FM Araghchi says Iran is reviewing the US counter-proposal and will answer 'within the next few days'; talks continue through mediators | G100: 86 | H100: n/a | I100: High | J100: Al Jazeera 2026-10-09; AP 2026-10-08 | K100: Verified | M100: Diplomatic | N100: 2 | O100: 2 | P100: 0.96 | Q100: Yes | R100: Holding pattern | S100: T16 | T100: Medium (6 pts)
...

Sheet Action-Reaction Pairs
A1: Pair ID | B1: Trigger ID | C1: Trigger Date | D1: Trigger Actor | E1: Trigger Action | F1: Response ID | G1: Response Date | H1: Response Actor | I1: Response Action | J1: Response Time (days) | K1: Trigger Category | L1: Response Caused Casualties | M1: Notes
A2: 1 | B2: 2 | C2: =INDEX('Event Log'!$B$2:$B$194,MATCH(B2,'Event Log'!$A$2:$A$194,0)) -> 46081 | D2: =INDEX('Event Log'!$C$2:$C$194,MATCH(B2,'Event Log'!$A$2:$A$194,0)) -> US/Israel | E2: =INDEX('Event Log'!$F$2:$F$194,MATCH(B2,'Event Log'!$A$2:$A$194,0)) -> Operation Epic Fury opens: Pentagon says 1,000+ targets hit in the first 24 hours; Khamenei and ~40 senior officials killed; a strike near Minab hits a girls' school | F2: 5 | G2: =INDEX('Event Log'!$B$2:$B$194,MATCH(F2,'Event Log'!$A$2:$A$194,0)) -> 46081 | H2: =INDEX('Event Log'!$C$2:$C$194,MATCH(F2,'Event Log'!$A$2:$A$194,0)) -> Iran | I2: =INDEX('Event Log'!$F$2:$F$194,MATCH(F2,'Event Log'!$A$2:$A$194,0)) -> Iran fires missiles at Israel, Kuwait and other Gulf targets; a missile hits a residential block in Tel Aviv; Kuwait International Airport is hit by a drone | J2: =G2-C2 -> 0 | K2: Personnel/Casualty | L2: Y | M2: Iran's opening retaliation wave, same day as the initial US/Israeli strikes that killed Khamenei and, per Iranian officials, 168-175 at a school
A3: 2 | B3: 10 | C3: =INDEX('Event Log'!$B$2:$B$194,MATCH(B3,'Event Log'!$A$2:$A$194,0)) -> 46084 | D3: =INDEX('Event Log'!$C$2:$C$194,MATCH(B3,'Event Log'!$A$2:$A$194,0)) -> Israel (IDF) | E3: =INDEX('Event Log'!$F$2:$F$194,MATCH(B3,'Event Log'!$A$2:$A$194,0)) -> IDF says it struck Iran's Supreme National Security Council complex in Tehran (Mar 2-3) and destroyed a secret underground site on Tehran's outskirts where Iran moved its nuclear work (IDF claim) | F3: 11 | G3: =INDEX('Event Log'!$B$2:$B$194,MATCH(F3,'Event Log'!$A$2:$A$194,0)) -> 46084 | H3: =INDEX('Event Log'!$C$2:$C$194,MATCH(F3,'Event Log'!$A$2:$A$194,0)) -> Iran | I3: =INDEX('Event Log'!$F$2:$F$194,MATCH(F3,'Event Log'!$A$2:$A$194,0)) -> Two Iranian drones hit the US embassy in Riyadh; limited fire and minor damage per Saudi Defense Ministry (AP) | J3: =G3-C3 -> 0 | K3: Military/Property | L3: N | M3: Retaliation against a symbolic/soft target (embassy annex) rather than in kind
A4: 3 | B4: 16 | C4: =INDEX('Event Log'!$B$2:$B$194,MATCH(B4,'Event Log'!$A$2:$A$194,0)) -> 46102 | D4: =INDEX('Event Log'!$C$2:$C$194,MATCH(B4,'Event Log'!$A$2:$A$194,0)) -> US/Israel (alleged) | E4: =INDEX('Event Log'!$F$2:$F$194,MATCH(B4,'Event Log'!$A$2:$A$194,0)) -> Iran reports an attack on Natanz and blames the US and Israel; the Israeli military denied involvement and the IAEA saw no rise in off-site radiation | F4: 17 | G4: =INDEX('Event Log'!$B$2:$B$194,MATCH(F4,'Event Log'!$A$2:$A$194,0)) -> 46102 | H4: =INDEX('Event Log'!$C$2:$C$194,MATCH(F4,'Event Log'!$A$2:$A$194,0)) -> Iran | I4: =INDEX('Event Log'!$F$2:$F$194,MATCH(F4,'Event Log'!$A$2:$A$194,0)) -> Iran strikes toward Dimona and Arad and calls it a 'response' to Natanz; Iran did not claim to target the Negev research center | J4: =G4-C4 -> 0 | K4: Military/Property | L4: Y | M4: Iran hits Israeli nuclear-adjacent sites in response to a US strike on Natanz
A5: 4 | B5: 20 | C5: =INDEX('Event Log'!$B$2:$B$194,MATCH(B5,'Event Log'!$A$2:$A$194,0)) -> 46107 | D5: =INDEX('Event Log'!$C$2:$C$194,MATCH(B5,'Event Log'!$A$2:$A$194,0)) -> Israel | E5: =INDEX('Event Log'!$F$2:$F$194,MATCH(B5,'Event Log'!$A$2:$A$194,0)) -> Israel says it killed IRGC Navy commander Tangsiri and the IRGC Navy's intelligence chief Rezaei in Bandar Abbas (Israeli claim, Mar 26); Iran confirmed Tangsiri's death on Mar 30 | F5: 21 | G5: =INDEX('Event Log'!$B$2:$B$194,MATCH(F5,'Event Log'!$A$2:$A$194,0)) -> 46108 | H5: =INDEX('Event Log'!$C$2:$C$194,MATCH(F5,'Event Log'!$A$2:$A$194,0)) -> Iran | I5: =INDEX('Event Log'!$F$2:$F$194,MATCH(F5,'Event Log'!$A$2:$A$194,0)) -> Strikes Prince Sultan Air Base | J5: =G5-C5 -> 1 | K5: Personnel/Casualty | L5: Y | M5: Retaliation for Israel's strike that it says killed the IRGC Navy commander and its intelligence chief (Iran confirmed only the commander, Mar 30)
A6: 5 | B6: 30 | C6: =INDEX('Event Log'!$B$2:$B$194,MATCH(B6,'Event Log'!$A$2:$A$194,0)) -> 46120 | D6: =INDEX('Event Log'!$C$2:$C$194,MATCH(B6,'Event Log'!$A$2:$A$194,0)) -> Israel | E6: =INDEX('Event Log'!$F$2:$F$194,MATCH(B6,'Event Log'!$A$2:$A$194,0)) -> Israel strikes 100+ targets across Beirut, southern Lebanon and the Bekaa in about 10 minutes, within hours of the ceasefire (AP) | F6: 31 | G6: =INDEX('Event Log'!$B$2:$B$194,MATCH(F6,'Event Log'!$A$2:$A$194,0)) -> 46120 | H6: =INDEX('Event Log'!$C$2:$C$194,MATCH(F6,'Event Log'!$A$2:$A$194,0)) -> Iran | I6: =INDEX('Event Log'!$F$2:$F$194,MATCH(F6,'Event Log'!$A$2:$A$194,0)) -> Iran restricts/resumes blockade, citing the Lebanon strikes as a ceasefire violation | J6: =G6-C6 -> 0 | K6: Political/Diplomatic | L6: N | M6: Iran treats an Israeli action as breaking a US-brokered ceasefire
A7: 6 | B7: 34 | C7: =INDEX('Event Log'!$B$2:$B$194,MATCH(B7,'Event Log'!$A$2:$A$194,0)) -> 46123 | D7: =INDEX('Event Log'!$C$2:$C$194,MATCH(B7,'Event Log'!$A$2:$A$194,0)) -> US/Iran/Pakistan | E7: =INDEX('Event Log'!$F$2:$F$194,MATCH(B7,'Event Log'!$A$2:$A$194,0)) -> Islamabad Talks: 21 hours of negotiation, collapse without agreement | F7: 35 | G7: =INDEX('Event Log'!$B$2:$B$194,MATCH(F7,'Event Log'!$A$2:$A$194,0)) -> 46125 | H7: =INDEX('Event Log'!$C$2:$C$194,MATCH(F7,'Event Log'!$A$2:$A$194,0)) -> US | I7: =INDEX('Event Log'!$F$2:$F$194,MATCH(F7,'Event Log'!$A$2:$A$194,0)) -> US naval blockade of Iran begins | J7: =G7-C7 -> 2 | K7: Political/Diplomatic | L7: N | M7: Failed talks preceded the US blockade decision
A8: 7 | B8: 35 | C8: =INDEX('Event Log'!$B$2:$B$194,MATCH(B8,'Event Log'!$A$2:$A$194,0)) -> 46125 | D8: =INDEX('Event Log'!$C$2:$C$194,MATCH(B8,'Event Log'!$A$2:$A$194,0)) -> US | E8: =INDEX('Event Log'!$F$2:$F$194,MATCH(B8,'Event Log'!$A$2:$A$194,0)) -> US naval blockade of Iran begins | F8: 36 | G8: =INDEX('Event Log'!$B$2:$B$194,MATCH(F8,'Event Log'!$A$2:$A$194,0)) -> 46130 | H8: =INDEX('Event Log'!$C$2:$C$194,MATCH(F8,'Event Log'!$A$2:$A$194,0)) -> Iran | I8: =INDEX('Event Log'!$F$2:$F$194,MATCH(F8,'Event Log'!$A$2:$A$194,0)) -> Iran announces the Strait closed again, citing continuation of the US blockade | J8: =G8-C8 -> 5 | K8: Economic/Blockade | L8: N | M8: Iran reopens hostilities citing the new US blockade
A9: 8 | B9: 37 | C9: =INDEX('Event Log'!$B$2:$B$194,MATCH(B9,'Event Log'!$A$2:$A$194,0)) -> 46131 | D9: =INDEX('Event Log'!$C$2:$C$194,MATCH(B9,'Event Log'!$A$2:$A$194,0)) -> US | E9: =INDEX('Event Log'!$F$2:$F$194,MATCH(B9,'Event Log'!$A$2:$A$194,0)) -> US disables the Iranian container ship Touska with gunfire from USS Spruance (Apr 19, USNI); tankers Tifani and Majestic X interdicted in the Indian Ocean around Apr 22-24 (dates not confirmed by an allowed outlet) | F9: 38 | G9: =INDEX('Event Log'!$B$2:$B$194,MATCH(F9,'Event Log'!$A$2:$A$194,0)) -> 46134 | H9: =INDEX('Event Log'!$C$2:$C$194,MATCH(F9,'Event Log'!$A$2:$A$194,0)) -> Iran | I9: =INDEX('Event Log'!$F$2:$F$194,MATCH(F9,'Event Log'!$A$2:$A$194,0)) -> IRGC seizes container ships MSC Epaminondas and MSC Francesca | J9: =G9-C9 -> 3 | K9: Economic/Blockade | L9: N | M9: Direct tit-for-tat ship seizures
A10: 9 | B10: 41 | C10: =INDEX('Event Log'!$B$2:$B$194,MATCH(B10,'Event Log'!$A$2:$A$194,0)) -> 46149 | D10: =INDEX('Event Log'!$C$2:$C$194,MATCH(B10,'Event Log'!$A$2:$A$194,0)) -> Iran | E10: =INDEX('Event Log'!$F$2:$F$194,MATCH(B10,'Event Log'!$A$2:$A$194,0)) -> Missiles, drones and small boats attack 3 US destroyers transiting the Strait | F10: 42 | G10: =INDEX('Event Log'!$B$2:$B$194,MATCH(F10,'Event Log'!$A$2:$A$194,0)) -> 46149 | H10: =INDEX('Event Log'!$C$2:$C$194,MATCH(F10,'Event Log'!$A$2:$A$194,0)) -> US | I10: =INDEX('Event Log'!$F$2:$F$194,MATCH(F10,'Event Log'!$A$2:$A$194,0)) -> US strikes sites near Bandar Abbas and Qeshm Island (CENTCOM did not name the IRGC) | J10: =G10-C10 -> 0 | K10: Military/Property | L10: N | M10: US strikes back same day after its destroyers are attacked (no casualties)
A11: 10 | B11: 44 | C11: =INDEX('Event Log'!$B$2:$B$194,MATCH(B11,'Event Log'!$A$2:$A$194,0)) -> 46181 | D11: =INDEX('Event Log'!$C$2:$C$194,MATCH(B11,'Event Log'!$A$2:$A$194,0)) -> Israel | E11: =INDEX('Event Log'!$F$2:$F$194,MATCH(B11,'Event Log'!$A$2:$A$194,0)) -> Strikes kill members of Iran's air-defense units | F11: 45 | G11: =INDEX('Event Log'!$B$2:$B$194,MATCH(F11,'Event Log'!$A$2:$A$194,0)) -> 46181 | H11: =INDEX('Event Log'!$C$2:$C$194,MATCH(F11,'Event Log'!$A$2:$A$194,0)) -> Iran | I11: =INDEX('Event Log'!$F$2:$F$194,MATCH(F11,'Event Log'!$A$2:$A$194,0)) -> Downs a US Apache helicopter over the Strait (US says a Shahed drone did it) | J11: =G11-C11 -> 0 | K11: Personnel/Casualty | L11: N | M11: Iran/US disagree on mechanism, but timing ties this to the preceding Israeli strike that killed air-defense personnel
A12: 11 | B12: 45 | C12: =INDEX('Event Log'!$B$2:$B$194,MATCH(B12,'Event Log'!$A$2:$A$194,0)) -> 46181 | D12: =INDEX('Event Log'!$C$2:$C$194,MATCH(B12,'Event Log'!$A$2:$A$194,0)) -> Iran | E12: =INDEX('Event Log'!$F$2:$F$194,MATCH(B12,'Event Log'!$A$2:$A$194,0)) -> Downs a US Apache helicopter over the Strait (US says a Shahed drone did it) | F12: 46 | G12: =INDEX('Event Log'!$B$2:$B$194,MATCH(F12,'Event Log'!$A$2:$A$194,0)) -> 46182 | H12: =INDEX('Event Log'!$C$2:$C$194,MATCH(F12,'Event Log'!$A$2:$A$194,0)) -> US | I12: =INDEX('Event Log'!$F$2:$F$194,MATCH(F12,'Event Log'!$A$2:$A$194,0)) -> US strikes Iranian air-defense, ground-control and surveillance radar sites near the Strait after Iran downs a US Apache (CENTCOM: 'proportional response') | J12: =G12-C12 -> 1 | K12: Military/Property | L12: N | M12: US retaliates for the downed Apache within hours (crew survived)
A13: 12 | B13: 46 | C13: =INDEX('Event Log'!$B$2:$B$194,MATCH(B13,'Event Log'!$A$2:$A$194,0)) -> 46182 | D13: =INDEX('Event Log'!$C$2:$C$194,MATCH(B13,'Event Log'!$A$2:$A$194,0)) -> US | E13: =INDEX('Event Log'!$F$2:$F$194,MATCH(B13,'Event Log'!$A$2:$A$194,0)) -> US strikes Iranian air-defense, ground-control and surveillance radar sites near the Strait after Iran downs a US Apache (CENTCOM: 'proportional response') | F13: 47 | G13: =INDEX('Event Log'!$B$2:$B$194,MATCH(F13,'Event Log'!$A$2:$A$194,0)) -> 46183 | H13: =INDEX('Event Log'!$C$2:$C$194,MATCH(F13,'Event Log'!$A$2:$A$194,0)) -> Iran | I13: =INDEX('Event Log'!$F$2:$F$194,MATCH(F13,'Event Log'!$A$2:$A$194,0)) -> Strikes Muwaffaq Salti AB plus bases in Kuwait and Bahrain | J13: =G13-C13 -> 1 | K13: Military/Property | L13: N | M13: Iran retaliates against Jordan for the US's Qeshm/Sirik counterstrikes
... A37: 37 | B37: 255 | C37: =INDEX('Event Log'!$B$2:$B$194,MATCH(B37,'Event Log'!$A$2:$A$194,0)) -> 45830 | D37: =INDEX('Event Log'!$C$2:$C$194,MATCH(B37,'Event Log'!$A$2:$A$194,0)) -> US | E37: =INDEX('Event Log'!$F$2:$F$194,MATCH(B37,'Event Log'!$A$2:$A$194,0)) -> Operation Midnight Hammer: US bombers and missiles strike Iran's Fordow, Natanz and Isfahan nuclear sites | F37: 256 | G37: =INDEX('Event Log'!$B$2:$B$194,MATCH(F37,'Event Log'!$A$2:$A$194,0)) -> 45831 | H37: =INDEX('Event Log'!$C$2:$C$194,MATCH(F37,'Event Log'!$A$2:$A$194,0)) -> Iran | I37: =INDEX('Event Log'!$F$2:$F$194,MATCH(F37,'Event Log'!$A$2:$A$194,0)) -> Iran fires 19 missiles at Al Udeid air base; one hits; Trump thanks Iran for 'early notice' | J37: =G37-C37 -> 1 | K37: Military/Property | L37: N | M37: Iran answers the strikes on its nuclear sites with a telegraphed missile attack on Al Udeid
A39: Average response time (days): | B39: =AVERAGE(J2:J37) -> 1.4166667
A40: Median response time (days): | B40: =MEDIAN(J2:J37) -> 1
A41: Number of pairs (n): | B41: =COUNT(J2:J37) -> 36
A42: Share responded within 1 day: | B42: =COUNTIF(J2:J37,"<=1")/COUNT(J2:J37) -> 0.66666667
A44: Pairs on hold (not counted in any statistic):
A45: Pair 21: trigger #75 -> response #76 (Military/Property). Iran follows up with a larger second wave the next day, after a strike that destroyed aircraft but killed no one Held because: event #76 is likely a duplicate of #75.

Sheet Factor Analysis
A1: Which factor drives a fast, reliable response?
A2: Each action-reaction pair is tagged by what kind of cost the trigger imposed on the side that responded. Grouping by that tag shows which kind of cost provokes the fastest, most reliable comeback - this is the closest thing this dataset has to 'which factor the country weighs most.'
A5: Trigger Category | B5: n (pairs) | C5: Mean response time (days) | D5: Share responded within 1 day | E5: 95% CI low | F5: 95% CI high | G5: Share responded within 2 days | H5: Share of responses that cause casualties
A6: Personnel/Casualty | B6: =COUNTIF('Action-Reaction Pairs'!$K$2:$K$37,A6) -> 11 | C6: =AVERAGEIF('Action-Reaction Pairs'!$K$2:$K$37,A6,'Action-Reaction Pairs'!$J$2:$J$37) -> 1.5454545 | D6: =SUMPRODUCT(('Action-Reaction Pairs'!$K$2:$K$37=A6)*('Action-Reaction Pairs'!$J$2:$J$37<=1))/COUNTIF('Action-Reaction Pairs'!$K$2:$K$37,A6) -> 0.63636364 | E6: =MAX(0,((D6+(1.96^2)/(2*B6)))/(1+(1.96^2)/B6)-(1.96*SQRT((D6*(1-D6)/B6)+((1.96^2)/(4*B6^2))))/(1+(1.96^2)/B6)) -> 0.35379678 | F6: =MIN(1,((D6+(1.96^2)/(2*B6)))/(1+(1.96^2)/B6)+(1.96*SQRT((D6*(1-D6)/B6)+((1.96^2)/(4*B6^2))))/(1+(1.96^2)/B6)) -> 0.84833776 | G6: =SUMPRODUCT(('Action-Reaction Pairs'!$K$2:$K$37=A6)*('Action-Reaction Pairs'!$J$2:$J$37<=2))/COUNTIF('Action-Reaction Pairs'!$K$2:$K$37,A6) -> 0.81818182 | H6: =COUNTIFS('Action-Reaction Pairs'!$K$2:$K$37,A6,'Action-Reaction Pairs'!$L$2:$L$37,"Y")/COUNTIF('Action-Reaction Pairs'!$K$2:$K$37,A6) -> 0.36363636
A7: Military/Property | B7: =COUNTIF('Action-Reaction Pairs'!$K$2:$K$37,A7) -> 15 | C7: =AVERAGEIF('Action-Reaction Pairs'!$K$2:$K$37,A7,'Action-Reaction Pairs'!$J$2:$J$37) -> 1 | D7: =SUMPRODUCT(('Action-Reaction Pairs'!$K$2:$K$37=A7)*('Action-Reaction Pairs'!$J$2:$J$37<=1))/COUNTIF('Action-Reaction Pairs'!$K$2:$K$37,A7) -> 0.8 | E7: =MAX(0,((D7+(1.96^2)/(2*B7)))/(1+(1.96^2)/B7)-(1.96*SQRT((D7*(1-D7)/B7)+((1.96^2)/(4*B7^2))))/(1+(1.96^2)/B7)) -> 0.54814065 | F7: =MIN(1,((D7+(1.96^2)/(2*B7)))/(1+(1.96^2)/B7)+(1.96*SQRT((D7*(1-D7)/B7)+((1.96^2)/(4*B7^2))))/(1+(1.96^2)/B7)) -> 0.92952579 | G7: =SUMPRODUCT(('Action-Reaction Pairs'!$K$2:$K$37=A7)*('Action-Reaction Pairs'!$J$2:$J$37<=2))/COUNTIF('Action-Reaction Pairs'!$K$2:$K$37,A7) -> 0.93333333 | H7: =COUNTIFS('Action-Reaction Pairs'!$K$2:$K$37,A7,'Action-Reaction Pairs'!$L$2:$L$37,"Y")/COUNTIF('Action-Reaction Pairs'!$K$2:$K$37,A7) -> 0.4
A8: Economic/Blockade | B8: =COUNTIF('Action-Reaction Pairs'!$K$2:$K$37,A8) -> 5 | C8: =AVERAGEIF('Action-Reaction Pairs'!$K$2:$K$37,A8,'Action-Reaction Pairs'!$J$2:$J$37) -> 2 | D8: =SUMPRODUCT(('Action-Reaction Pairs'!$K$2:$K$37=A8)*('Action-Reaction Pairs'!$J$2:$J$37<=1))/COUNTIF('Action-Reaction Pairs'!$K$2:$K$37,A8) -> 0.6 | E8: =MAX(0,((D8+(1.96^2)/(2*B8)))/(1+(1.96^2)/B8)-(1.96*SQRT((D8*(1-D8)/B8)+((1.96^2)/(4*B8^2))))/(1+(1.96^2)/B8)) -> 0.23071993 | F8: =MIN(1,((D8+(1.96^2)/(2*B8)))/(1+(1.96^2)/B8)+(1.96*SQRT((D8*(1-D8)/B8)+((1.96^2)/(4*B8^2))))/(1+(1.96^2)/B8)) -> 0.88238177 | G8: =SUMPRODUCT(('Action-Reaction Pairs'!$K$2:$K$37=A8)*('Action-Reaction Pairs'!$J$2:$J$37<=2))/COUNTIF('Action-Reaction Pairs'!$K$2:$K$37,A8) -> 0.6 | H8: =COUNTIFS('Action-Reaction Pairs'!$K$2:$K$37,A8,'Action-Reaction Pairs'!$L$2:$L$37,"Y")/COUNTIF('Action-Reaction Pairs'!$K$2:$K$37,A8) -> 0
A9: Political/Diplomatic | B9: =COUNTIF('Action-Reaction Pairs'!$K$2:$K$37,A9) -> 5 | C9: =AVERAGEIF('Action-Reaction Pairs'!$K$2:$K$37,A9,'Action-Reaction Pairs'!$J$2:$J$37) -> 1.8 | D9: =SUMPRODUCT(('Action-Reaction Pairs'!$K$2:$K$37=A9)*('Action-Reaction Pairs'!$J$2:$J$37<=1))/COUNTIF('Action-Reaction Pairs'!$K$2:$K$37,A9) -> 0.4 | E9: =MAX(0,((D9+(1.96^2)/(2*B9)))/(1+(1.96^2)/B9)-(1.96*SQRT((D9*(1-D9)/B9)+((1.96^2)/(4*B9^2))))/(1+(1.96^2)/B9)) -> 0.11761823 | F9: =MIN(1,((D9+(1.96^2)/(2*B9)))/(1+(1.96^2)/B9)+(1.96*SQRT((D9*(1-D9)/B9)+((1.96^2)/(4*B9^2))))/(1+(1.96^2)/B9)) -> 0.76928007 | G9: =SUMPRODUCT(('Action-Reaction Pairs'!$K$2:$K$37=A9)*('Action-Reaction Pairs'!$J$2:$J$37<=2))/COUNTIF('Action-Reaction Pairs'!$K$2:$K$37,A9) -> 0.6 | H9: =COUNTIFS('Action-Reaction Pairs'!$K$2:$K$37,A9,'Action-Reaction Pairs'!$L$2:$L$37,"Y")/COUNTIF('Action-Reaction Pairs'!$K$2:$K$37,A9) -> 0
A11: Reading this table: 'Personnel/Casualty' pairs are triggers that killed or injured someone (an assassination, a strike that hit a school or a wedding, an attack on air-defense crews). 'Economic/Blockade' pairs are triggers about ships, seizures, sanctions, or oil - no one was hurt.
A13: What it shows, two ways: (1) SPEED/RELIABILITY - triggers that cost human lives get answered faster and more reliably than triggers that only cost money or equipment; economic/blockade moves are the slowest and least certain. (2) COST OF THE COMEBACK - the last column shows how often the response itself produces real casualties, not just a symbolic hit. Personnel/Casualty triggers are answered both fastest AND with the highest chance of a genuinely costly response. Economic/Blockade and Political/Diplomatic triggers have never (in this dataset) drawn a response that killed or injured anyone - the retaliation happens, but it stays contained to property and equipment.
A15: The 95% CI columns are Wilson score intervals on the 'within 1 day' share - the honest range given how few examples each category has. Notice how wide these are (often 30-40 points wide) for the n=4-5 categories - that's the real uncertainty, not a flaw in the formula. Treat the RANKING across categories as solid; treat any single percentage as a rough midpoint of a wide range.
A17: Sample-size warning: each group has 4-10 pairs. This is a real, directionally consistent pattern, not a precise coefficient.
A19: Important limit: every share on this sheet is measured only among pairs where a reply happened. It says how fast and how costly replies are, not whether one comes. For the chance a reply happens at all, see the Trigger Census sheet.

Sheet Trigger Census
A1: How often does a hostile act actually get a reply?
A2: Factor Analysis only sees pairs where a reply happened, so it overstates how reliable replies are. This sheet lists every countable hostile act (strikes, seizures, blockade moves, sanctions) and whether the other side hit back within about 5 days - including the ones where nothing followed. Diplomatic moves are not covered.
A5: Trigger Category | B5: Acts counted | C5: Got a reply | D5: No reply found | E5: Unclear | F5: Unverified (not counted) | G5: P(any reply) LOW | H5: P(any reply) BEST | I5: P(any reply) HIGH | J5: 95% CI low (BEST) | K5: 95% CI high (BEST)
A6: Personnel/Casualty | B6: =C6+D6 -> 7 | C6: =COUNTIFS($F$24:$F$79,A6,$G$24:$G$79,"R-strong")+COUNTIFS($F$24:$F$79,A6,$G$24:$G$79,"R-weak")+COUNTIFS($F$24:$F$79,A6,$G$24:$G$79,"R-proxy") -> 6 | D6: =COUNTIFS($F$24:$F$79,A6,$G$24:$G$79,"N") -> 1 | E6: =COUNTIFS($F$24:$F$79,A6,$G$24:$G$79,"Unclear") -> 0 | F6: =COUNTIFS($F$24:$F$79,A6,$G$24:$G$79,"Unverified") -> 0 | G6: =COUNTIFS($F$24:$F$79,A6,$G$24:$G$79,"R-strong")/(B6+E6) -> 0.71428571 | H6: =C6/B6 -> 0.85714286 | I6: =(C6+E6)/(B6+E6) -> 0.85714286 | J6: =MAX(0,((H6+(1.96^2)/(2*B6)))/(1+(1.96^2)/B6)-(1.96*SQRT((H6*(1-H6)/B6)+((1.96^2)/(4*B6^2))))/(1+(1.96^2)/B6)) -> 0.4868655 | K6: =MIN(1,((H6+(1.96^2)/(2*B6)))/(1+(1.96^2)/B6)+(1.96*SQRT((H6*(1-H6)/B6)+((1.96^2)/(4*B6^2))))/(1+(1.96^2)/B6)) -> 0.97432104
A7: Military/Property | B7: =C7+D7 -> 19 | C7: =COUNTIFS($F$24:$F$79,A7,$G$24:$G$79,"R-strong")+COUNTIFS($F$24:$F$79,A7,$G$24:$G$79,"R-weak")+COUNTIFS($F$24:$F$79,A7,$G$24:$G$79,"R-proxy") -> 17 | D7: =COUNTIFS($F$24:$F$79,A7,$G$24:$G$79,"N") -> 2 | E7: =COUNTIFS($F$24:$F$79,A7,$G$24:$G$79,"Unclear") -> 2 | F7: =COUNTIFS($F$24:$F$79,A7,$G$24:$G$79,"Unverified") -> 1 | G7: =COUNTIFS($F$24:$F$79,A7,$G$24:$G$79,"R-strong")/(B7+E7) -> 0.42857143 | H7: =C7/B7 -> 0.89473684 | I7: =(C7+E7)/(B7+E7) -> 0.9047619 | J7: =MAX(0,((H7+(1.96^2)/(2*B7)))/(1+(1.96^2)/B7)-(1.96*SQRT((H7*(1-H7)/B7)+((1.96^2)/(4*B7^2))))/(1+(1.96^2)/B7)) -> 0.6860545 | K7: =MIN(1,((H7+(1.96^2)/(2*B7)))/(1+(1.96^2)/B7)+(1.96*SQRT((H7*(1-H7)/B7)+((1.96^2)/(4*B7^2))))/(1+(1.96^2)/B7)) -> 0.97064206
A8: Economic/Blockade | B8: =C8+D8 -> 22 | C8: =COUNTIFS($F$24:$F$79,A8,$G$24:$G$79,"R-strong")+COUNTIFS($F$24:$F$79,A8,$G$24:$G$79,"R-weak")+COUNTIFS($F$24:$F$79,A8,$G$24:$G$79,"R-proxy") -> 8 | D8: =COUNTIFS($F$24:$F$79,A8,$G$24:$G$79,"N") -> 14 | E8: =COUNTIFS($F$24:$F$79,A8,$G$24:$G$79,"Unclear") -> 3 | F8: =COUNTIFS($F$24:$F$79,A8,$G$24:$G$79,"Unverified") -> 2 | G8: =COUNTIFS($F$24:$F$79,A8,$G$24:$G$79,"R-strong")/(B8+E8) -> 0.2 | H8: =C8/B8 -> 0.36363636 | I8: =(C8+E8)/(B8+E8) -> 0.44 | J8: =MAX(0,((H8+(1.96^2)/(2*B8)))/(1+(1.96^2)/B8)-(1.96*SQRT((H8*(1-H8)/B8)+((1.96^2)/(4*B8^2))))/(1+(1.96^2)/B8)) -> 0.19732973 | K8: =MIN(1,((H8+(1.96^2)/(2*B8)))/(1+(1.96^2)/B8)+(1.96*SQRT((H8*(1-H8)/B8)+((1.96^2)/(4*B8^2))))/(1+(1.96^2)/B8)) -> 0.57048651
A10: PROVISIONAL. These statuses were first assigned from the Wikipedia-based log and a research pass that used some weak outlets. The log has since been re-sourced to credible outlets (see Event Log column K), which found real errors. Most unclear census rows have now been re-checked (see Evidence quality); a few Unverified rows are still left out of the rates. Many 'reply' calls are R-weak, meaning only timing links the reply to the act. Treat every rate on this sheet as a rough draft. Samples are tiny (about 4-12 acts per category), so the ranges matter more than the point estimates.
A12: Continuous-fighting rule: triggers dated Feb 28-Apr 7 and Jul 7-25 are excluded (except the acts that started those stretches), because while both sides strike each other daily every act is automatically 'answered'. The exclusion list at the bottom names every row moved out.
A14: Status codes: R-strong = reply is in the log with an explicit link. R-weak = a distinct hostile act followed within 5 days but only timing links it. N = checked against outside sources, no reply found (a pause, talks, or rhetoric only). Unclear = sources conflict or are too thin. Unverified = not checked yet, so left out of every rate below.
A16: Three estimates because the coding involves judgment. LOW counts only R-strong as replies and treats R-weak, N and Unclear all as no reply. BEST counts R-strong and R-weak as replies and ignores Unclear. HIGH also counts every Unclear as a reply. If a conclusion only holds under one of the three, it is not solid.
A18: The 95% CI is a Wilson interval around the BEST estimate and shows the sampling uncertainty on top of that judgment range. Samples are small (10-13 acts per category), so treat these as ranges, not points.
A20: Preliminary: the rows marked Unverified (see the Unverified column) have not been checked against outside sources. They are left out of the rates, not assumed to be replies or non-replies.
A23: Trigger ID | B23: Date | C23: Actor | D23: Action Type | E23: What happened | F23: Trigger Category | G23: Status | H23: Evidence / note | I23: Evidence quality
A24: 2 | B24: =INDEX('Event Log'!$B$2:$B$194,MATCH(A24,'Event Log'!$A$2:$A$194,0)) -> 46081 | C24: =INDEX('Event Log'!$C$2:$C$194,MATCH(A24,'Event Log'!$A$2:$A$194,0)) -> US/Israel | D24: =INDEX('Event Log'!$D$2:$D$194,MATCH(A24,'Event Log'!$A$2:$A$194,0)) -> Strike (war start) | E24: =INDEX('Event Log'!$F$2:$F$194,MATCH(A24,'Event Log'!$A$2:$A$194,0)) -> Operation Epic Fury opens: Pentagon says 1,000+ targets hit in the first 24 hours; Khamenei and ~40 senior officials killed; a strike near Minab hits a girls' school | F24: Personnel/Casualty | G24: R-strong | H24: Opening wave; Iran's big retaliation came the same day (pair 1). The act that started the war counts; the rest of Feb 28-Mar 4 is excluded. | I24: Trigger: Corrected. Reply #5: Partly verified
A25: 31 | B25: =INDEX('Event Log'!$B$2:$B$194,MATCH(A25,'Event Log'!$A$2:$A$194,0)) -> 46120 | C25: =INDEX('Event Log'!$C$2:$C$194,MATCH(A25,'Event Log'!$A$2:$A$194,0)) -> Iran | D25: =INDEX('Event Log'!$D$2:$D$194,MATCH(A25,'Event Log'!$A$2:$A$194,0)) -> Blockade re-escalation | E25: =INDEX('Event Log'!$F$2:$F$194,MATCH(A25,'Event Log'!$A$2:$A$194,0)) -> Iran restricts/resumes blockade, citing the Lebanon strikes as a ceasefire violation | F25: Economic/Blockade | G25: R-weak | H25: Iran keeps the Strait mostly shut after the Apr 8 ceasefire, citing Lebanon strikes. The US announced its blockade Apr 12 (in force Apr 13), but outlets tie it to the collapse of the Islamabad talks, not to Iran's restriction. Timing only. | I25: Re-checked (Times of Israel, NPR snippets, Al Jazeera): blockade came Apr 12-13, tied to failed talks. NPR pages were seen only as snippets.
A26: 33 | B26: =INDEX('Event Log'!$B$2:$B$194,MATCH(A26,'Event Log'!$A$2:$A$194,0)) -> 46123 | C26: =INDEX('Event Log'!$C$2:$C$194,MATCH(A26,'Event Log'!$A$2:$A$194,0)) -> US | D26: =INDEX('Event Log'!$D$2:$D$194,MATCH(A26,'Event Log'!$A$2:$A$194,0)) -> Blockade-adjacent action | E26: =INDEX('Event Log'!$F$2:$F$194,MATCH(A26,'Event Log'!$A$2:$A$194,0)) -> US Navy destroyers transit the Strait for the first time since the war began (mine-clearance framing) | F26: Economic/Blockade | G26: N | H26: US destroyers transit the Strait, Apr 11-12. Iran only issued warnings; no kinetic action found Apr 11-16. | I26: Re-checked (Reuters Apr 12, USNI, The War Zone, NPR): only an IRGC warning; no Iranian attacks Apr 11-17.
A27: 35 | B27: =INDEX('Event Log'!$B$2:$B$194,MATCH(A27,'Event Log'!$A$2:$A$194,0)) -> 46125 | C27: =INDEX('Event Log'!$C$2:$C$194,MATCH(A27,'Event Log'!$A$2:$A$194,0)) -> US | D27: =INDEX('Event Log'!$D$2:$D$194,MATCH(A27,'Event Log'!$A$2:$A$194,0)) -> Blockade start | E27: =INDEX('Event Log'!$F$2:$F$194,MATCH(A27,'Event Log'!$A$2:$A$194,0)) -> US naval blockade of Iran begins | F27: Economic/Blockade | G27: R-strong | H27: US blockade begins -> Iran closes the Strait again (pair 7). | I27: Trigger: Verified. Reply #36: Verified
A28: 36 | B28: =INDEX('Event Log'!$B$2:$B$194,MATCH(A28,'Event Log'!$A$2:$A$194,0)) -> 46130 | C28: =INDEX('Event Log'!$C$2:$C$194,MATCH(A28,'Event Log'!$A$2:$A$194,0)) -> Iran | D28: =INDEX('Event Log'!$D$2:$D$194,MATCH(A28,'Event Log'!$A$2:$A$194,0)) -> Blockade re-escalation | E28: =INDEX('Event Log'!$F$2:$F$194,MATCH(A28,'Event Log'!$A$2:$A$194,0)) -> Iran announces the Strait closed again, citing continuation of the US blockade | F28: Economic/Blockade | G28: R-weak | H28: Iran re-closes the Strait Apr 18 over the US blockade. The US seized the container ship Touska about Apr 19 (NPR), but NPR does not say it answers the closure; it is blockade enforcement that was already under way. Timing only. | I28: Re-checked (NPR, Al Jazeera): Touska seized about Apr 19; NPR does not link it to the closure.
A29: 37 | B29: =INDEX('Event Log'!$B$2:$B$194,MATCH(A29,'Event Log'!$A$2:$A$194,0)) -> 46131 | C29: =INDEX('Event Log'!$C$2:$C$194,MATCH(A29,'Event Log'!$A$2:$A$194,0)) -> US | D29: =INDEX('Event Log'!$D$2:$D$194,MATCH(A29,'Event Log'!$A$2:$A$194,0)) -> Seizure | E29: =INDEX('Event Log'!$F$2:$F$194,MATCH(A29,'Event Log'!$A$2:$A$194,0)) -> US disables the Iranian container ship Touska with gunfire from USS Spruance (Apr 19, USNI); tankers Tifani and Majestic X interdicted in the Indian Ocean around Apr 22-24 (dates not confirmed by an allowed outlet) | F29: Economic/Blockade | G29: R-strong | H29: US tanker seizures -> Iran seizes two container ships (pair 8). | I29: Trigger: Corrected. Reply #38: Verified
A30: 38 | B30: =INDEX('Event Log'!$B$2:$B$194,MATCH(A30,'Event Log'!$A$2:$A$194,0)) -> 46134 | C30: =INDEX('Event Log'!$C$2:$C$194,MATCH(A30,'Event Log'!$A$2:$A$194,0)) -> Iran | D30: =INDEX('Event Log'!$D$2:$D$194,MATCH(A30,'Event Log'!$A$2:$A$194,0)) -> Seizure (retaliation) | E30: =INDEX('Event Log'!$F$2:$F$194,MATCH(A30,'Event Log'!$A$2:$A$194,0)) -> IRGC seizes container ships MSC Epaminondas and MSC Francesca | F30: Economic/Blockade | G30: Unverified | H30: Iran seizes two container ships, Apr 22. US reply not checked yet. | I30: Trigger: Verified. Status itself pending credible re-verification
A31: 40 | B31: =INDEX('Event Log'!$B$2:$B$194,MATCH(A31,'Event Log'!$A$2:$A$194,0)) -> 46146 | C31: =INDEX('Event Log'!$C$2:$C$194,MATCH(A31,'Event Log'!$A$2:$A$194,0)) -> US | D31: =INDEX('Event Log'!$D$2:$D$194,MATCH(A31,'Event Log'!$A$2:$A$194,0)) -> Operation | E31: =INDEX('Event Log'!$F$2:$F$194,MATCH(A31,'Event Log'!$A$2:$A$194,0)) -> Operation Project Freedom: announced May 3, began May 4; Navy escort mission for stranded ships; US says six boats sunk (Trump said seven); pause announced May 5 US time (May 6 Gulf time) | F31: Military/Property | G31: R-weak | H31: Project Freedom began May 4 (paused May 5). Iran hit the UAE, a tanker and a cargo ship May 4 (CBS, Al Jazeera), but Al Jazeera stops short of calling it retaliation. Timing only. | I31: Re-checked (CBS, Al Jazeera): Iran attacked the UAE and ships May 4; no outlet calls it retaliation.
A32: 41 | B32: =INDEX('Event Log'!$B$2:$B$194,MATCH(A32,'Event Log'!$A$2:$A$194,0)) -> 46149 | C32: =INDEX('Event Log'!$C$2:$C$194,MATCH(A32,'Event Log'!$A$2:$A$194,0)) -> Iran | D32: =INDEX('Event Log'!$D$2:$D$194,MATCH(A32,'Event Log'!$A$2:$A$194,0)) -> Strike | E32: =INDEX('Event Log'!$F$2:$F$194,MATCH(A32,'Event Log'!$A$2:$A$194,0)) -> Missiles, drones and small boats attack 3 US destroyers transiting the Strait | F32: Military/Property | G32: R-strong | H32: Iran attacks 3 US destroyers -> US strikes back same day (pair 9). | I32: Trigger: Verified. Reply #42: Verified
A33: 42 | B33: =INDEX('Event Log'!$B$2:$B$194,MATCH(A33,'Event Log'!$A$2:$A$194,0)) -> 46149 | C33: =INDEX('Event Log'!$C$2:$C$194,MATCH(A33,'Event Log'!$A$2:$A$194,0)) -> US | D33: =INDEX('Event Log'!$D$2:$D$194,MATCH(A33,'Event Log'!$A$2:$A$194,0)) -> Retaliation strike | E33: =INDEX('Event Log'!$F$2:$F$194,MATCH(A33,'Event Log'!$A$2:$A$194,0)) -> US strikes sites near Bandar Abbas and Qeshm Island (CENTCOM did not name the IRGC) | F33: Military/Property | G33: R-weak | H33: US strikes near Bandar Abbas/Qeshm, May 7. The UAE said it intercepted Iranian missiles and drones May 8 (Reuters), but Iran claimed no reply and CENTCOM disputed Iran's claimed counterattack. Weak call. | I33: Re-checked (Reuters): weak. Reply is the UAE intercepting Iranian missiles May 8, which Iran did not claim.
A34: 44 | B34: =INDEX('Event Log'!$B$2:$B$194,MATCH(A34,'Event Log'!$A$2:$A$194,0)) -> 46181 | C34: =INDEX('Event Log'!$C$2:$C$194,MATCH(A34,'Event Log'!$A$2:$A$194,0)) -> Israel | D34: =INDEX('Event Log'!$D$2:$D$194,MATCH(A34,'Event Log'!$A$2:$A$194,0)) -> Strike (ceasefire violation) | E34: =INDEX('Event Log'!$F$2:$F$194,MATCH(A34,'Event Log'!$A$2:$A$194,0)) -> Strikes kill members of Iran's air-defense units | F34: Personnel/Casualty | G34: R-strong | H34: Israeli strike kills air-defense crews -> Iran downs a US Apache (pair 10). | I34: Trigger: Corrected. Reply #45: Corrected
A35: 45 | B35: =INDEX('Event Log'!$B$2:$B$194,MATCH(A35,'Event Log'!$A$2:$A$194,0)) -> 46181 | C35: =INDEX('Event Log'!$C$2:$C$194,MATCH(A35,'Event Log'!$A$2:$A$194,0)) -> Iran | D35: =INDEX('Event Log'!$D$2:$D$194,MATCH(A35,'Event Log'!$A$2:$A$194,0)) -> Retaliation | E35: =INDEX('Event Log'!$F$2:$F$194,MATCH(A35,'Event Log'!$A$2:$A$194,0)) -> Downs a US Apache helicopter over the Strait (US says a Shahed drone did it) | F35: Military/Property | G35: R-strong | H35: Apache downed -> US self-defense strikes within hours (pair 11). | I35: Trigger: Corrected. Reply #46: Corrected
... A79: 265 | B79: =INDEX('Event Log'!$B$2:$B$194,MATCH(A79,'Event Log'!$A$2:$A$194,0)) -> 44936 | C79: =INDEX('Event Log'!$C$2:$C$194,MATCH(A79,'Event Log'!$A$2:$A$194,0)) -> US | D79: =INDEX('Event Log'!$D$2:$D$194,MATCH(A79,'Event Log'!$A$2:$A$194,0)) -> Seizure (weapons shipment) | E79: =INDEX('Event Log'!$F$2:$F$194,MATCH(A79,'Event Log'!$A$2:$A$194,0)) -> US Navy patrol ships intercept a fishing vessel carrying 2,116 AK-47s on a route from Iran to Yemen (seized Jan 6, announced Jan 10; logged on the announcement date) | F79: Economic/Blockade | G79: N | H79: Seizure of 2,116 rifles shipped from Iran, announced Jan 10, 2023. No attack by Iran or an Iran-backed group on US forces found Jan 11-15; the next was a drone attack on the al-Tanf base on Jan 20 (Al Jazeera, https://www.aljazeera.com/news/2023/1/20/drone-attack-hits-us-led-coalition-base-in-southern-syria), outside the window. | I79: Trigger: Verified. Status itself pending credible re-verification
A81: Not counted, and why
A82: Continuous war, Feb 28 - Apr 7 (until the first ceasefire): both sides were striking each other every day, so every act has a 'reply' by default, which would inflate the rate. Event 2, the act that started the war, is counted; later events in that stretch are not.
A83: Nightly US campaign, Jul 7-25 (events 58 and 61-67): same reason. Events 57 and 60, which started it, are counted. Event 65 (US troops killed Jul 17) was followed by a US strike on Jul 18 that officials said was to 'punish' the IRGC, but it is excluded here for consistency.
A84: Diplomatic and ceasefire moves (events 18, 19, 24, 27-30, 34, 43, 49-52, 59, 81, 82, 86, 88): their 'reply' is a formal answer, which this log does not track reliably. Not covered yet.
A85: Covert, defensive, accidental or not hostile (events 1, 26, 32, 68, 69, 72, 83, 89): covert acts the other side could not respond to, a defensive shootdown, an accident, an analyst note, a mine-clearing mission, a foiled plot, and a troop deployment.
A86: Disputed attribution (event 84, low confidence) and same-wave duplicates (event 73, same wave as event 74).
A87: Candidates moved out of the census by the continuous-war rule: #14, #15, #16, #17, #20, #21, #22, #23, #25, #58.
A88: Bubiyan Island raid (May 1): Kuwait did not announce it until May 12, so no one could reply within 5 days. Kuwait's reply on May 12 was a protest and an ambassador summons, not a hostile act. Not counted.
A89: Pre-war continuous fighting: Oct 17, 2023 - Jan 29, 2024, Iran-backed militias attacked US forces almost daily, so US strikes in that stretch (#233, #234, #236, #237) are context only. The twelve-day war (Jun 13-24, 2025) is treated the same way; the US strike that brought the US in (#255) is counted.
A90: Pre-war rows not counted: #207 (defensive drone shootdown), #211/#231/#246/#259/#261 (deployments, measured separately), talks (#248-#252, #260, #262).
A91: Left out by the credibility rule (event credibility under 0.50, or a merged duplicate): #76.

Sheet Options
A1: Options and their risks - NAPOR does not rank or pick an option
A2: Situation as of 2026-10-26: war phase = Holding pattern. No direct US-Iran strikes since Sep 9; attacks on shipping continue; Trump says no US strikes before the Nov 3 midterms; Iran is expected to answer the US counter-offer.
A3: How to read it: each risk is 'x of n' past cases, so you can see how much evidence is behind it. The range is a 95% Wilson interval: with this few cases, the true chance could be anywhere in it. 'Very thin' means 1-3 past cases.
A4: Important: almost all past cases come from the fragile ceasefire and low-intensity phases, when nearly every hostile act drew a reply. The current quiet phase has only been tested by sanctions (0 of 2 drew a reply). Whether a US strike now would be answered the same way is unknown.
A5: Risk profile: every option on the same five risks, plus pros. Each cell says what was measured (x of n past cases) or 'not measured'.
A6: Option | B6: What it means | C6: 1. Harm to people | D6: 2. Escalation | E6: 3. Military cost | F6: 4. Economic harm | G6: 5. Political / diplomatic | H6: Pros (analyst notes) | I6: Other notes on harms (analyst notes) | J6: Evidence strength
A7: A. Hold: no new action | B7: Keep the current posture: blockade stays, no new strikes or sanctions. | C7: Ship crews: attacks on shipping continue at ~2.4 a week (e.g. On Peace, Oct 6: 12 crew injured). No new US act to answer. | D7: No new US trigger. Iranian or unidentified attacks on shipping keep happening anyway (baseline). Whether holding back changes Iran's behaviour: not measured. | E7: No added interceptor use from a US act; the blockade and patrols continue to cost what they cost now (not measured). | F7: Baseline: ~2.4 attacks on shipping a week in the current phase. Oil prices and shipping costs: not measured. | G7: Iran is expected to answer the US counter-offer; Trump's no-strike pledge stands until Nov 3. Strain with allies: not measured. | H7: No new US act for Iran to answer, so no added risk of retaliation from it. Keeps Trump's stated no-strike pledge before Nov 3. Leaves room for Iran's expected reply to the US counter-offer. Uses no interceptors. | I7: Attacks on shipping continue at about 1-2 a week (baseline), injuring crews (On Peace: 12 hurt) and raising shipping risk. Whether holding back weakens deterrence cannot be measured from this log. | J7: No data
A8: B. Diplomatic move | B8: Answer Iran's expected reply to the US counter-offer, make a new offer, or ask a mediator to push talks. | C8: No direct casualties from the move itself. | D8: Iran struck within 7 days after 3 of 16 past conciliatory US moves (timing only, not shown to be replies). Reply rate to diplomacy: not measured (not in the census). | E8: No interceptor use expected from the move itself. | F8: Attacks on shipping, 7 days before -> after past cases: 5 -> 10 (total). Oil prices and shipping costs: not measured. | G8: Talks within 14 days after: 8 of 16 (statements and threats do not count). Strain with allies (Jordan, Gulf states, UK): not measured. | H8: No direct casualties. In the log, US diplomatic moves were usually followed by more diplomacy within two weeks (see measured column). A deal is the only option that addresses all the goals at once: the June memorandum included phased Hormuz reopening and an end to the blockade. | I8: Past deals did not hold: the April ceasefire was violated the same day, and the June deal collapsed on Jul 7 (Iran later said it never took effect). Shipping attacks continued during talks. Political costs of concessions are not measured here. | J8: 16 past cases (timing only)
A9: C. New sanctions | B9: More Treasury sanctions on Iranian industries, networks or people. | C9: No direct casualties. Harm to ordinary Iranians from sanctions: not measured. | D9: Iran replied within ~5 days: 0 of 9 (0%) (range 0%-30%). Fast (within 2 days): No past replies to measure. Back-and-forth past one reply: No past replies. In the current quiet phase: 0 of 2. | E9: No interceptor use expected from the move itself. | F9: Attacks on shipping, 7 days before -> after past cases: 9 -> 15 (total). Oil prices and shipping costs: not measured. | G9: Talks within 14 days after: 4 of 11 (statements and threats do not count). Strain with allies (Jordan, Gulf states, UK): not measured. | H9: Economic pressure without casualties or interceptor use. Neither past case drew an Iranian military reply. | I9: No measured effect on shipping attacks (they rose in the following week, during the record week, so this may be coincidence). Possible economic harm to ordinary Iranians is not measured. Iran's president called talks 'futile' days later (no causal link shown). | J9: OK
A10: D. Naval pressure (blockade enforcement, transits, seizures) | B10: Tighten or enforce the blockade: stop or disable blockade runners, escort or transit warships. | C10: Iranian replies that hurt people: 0 of 2. US personnel hurt in these logged replies: 0 of 2 (US troops were killed on Jul 17, #65, during the July campaign, which is outside these counts). Civilian harm reported in the US act itself: 0 of 7 reported. | D10: Iran replied within ~5 days: 2 of 6 (33%) (range 10%-70%). Fast (within 2 days): 0 of 2. Back-and-forth past one reply: ~37% (all chains, n=27). In the current quiet phase: Not tested in this phase yet. | E10: Patriot interceptors: ~10 if the reply is a missile salvo like Sep 8-9. Confirmed US equipment losses in past replies: none logged. | F10: Attacks on shipping, 7 days before -> after past cases: 7 -> 7 (total). Oil prices and shipping costs: not measured. | G10: Talks within 14 days after: 1 of 7 (statements and threats do not count). Strain with allies (Jordan, Gulf states, UK): not measured. | H10: Aims directly at the blockade and Hormuz goals. In the April cases, no direct Iranian strike followed within 7 days, and the replies that came caused no casualties (0 of 2). | I10: In 2026, Iran answered 2 of 3 counted cases at sea (re-closing the Strait, seizing ships), so pressure at sea can spread at sea. Risk to the crews of disabled ships. The Oct 10-11 case drew no attack on US forces (forecast F001: NO), but shipping attacks surged the same week; whether that counts as a reply is not settled. | J10: Thin
A11: E. Strike Iranian shipping (e.g. tankers) | B11: Destroy IRGC-linked tankers or vessels, as on Sep 5 and Sep 8. | C11: Iranian replies that hurt people: 0 of 1. US personnel hurt in these logged replies: 0 of 1 (US troops were killed on Jul 17, #65, during the July campaign, which is outside these counts). Civilian harm reported in the US act itself: 0 of 3 reported. | D11: Iran replied within ~5 days: 2 of 2 (100%) (range 34%-100%). Fast (within 2 days): 1 of 1. Back-and-forth past one reply: ~37% (all chains, n=27). In the current quiet phase: Not tested in this phase yet. | E11: Patriot interceptors: ~30 if the reply is a missile salvo like Sep 8-9. Confirmed US equipment losses in past replies: Sep 8-9 Jordan: 1 A-10 lost a wing, ~8 F-15s lightly damaged (CBS, anonymous US sources). | F11: Attacks on shipping, 7 days before -> after past cases: 2 -> 5 (total). Oil prices and shipping costs: not measured. | G11: Talks within 14 days after: 1 of 3 (statements and threats do not count). Strain with allies (Jordan, Gulf states, UK): not measured. | H11: In both past cases, logged attacks on shipping dropped to zero the following week. Hits IRGC oil revenue (US claim). Crews were told to abandon ship before the Sep 8 strike, and no deaths were reported. | I11: Both cases drew Iranian missile fire within days (at a US warship, then at a Jordan base, where an A-10 was badly damaged, ~8 F-15s were lightly damaged and ~30 Patriots were used). Possible environmental damage from destroyed laden tankers is not measured. | J11: Very thin
A12: F. Strike military sites (equipment, not people) | B12: Hit launchers, radars, missile or drone sites, aiming to avoid casualties. | C12: Iranian replies that hurt people: 5 of 10 (#62 Qatar: 3 wounded incl. a child; #220 3 US service members (2 seriously) and 2 Iraqi soldiers wounded (AP); #226 3 US service members treated for minor injuries (AP); #229 1 US service member wounded (ABC); #241 6 SDF fighters killed; no US troops hurt (AP)). US personnel hurt in these logged replies: 0 of 10 (US troops were killed on Jul 17, #65, during the July campaign, which is outside these counts). Civilian harm reported in the US act itself: 0 of 12 reported. | D12: Iran replied within ~5 days: 11 of 12 (92%) (range 65%-99%). Fast (within 2 days): 9 of 10. Back-and-forth past one reply: ~37% (all chains, n=27). In the current quiet phase: Not tested in this phase yet. | E12: Patriot interceptors: ~28 if the reply is a missile salvo like Sep 8-9. Confirmed US equipment losses in past replies: none logged. | F12: Attacks on shipping, 7 days before -> after past cases: 3 -> 1 (total). Oil prices and shipping costs: not measured. | G12: Talks within 14 days after: 2 of 12 (statements and threats do not count). Strain with allies (Jordan, Gulf states, UK): not measured. | H12: Aims to reduce Iran's ability to launch missiles, drones and mines (military effect is claimed by CENTCOM, not independently measured). In 1 of 4 logged replies did anyone get hurt. | I12: Every past case drew a reply; Iranian strikes followed within 7 days in most. One logged reply wounded civilians in Qatar. Bridges were hit later in the July campaign (two in Hormozgan, Jul 16-17, 3 killed per Iranian state TV via AFP), outside the counted cases. Untested in the current quiet phase: it could restart the cycle. | J12: OK
A13: G. Strike that risks killing personnel | B13: Strikes on IRGC units or sites where people are likely to be killed. | C13: Iranian replies that hurt people: 2 of 6 (#5 Tel Aviv: 1 killed, 27 injured (Times of Israel); Kuwait airport: mino; #216 No deaths; more than 100 US troops later diagnosed with brain injuries). US personnel hurt in these logged replies: 0 of 6 (US troops were killed on Jul 17, #65, during the July campaign, which is outside these counts). Civilian harm reported in the US act itself: 2 of 7: #2 Minab girls' school: Iranian authorities say 168-175 killed; no country has claimed the strike (AP, NBC); #74 Kuhestak wedding: Iranian figures 4-5 killed incl. children, 50+ wounded; the US said it was investigating. | D13: Iran replied within ~5 days: 6 of 7 (86%) (range 49%-97%). Fast (within 2 days): 5 of 6. Back-and-forth past one reply: ~37% (all chains, n=27). In the current quiet phase: Not tested in this phase yet. | E13: Patriot interceptors: ~26 if the reply is a missile salvo like Sep 8-9. Confirmed US equipment losses in past replies: Jun 9: a US Apache helicopter downed over the Strait (crew rescued). | F13: Attacks on shipping, 7 days before -> after past cases: 1 -> 1 (total). Oil prices and shipping costs: not measured. | G13: Talks within 14 days after: 1 of 7 (statements and threats do not count). Strain with allies (Jordan, Gulf states, UK): not measured. | H13: Can remove commanders or units preparing attacks (e.g. the Aug 30 Larak strike hit launchers said to be preparing sea mines). Military effect is claimed, not independently measured. | I13: Every past case drew a fast reply, mostly the same day. Civilians were reported killed in 2 of 4 past cases (Iranian figures). One logged reply killed a civilian in Tel Aviv. Highest risk of a longer back-and-forth. | J13: Thin
A14: H. Change force posture (deploy or withdraw) | B14: Send more ships, aircraft or troops to the region, or pull some back. | C14: No direct casualties from the move itself. | D14: Iran struck within 7 days after 1 of 10 past posture changes (all early October). Not tested as triggers. | E14: No interceptor use expected from the move itself. | F14: Attacks on shipping, 7 days before -> after past cases: 6 -> 14 (total). Oil prices and shipping costs: not measured. | G14: Talks within 14 days after: 5 of 10 (statements and threats do not count). Strain with allies (Jordan, Gulf states, UK): not measured. | H14: No direct harm. Adding forces strengthens defence; pulling back reduces exposure (bombers left RAF Fairford after a suspected Iranian drone plot). | I14: Deployments in early October were followed by more shipping attacks, but that was the record week anyway. No data on how Iran reads deployments or withdrawals. | J14: 10 past cases (timing only)
A16: Details behind the numbers
A18: Option | B18: What it means | C18: Chance of an Iranian hostile reply within ~5 days (past cases) | D18: Plausible range (95%) | E18: In the current phase | F18: Reply within 2 days (of replies) | G18: Reply caused casualties (of replies) | H18: Chance a back-and-forth goes past one reply | I18: Patriot interceptors likely used | J18: Evidence strength | K18: Avg credibility of cases | L18: Past cases used | M18: What we don't know
A19: A. Hold: no new action | B19: Keep the current posture: blockade stays, no new strikes or sanctions. | C19: Not measured | F19: Not measured | G19: Not measured | J19: No data | M19: Shipping attacks have kept coming without any new US move (see the baseline line). Trump has said there will be no US strikes before Nov 3; what Iran does if that holds is not in the data.
A20: B. Diplomatic move | B20: Answer Iran's expected reply to the US counter-offer, make a new offer, or ask a mediator to push talks. | C20: Not measured | F20: Not measured | G20: Not measured | J20: No data | M20: Diplomatic moves are not in the census, so there is no reply rate. The last rounds (Sep 23 - Oct 9) drew rejections and counter-offers, not attacks. Iran called the US answer 'insufficient' (Oct 11) and on Oct 18 said it was still reviewing US 'comments'.
A21: C. New sanctions | B21: More Treasury sanctions on Iranian industries, networks or people. | C21: 0 of 9 (0%) | D21: 0%-30% | E21: 0 of 2 | F21: No past replies to measure | G21: No past replies to measure | H21: No past replies | I21: Unlikely to need any | J21: OK | K21: 0.72 | L21: #85, #87, #206, #208, #210, #217, #244, #247, #258 (+ unclear: #107, #110) | M21: Both past cases are from the current quiet phase, and neither drew a linked attack. Tanker attacks continued that week, but no outlet tied them to the sanctions.
A22: D. Naval pressure (blockade enforcement, transits, seizures) | B22: Tighten or enforce the blockade: stop or disable blockade runners, escort or transit warships. | C22: 2 of 6 (33%) | D22: 10%-70% | E22: Not tested in this phase yet | F22: 0 of 2 | G22: 0 of 2 | H22: ~37% (all chains, n=27) | I22: ~10 if the reply is a missile salvo like Sep 8-9 | J22: Thin | K22: 0.92 | L22: #33, #35, #37, #221, #264, #265 (+ unclear: #104) | M22: Small sample. The pre-war cases (a 2020 fuel-cargo seizure and two seizures of Iranian arms bound for the Houthis, 2020 and 2023) drew no reply. In 2026, Iran answered the blockade start and a ship seizure, but not a warship transit. The Oct 10-11 strike on a blockade runner drew no Iranian attack on US forces within 5 days (F001: NO), but attacks on commercial shipping surged; how to score it is waiting for Sidd (census row #104 is 'Unclear').
A23: E. Strike Iranian shipping (e.g. tankers) | B23: Destroy IRGC-linked tankers or vessels, as on Sep 5 and Sep 8. | C23: 2 of 2 (100%) | D23: 34%-100% | E23: Not tested in this phase yet | F23: 1 of 1 | G23: 0 of 1 | H23: ~37% (all chains, n=27) | I23: ~30 if the reply is a missile salvo like Sep 8-9 | J23: Very thin | K23: 0.90 | L23: #77, #79 (+ unclear: #106) | M23: Only 2 cases, both in early September; both drew Iranian missile fire (at a US warship, then at a Jordan base).
A24: F. Strike military sites (equipment, not people) | B24: Hit launchers, radars, missile or drone sites, aiming to avoid casualties. | C24: 11 of 12 (92%) | D24: 65%-99% | E24: Not tested in this phase yet | F24: 9 of 10 | G24: 5 of 10 | H24: ~37% (all chains, n=27) | I24: ~28 if the reply is a missile salvo like Sep 8-9 | J24: OK | K24: 0.84 | L24: #40, #42, #46, #55, #60, #219, #222, #223, #225, #228, #240, #255 | M24: Every past case drew a reply, but all were before the current quiet phase. One logged reply caused casualties (Qatar, Jul 12: 3 wounded, including a child).
A25: G. Strike that risks killing personnel | B25: Strikes on IRGC units or sites where people are likely to be killed. | C25: 6 of 7 (86%) | D25: 49%-97% | E25: Not tested in this phase yet | F25: 5 of 6 | G25: 2 of 6 | H25: ~37% (all chains, n=27) | I25: ~26 if the reply is a missile salvo like Sep 8-9 | J25: Thin | K25: 0.85 | L25: #2, #44, #70, #74, #213, #215, #242 | M25: Every past case drew a fast reply, mostly the same day. One logged reply caused casualties (Tel Aviv, Feb 28: 1 killed, 27 injured). None in the current quiet phase.
A26: H. Change force posture (deploy or withdraw) | B26: Send more ships, aircraft or troops to the region, or pull some back. | C26: Not measured | F26: Not measured | G26: Not measured | J26: No data | M26: No data: deployments and withdrawals are logged but not tested as triggers. The US recently pulled bombers from RAF Fairford and one carrier left the region.
A28: Baseline (what happens with no new US move): in the current phase, 16 hostile acts by Iran or unknown attackers were logged over 6.7 weeks (about 2.4 per week), almost all attacks on shipping: #84, #90, #94, #96, #100, #101, #103, #105, #109, #112, #113, #114, #117, #118, #121, #123. Houthi strikes on Saudi Arabia are a separate front and not counted.
A29: Back-and-forth column: across all 27 logged chains with a hostile act, about a third went past one reply (longest: 3 rounds). It is not broken down by option because each option has too few chains.
A30: Interceptors: one measured salvo (Sep 8-9, Jordan) used about 30 Patriots ('roughly 30' per a US official; 'more than 30' per CBS). The column multiplies that by the reply chance. CSIS estimated fewer than 850 Patriots left theater-wide (Sep). Not independently re-checked.
A31: Only events with credibility 0.50+ are used. Every number here is recomputed from the Event Log by napor_options.py when the workbook is rebuilt.

Sheet Monthly Summary
A1: Month | B1: US/Israel strikes (on territory/forces) | C1: Iran strikes (on territory/forces) | D1: Shipping/blockade incidents (any side) | E1: Diplomatic events (talks, proposals, ceasefires) | F1: Ceasefire status | G1: Notes
A2: Feb 2026 | B2: =COUNTIFS('Event Log'!$C$2:$C$194,"US*",'Event Log'!$M$2:$M$194,"Kinetic",'Event Log'!$B$2:$B$194,">="&DATE(2026,2,1),'Event Log'!$B$2:$B$194,"<="&DATE(2026,2,28))+COUNTIFS('Event Log'!$C$2:$C$194,"Israel*",'Event Log'!$M$2:$M$194,"Kinetic",'Event Log'!$B$2:$B$194,">="&DATE(2026,2,1),'Event Log'!$B$2:$B$194,"<="&DATE(2026,2,28)) -> 3 | C2: =COUNTIFS('Event Log'!$C$2:$C$194,"Iran*",'Event Log'!$M$2:$M$194,"Kinetic",'Event Log'!$B$2:$B$194,">="&DATE(2026,2,1),'Event Log'!$B$2:$B$194,"<="&DATE(2026,2,28)) -> 1 | D2: =COUNTIFS('Event Log'!$M$2:$M$194,"Maritime",'Event Log'!$B$2:$B$194,">="&DATE(2026,2,1),'Event Log'!$B$2:$B$194,"<="&DATE(2026,2,28)) -> 1 | E2: =COUNTIFS('Event Log'!$M$2:$M$194,"Diplomatic",'Event Log'!$B$2:$B$194,">="&DATE(2026,2,1),'Event Log'!$B$2:$B$194,"<="&DATE(2026,2,28)) -> 3 | F2: No ceasefire - war start | G2: War start (Feb 28)
A3: Mar 2026 | B3: =COUNTIFS('Event Log'!$C$2:$C$194,"US*",'Event Log'!$M$2:$M$194,"Kinetic",'Event Log'!$B$2:$B$194,">="&DATE(2026,3,1),'Event Log'!$B$2:$B$194,"<="&DATE(2026,3,31))+COUNTIFS('Event Log'!$C$2:$C$194,"Israel*",'Event Log'!$M$2:$M$194,"Kinetic",'Event Log'!$B$2:$B$194,">="&DATE(2026,3,1),'Event Log'!$B$2:$B$194,"<="&DATE(2026,3,31)) -> 6 | C3: =COUNTIFS('Event Log'!$C$2:$C$194,"Iran*",'Event Log'!$M$2:$M$194,"Kinetic",'Event Log'!$B$2:$B$194,">="&DATE(2026,3,1),'Event Log'!$B$2:$B$194,"<="&DATE(2026,3,31)) -> 7 | D3: =COUNTIFS('Event Log'!$M$2:$M$194,"Maritime",'Event Log'!$B$2:$B$194,">="&DATE(2026,3,1),'Event Log'!$B$2:$B$194,"<="&DATE(2026,3,31)) -> 2 | E3: =COUNTIFS('Event Log'!$M$2:$M$194,"Diplomatic",'Event Log'!$B$2:$B$194,">="&DATE(2026,3,1),'Event Log'!$B$2:$B$194,"<="&DATE(2026,3,31)) -> 3 | F3: No ceasefire | G3: Highest-intensity month of the initial campaign
A4: Apr 2026 | B4: =COUNTIFS('Event Log'!$C$2:$C$194,"US*",'Event Log'!$M$2:$M$194,"Kinetic",'Event Log'!$B$2:$B$194,">="&DATE(2026,4,1),'Event Log'!$B$2:$B$194,"<="&DATE(2026,4,30))+COUNTIFS('Event Log'!$C$2:$C$194,"Israel*",'Event Log'!$M$2:$M$194,"Kinetic",'Event Log'!$B$2:$B$194,">="&DATE(2026,4,1),'Event Log'!$B$2:$B$194,"<="&DATE(2026,4,30)) -> 2 | C4: =COUNTIFS('Event Log'!$C$2:$C$194,"Iran*",'Event Log'!$M$2:$M$194,"Kinetic",'Event Log'!$B$2:$B$194,">="&DATE(2026,4,1),'Event Log'!$B$2:$B$194,"<="&DATE(2026,4,30)) -> 1 | D4: =COUNTIFS('Event Log'!$M$2:$M$194,"Maritime",'Event Log'!$B$2:$B$194,">="&DATE(2026,4,1),'Event Log'!$B$2:$B$194,"<="&DATE(2026,4,30)) -> 6 | E4: =COUNTIFS('Event Log'!$M$2:$M$194,"Diplomatic",'Event Log'!$B$2:$B$194,">="&DATE(2026,4,1),'Event Log'!$B$2:$B$194,"<="&DATE(2026,4,30)) -> 4 | F4: Two-week ceasefire announced Apr 7-8 (no signed text found), violated same day, collapsing through month | G4: Ceasefire signed and broken within hours
A5: May 2026 | B5: =COUNTIFS('Event Log'!$C$2:$C$194,"US*",'Event Log'!$M$2:$M$194,"Kinetic",'Event Log'!$B$2:$B$194,">="&DATE(2026,5,1),'Event Log'!$B$2:$B$194,"<="&DATE(2026,5,31))+COUNTIFS('Event Log'!$C$2:$C$194,"Israel*",'Event Log'!$M$2:$M$194,"Kinetic",'Event Log'!$B$2:$B$194,">="&DATE(2026,5,1),'Event Log'!$B$2:$B$194,"<="&DATE(2026,5,31)) -> 2 | C5: =COUNTIFS('Event Log'!$C$2:$C$194,"Iran*",'Event Log'!$M$2:$M$194,"Kinetic",'Event Log'!$B$2:$B$194,">="&DATE(2026,5,1),'Event Log'!$B$2:$B$194,"<="&DATE(2026,5,31)) -> 2 | D5: =COUNTIFS('Event Log'!$M$2:$M$194,"Maritime",'Event Log'!$B$2:$B$194,">="&DATE(2026,5,1),'Event Log'!$B$2:$B$194,"<="&DATE(2026,5,31)) -> 0 | E5: =COUNTIFS('Event Log'!$M$2:$M$194,"Diplomatic",'Event Log'!$B$2:$B$194,">="&DATE(2026,5,1),'Event Log'!$B$2:$B$194,"<="&DATE(2026,5,31)) -> 0 | F5: Nominal ceasefire, blockade/counter-blockade ongoing | G5: Blockade/counter-blockade tit-for-tat, lower kinetic tempo
A6: Jun 2026 | B6: =COUNTIFS('Event Log'!$C$2:$C$194,"US*",'Event Log'!$M$2:$M$194,"Kinetic",'Event Log'!$B$2:$B$194,">="&DATE(2026,6,1),'Event Log'!$B$2:$B$194,"<="&DATE(2026,6,30))+COUNTIFS('Event Log'!$C$2:$C$194,"Israel*",'Event Log'!$M$2:$M$194,"Kinetic",'Event Log'!$B$2:$B$194,">="&DATE(2026,6,1),'Event Log'!$B$2:$B$194,"<="&DATE(2026,6,30)) -> 4 | C6: =COUNTIFS('Event Log'!$C$2:$C$194,"Iran*",'Event Log'!$M$2:$M$194,"Kinetic",'Event Log'!$B$2:$B$194,">="&DATE(2026,6,1),'Event Log'!$B$2:$B$194,"<="&DATE(2026,6,30)) -> 5 | D6: =COUNTIFS('Event Log'!$M$2:$M$194,"Maritime",'Event Log'!$B$2:$B$194,">="&DATE(2026,6,1),'Event Log'!$B$2:$B$194,"<="&DATE(2026,6,30)) -> 3 | E6: =COUNTIFS('Event Log'!$M$2:$M$194,"Diplomatic",'Event Log'!$B$2:$B$194,">="&DATE(2026,6,1),'Event Log'!$B$2:$B$194,"<="&DATE(2026,6,30)) -> 3 | F6: New ceasefire Jun 8, MOU signed Jun 17 | G6: Two ceasefires reached; MOU by month end
A7: Jul 2026 | B7: =COUNTIFS('Event Log'!$C$2:$C$194,"US*",'Event Log'!$M$2:$M$194,"Kinetic",'Event Log'!$B$2:$B$194,">="&DATE(2026,7,1),'Event Log'!$B$2:$B$194,"<="&DATE(2026,7,31))+COUNTIFS('Event Log'!$C$2:$C$194,"Israel*",'Event Log'!$M$2:$M$194,"Kinetic",'Event Log'!$B$2:$B$194,">="&DATE(2026,7,1),'Event Log'!$B$2:$B$194,"<="&DATE(2026,7,31)) -> 1 | C7: =COUNTIFS('Event Log'!$C$2:$C$194,"Iran*",'Event Log'!$M$2:$M$194,"Kinetic",'Event Log'!$B$2:$B$194,">="&DATE(2026,7,1),'Event Log'!$B$2:$B$194,"<="&DATE(2026,7,31)) -> 6 | D7: =COUNTIFS('Event Log'!$M$2:$M$194,"Maritime",'Event Log'!$B$2:$B$194,">="&DATE(2026,7,1),'Event Log'!$B$2:$B$194,"<="&DATE(2026,7,31)) -> 2 | E7: =COUNTIFS('Event Log'!$M$2:$M$194,"Diplomatic",'Event Log'!$B$2:$B$194,">="&DATE(2026,7,1),'Event Log'!$B$2:$B$194,"<="&DATE(2026,7,31)) -> 1 | F7: MOU collapses Jul 7-8; heaviest fighting month | G7: MOU collapse; deadliest month for US troops
A8: Aug 2026 | B8: =COUNTIFS('Event Log'!$C$2:$C$194,"US*",'Event Log'!$M$2:$M$194,"Kinetic",'Event Log'!$B$2:$B$194,">="&DATE(2026,8,1),'Event Log'!$B$2:$B$194,"<="&DATE(2026,8,31))+COUNTIFS('Event Log'!$C$2:$C$194,"Israel*",'Event Log'!$M$2:$M$194,"Kinetic",'Event Log'!$B$2:$B$194,">="&DATE(2026,8,1),'Event Log'!$B$2:$B$194,"<="&DATE(2026,8,31)) -> 1 | C8: =COUNTIFS('Event Log'!$C$2:$C$194,"Iran*",'Event Log'!$M$2:$M$194,"Kinetic",'Event Log'!$B$2:$B$194,">="&DATE(2026,8,1),'Event Log'!$B$2:$B$194,"<="&DATE(2026,8,31)) -> 1 | D8: =COUNTIFS('Event Log'!$M$2:$M$194,"Maritime",'Event Log'!$B$2:$B$194,">="&DATE(2026,8,1),'Event Log'!$B$2:$B$194,"<="&DATE(2026,8,31)) -> 2 | E8: =COUNTIFS('Event Log'!$M$2:$M$194,"Diplomatic",'Event Log'!$B$2:$B$194,">="&DATE(2026,8,1),'Event Log'!$B$2:$B$194,"<="&DATE(2026,8,31)) -> 0 | F8: No ceasefire, lower-intensity than July | G8: Relative lull; Larak Island strike late month
A9: Sep 2026 | B9: =COUNTIFS('Event Log'!$C$2:$C$194,"US*",'Event Log'!$M$2:$M$194,"Kinetic",'Event Log'!$B$2:$B$194,">="&DATE(2026,9,1),'Event Log'!$B$2:$B$194,"<="&DATE(2026,9,30))+COUNTIFS('Event Log'!$C$2:$C$194,"Israel*",'Event Log'!$M$2:$M$194,"Kinetic",'Event Log'!$B$2:$B$194,">="&DATE(2026,9,1),'Event Log'!$B$2:$B$194,"<="&DATE(2026,9,30)) -> 4 | C9: =COUNTIFS('Event Log'!$C$2:$C$194,"Iran*",'Event Log'!$M$2:$M$194,"Kinetic",'Event Log'!$B$2:$B$194,">="&DATE(2026,9,1),'Event Log'!$B$2:$B$194,"<="&DATE(2026,9,30)) -> 4 | D9: =COUNTIFS('Event Log'!$M$2:$M$194,"Maritime",'Event Log'!$B$2:$B$194,">="&DATE(2026,9,1),'Event Log'!$B$2:$B$194,"<="&DATE(2026,9,30)) -> 1 | E9: =COUNTIFS('Event Log'!$M$2:$M$194,"Diplomatic",'Event Log'!$B$2:$B$194,">="&DATE(2026,9,1),'Event Log'!$B$2:$B$194,"<="&DATE(2026,9,30)) -> 3 | F9: No ceasefire; new Iranian proposal Sep 23, rejected Sep 26 | G9: Partial month - renewed escalation, then a new peace proposal
A10: Oct 2026 (to Oct 26) | B10: =COUNTIFS('Event Log'!$C$2:$C$194,"US*",'Event Log'!$M$2:$M$194,"Kinetic",'Event Log'!$B$2:$B$194,">="&DATE(2026,10,1),'Event Log'!$B$2:$B$194,"<="&DATE(2026,10,31))+COUNTIFS('Event Log'!$C$2:$C$194,"Israel*",'Event Log'!$M$2:$M$194,"Kinetic",'Event Log'!$B$2:$B$194,">="&DATE(2026,10,1),'Event Log'!$B$2:$B$194,"<="&DATE(2026,10,31)) -> 1 | C10: =COUNTIFS('Event Log'!$C$2:$C$194,"Iran*",'Event Log'!$M$2:$M$194,"Kinetic",'Event Log'!$B$2:$B$194,">="&DATE(2026,10,1),'Event Log'!$B$2:$B$194,"<="&DATE(2026,10,31)) -> 0 | D10: =COUNTIFS('Event Log'!$M$2:$M$194,"Maritime",'Event Log'!$B$2:$B$194,">="&DATE(2026,10,1),'Event Log'!$B$2:$B$194,"<="&DATE(2026,10,31)) -> 16 | E10: =COUNTIFS('Event Log'!$M$2:$M$194,"Diplomatic",'Event Log'!$B$2:$B$194,">="&DATE(2026,10,1),'Event Log'!$B$2:$B$194,"<="&DATE(2026,10,31)) -> 14 | F10: No ceasefire; Trump says no US strikes on Iran before the Nov 3 midterms (Oct 8); strike plans reported (Oct 16); Trump weighs 'a deal' or renewed strikes (Oct 23-25) | G10: Partial month. Record attacks on shipping (GFS Pride sunk Oct 13); US bombers leave RAF Fairford; more US sanctions; US staff drawdown from Gulf posts (Oct 21-23); no US-Iran strikes

Sheet Reports
A1: Report ID | B1: Event ID | C1: Outlet | D1: Kind of source | E1: Headline | F1: Published | G1: URL | H1: Read as | I1: Logged under | J1: Source score | K1: Fit score | L1: Weight (counts if 0.30+)
A2: R0001 | B2: 1 | C2: AP (syndicated on KSAT/click2houston) | D2: Independent outlet | E2: How the US-Israeli strikes on Iran unfolded, moment by moment | F2: 2026-03-02 | G2: https://www.click2houston.com/news/world/2026/03/02/how-the-us-israeli-strikes-on-iran-unfolded-moment-by-moment/ | H2: full text | J2: 0.8 | K2: 1 | L2: 0.8
A3: R0002 | B3: 1 | C3: AP (syndicated on WJXT/news4jax) | D3: Independent outlet | E3: This is how the US-Israeli strikes on Iran played out | F3: 2026-03-02 | G3: https://www.news4jax.com/news/world/2026/03/02/this-is-how-the-us-israeli-strikes-on-iran-played-out/ | H3: full text | J3: 0.8 | K3: 1 | L3: 0.8
A4: R0003 | B4: 2 | C4: AP (syndicated on KSAT/click2houston) | D4: Independent outlet | E4: How the US-Israeli strikes on Iran unfolded, moment by moment | F4: 2026-03-02 | G4: https://www.click2houston.com/news/world/2026/03/02/how-the-us-israeli-strikes-on-iran-unfolded-moment-by-moment/ | H4: full text | J4: 0.8 | K4: 1 | L4: 0.8
A5: R0004 | B5: 2 | C5: NBC News (via AOL) | D5: Independent outlet | E5: What we know about the strike on a school in Iran as the death toll rises | F5: 2026-03-03 | G5: https://www.aol.com/articles/know-strike-school-iran-death-223303330.html | H5: full text | J5: 0.8 | K5: 1 | L5: 0.8
A6: R0005 | B6: 2 | C6: AP (syndicated on Alaska Dispatch News/adn.com) | D6: Independent outlet | E6: Iranians mourn elementary school students killed in missile strike | F6: 2026-03-04 | G6: https://www.adn.com/nation-world/2026/03/04/iranians-mourn-elementary-school-students-killed-in-missile-strike/ | H6: full text | J6: 0.8 | K6: 1 | L6: 0.8
A7: R0006 | B7: 3 | C7: Defense News (Military Times) | D7: Independent outlet | E7: 9 Iranian naval ships have been destroyed and sunk, Trump says | F7: 2026-03-01 | G7: https://www.defensenews.com/news/your-military/2026/03/01/9-iranian-naval-ships-have-been-destroyed-and-sunk-trump-says/ | H7: full text | J7: 0.8 | K7: 1 | L7: 0.8
A8: R0007 | B8: 3 | C8: The War Zone | D8: Independent outlet | E8: Iran's Key Naval Base On Strait Of Hormuz Set Ablaze From Strikes | F8: 2026-03-02 | G8: https://www.twz.com/news-features/irans-key-naval-base-on-strait-of-hormuz-set-ablaze-from-strikes | H8: full text | J8: 0.8 | K8: 1 | L8: 0.8
A9: R0008 | B9: 3 | C9: USNI News | D9: Independent outlet | E9: Iranian Naval Forces are Major Target in Operation Epic Fury Strikes | F9: 2026-03-02 | G9: https://news.usni.org/?p=121082 | H9: full text | J9: 0.8 | K9: 1 | L9: 0.8
A10: R0009 | B10: 4 | C10: Reuters (via Yahoo) | D10: Independent outlet | E10: IRGC tell ships passage through Strait of Hormuz 'not allowed' | F10: 2026-02-28 | G10: https://www.yahoo.com/news/articles/irgc-tell-ships-passage-strait-190331404.html | H10: full text | J10: 0.8 | K10: 1 | L10: 0.8
A11: R0010 | B11: 4 | C11: Reuters (via Malay Mail) | D11: Independent outlet | E11: How the Strait of Hormuz blockade is choking global shipping and oil flows | F11: 2026-03-19 | G11: https://www.malaymail.com/news/world/2026/03/19/how-the-strait-of-hormuz-blockade-is-choking-global-shipping-and-oil-flows/213223 | H11: full text | J11: 0.8 | K11: 1 | L11: 0.8
A12: R0011 | B12: 5 | C12: Al Jazeera | D12: Independent outlet | E12: Multiple Arab states that host US assets targeted in Iran retaliation | F12: 2026-02-28 | G12: https://www.aljazeera.com/news/2026/2/28/multiple-gulf-arab-states-that-host-us-assets-targeted-in-iran-retaliation | H12: full text | J12: 0.8 | K12: 1 | L12: 0.8
A13: R0012 | B13: 5 | C13: Times of Israel | D13: Independent outlet | E13: Woman killed, dozens injured as Iranian missile strikes Tel Aviv residential block | F13: 2026-03-01 | G13: https://www.timesofisrael.com/woman-killed-dozens-injured-as-iranian-missile-strikes-tel-aviv-residential-block/ | H13: full text | J13: 0.8 | K13: 1 | L13: 0.8
... A64: R0063 | B64: 28 | C64: Reuters (copy hosted by Bangor Daily News) | D64: Independent outlet | E64: Trump ceasefire with Iran (wire headline not shown in the result) | F64: 2026-04-07 | G64: https://www.bangordailynews.com/2026/04/07/nation/trump-ceasefire-with-iran/ | H64: full text | J64: 0.8 | K64: 1 | L64: 0.8
A65: R0064 | B65: 28 | C65: AP (via KY3) | D65: Independent outlet | E65: US and Iran agree to 2-week ceasefire as Trump pulls back on threats | F65: 2026-04-07 | G65: https://www.ky3.com/2026/04/07/iran-calls-human-chains-protect-power-plants-trumps-deadline-nears/ | H65: full text | I65: 29 | J65: 0.8 | K65: 1 | L65: 0.8
A66: R0065 | B66: 28 | C66: Reuters (copy hosted by Bangor Daily News) | D66: Independent outlet | E66: Trump ceasefire with Iran (wire headline not shown in the result) | F66: 2026-04-07 | G66: https://www.bangordailynews.com/2026/04/07/nation/trump-ceasefire-with-iran/ | H66: full text | I66: 29 | J66: 0.8 | K66: 1 | L66: 0.8
A67: R0066 | B67: 28 | C67: AP (via WSLS) | D67: Independent outlet | E67: The Latest: Trump pulls back on threats as US, Israel and Iran reach a 2-week ceasefire deal | F67: 2026-04-08 | G67: https://www.wsls.com/news/world/2026/04/08/the-latest-trump-pulls-back-on-threats-as-us-israel-and-iran-reach-a-2-week-ceasefire-deal/ | H67: full text | J67: 0.8 | K67: 1 | L67: 0.8
A68: R0067 | B68: 28 | C68: AP (via WSLS) | D68: Independent outlet | E68: The Latest: Trump pulls back on threats as US, Israel and Iran reach a 2-week ceasefire deal | F68: 2026-04-08 | G68: https://www.wsls.com/news/world/2026/04/08/the-latest-trump-pulls-back-on-threats-as-us-israel-and-iran-reach-a-2-week-ceasefire-deal/ | H68: full text | I68: 29 | J68: 0.8 | K68: 1 | L68: 0.8
A69: R0068 | B69: 30 | C69: AP (via Spectrum News) | D69: Independent outlet | E69: Israel strikes Lebanon, Beirut, 100 targets, saying ceasefire does not apply | F69: 2026-04-08 | G69: https://spectrumlocalnews.com/us/snplus/international/2026/04/08/israel-strikes-lebanon-beirut-100-targets-saying-ceasefire-does-not-apply | H69: full text | J69: 0.8 | K69: 1 | L69: 0.8
A70: R0069 | B70: 30 | C70: Al Jazeera | D70: Independent outlet | E70: Israel launches 100 air strikes in 10 minutes across Lebanon | F70: 2026-04-08 | G70: https://www.aljazeera.com/video/newsfeed/2026/4/8/israel-launches-100-air-strikes-in-10-minutes-across-lebanon | H70: full text | J70: 0.8 | K70: 1 | L70: 0.8
A71: R0070 | B71: 30 | C71: Reuters (copy hosted by Daily Maverick) | D71: Independent outlet | E71: Israeli strikes pummel Lebanon, killing 250 in deadliest day of war | F71: 2026-04-09 | G71: https://www.dailymaverick.co.za/article/2026-04-09-israeli-strikes-pummel-lebanon-killing-250-in-deadliest-day-of-war | H71: full text | J71: 0.8 | K71: 1 | L71: 0.8
A72: R0071 | B72: 31 | C72: AP (via WSLS) | D72: Independent outlet | E72: The Latest: Trump pulls back on threats as US, Israel and Iran reach a 2-week ceasefire deal | F72: 2026-04-08 | G72: https://www.wsls.com/news/world/2026/04/08/the-latest-trump-pulls-back-on-threats-as-us-israel-and-iran-reach-a-2-week-ceasefire-deal/ | H72: full text | J72: 0.8 | K72: 1 | L72: 0.8
A73: R0072 | B73: 31 | C73: Reuters (copy hosted by Daily Maverick) | D73: Independent outlet | E73: Israeli strikes pummel Lebanon, killing 250 in deadliest day of war | F73: 2026-04-09 | G73: https://www.dailymaverick.co.za/article/2026-04-09-israeli-strikes-pummel-lebanon-killing-250-in-deadliest-day-of-war | H73: full text | J73: 0.8 | K73: 1 | L73: 0.8
A74: R0073 | B74: 31 | C74: The War Zone | D74: Independent outlet | E74: Iran ceasefire hangs in balance as Israel bombards Lebanon | F74: 2026-04-09 | G74: https://www.twz.com/news-features/iran-ceasefire-hangs-in-balance-as-israel-bombards-lebanon.md | H74: full text | J74: 0.8 | K74: 1 | L74: 0.8
A75: R0074 | B75: 32 | C75: Times of Israel | D75: Independent outlet | E75: Despite ceasefire, Iran claims refinery hit, launches wave of attacks against UAE, Kuwait | F75: 2026-04-08 | G75: https://www.timesofisrael.com/despite-ceasefire-iran-claims-refinery-hit-launches-wave-of-attacks-against-uae-kuwait/ | H75: full text | J75: 0.8 | K75: 1 | L75: 0.8
A76: R0075 | B76: 32 | C76: Times of Israel (liveblog) | D76: Independent outlet | E76: Iran says oil refinery on Lavan Island hit by airstrikes this morning | F76: 2026-04-08 | G76: https://www.timesofisrael.com/liveblog_entry/iran-says-oil-refinery-on-lavan-island-hit-by-airstrikes-this-morning/ | H76: full text | J76: 0.8 | K76: 1 | L76: 0.8
A77: R0076 | B77: 32 | C77: Times of Israel (reporting WSJ) | D77: Independent outlet | E77: UAE secretly launched strikes on Iran during war, attacked oil refinery -- report | F77: 2026-05-12 | G77: https://www.timesofisrael.com/uae-secretly-carried-out-strikes-on-iran-including-on-oil-refinery-report/ | H77: full text | J77: 0.8 | K77: 1 | L77: 0.8
A78: R0077 | B78: 32 | C78: Times of Israel (reporting WSJ) | D78: Independent outlet | E78: UAE struck Iran dozens of times, with US and Israeli intel, during war and amid truce -- WSJ | F78: 2026-05-30 | G78: https://www.timesofisrael.com/uae-struck-iran-dozens-of-times-during-war-and-amid-truce-including-with-israel-wsj/ | H78: full text | J78: 0.8 | K78: 1 | L78: 0.8
A79: R0078 | B79: 33 | C79: Axios | D79: Independent outlet | E79: U.S. warships cross Strait of Hormuz for first time since Iran war began | F79: 2026-04-11 | G79: https://axios.com/2026/04/11/us-iran-navy-strait-of-hormuz | H79: full text | J79: 0.8 | K79: 1 | L79: 0.8
A80: R0079 | B80: 33 | C80: USNI News | D80: Independent outlet | E80: UPDATED: Two U.S. Warships Sail Through Strait of Hormuz to Establish New Route for Merchant Ships | F80: 2026-04-11 | G80: https://news.usni.org/?p=121862 | H80: full text | J80: 0.8 | K80: 1 | L80: 0.8
... A109: R0108 | B109: 48 | C109: AFP (via Ahram; later reference to 11 Jun) | D109: Independent outlet | E109: Jordan's military says intercepted 8 missiles fired from Iran | F109: 2026-07-09 | G109: https://english.ahram.org.eg/News/572559.aspx | H109: full text | J109: 0.8 | K109: 1 | L109: 0.8
A110: R0109 | B110: 50 | C110: Axios | D110: Independent outlet | E110: Trump claims Iran deal reached, Tehran says no 'final decision' | F110: 2026-06-11 | G110: https://axios.com/2026/06/11/trump-cancel-iran-strikes-deal-strait | H110: full text | I110: 49 | J110: 0.8 | K110: 1 | L110: 0.8
A111: R0110 | B111: 50 | C111: Reuters (via Al-Monitor) | D111: Independent outlet | E111: Pakistan PM Sharif says in X post that final text of US-Iran peace deal agreed, working on next steps | F111: 2026-06-12 | G111: https://www.al-monitor.com/originals/2026/06/pakistan-pm-sharif-says-x-post-final-text-us-iran-peace-deal-agreed-working-next | H111: snippet | I111: 49 | J111: 0.8 | K111: 0.8 | L111: 0.64
A112: R0111 | B112: 50 | C112: Reuters (via Dubai Eye 103.8) | D112: Independent outlet | E112: US, Iran sign interim ceasefire agreement | F112: 2026-06-17 | G112: https://www.dubaieye1038.com/news/international/us-iran-sign-interim-ceasefire-agreement/ | H112: full text | I112: 49 | J112: 0.8 | K112: 1 | L112: 0.8
A113: R0112 | B113: 50 | C113: Al Jazeera | D113: Independent outlet | E113: Iran, US presidents sign deal to extend ceasefire, reopen Strait of Hormuz | F113: 2026-06-17 | G113: https://www.aljazeera.com/news/2026/6/17/iran-confirms-that-mou-has-been-signed-electronically-by-both-sides | H113: full text | J113: 0.8 | K113: 1 | L113: 0.8
A114: R0113 | B114: 50 | C114: NPR | D114: Independent outlet | E114: Trump signs preliminary agreement with Iran, after releasing details | F114: 2026-06-17 | G114: https://www.npr.org/2026/06/17/nx-s1-5860782/trump-iran-agreement-g7 | H114: full text | J114: 0.8 | K114: 1 | L114: 0.8
A115: R0114 | B115: 50 | C115: Al Jazeera | D115: Independent outlet | E115: What the Trump-Iran agreement says about Lebanon, Hormuz and uranium | F115: 2026-06-18 | G115: https://www.aljazeera.com/news/2026/6/18/what-the-trump-iran-14-point-plan-says-about-lebanon-hormuz-and-uranium | H115: full text | J115: 0.8 | K115: 1 | L115: 0.8
A116: R0115 | B116: 50 | C116: NPR | D116: Independent outlet | E116: What you need to know about the preliminary U.S.-Iran agreement signed by Trump | F116: 2026-06-19 | G116: https://www.npr.org/2026/06/19/nx-s1-5863544/trump-us-iran-agreement | H116: full text | J116: 0.8 | K116: 1 | L116: 0.8
A117: R0116 | B117: 51 | C117: Al Jazeera | D117: Independent outlet | E117: US military says it has lifted naval blockade of Iranian ports | F117: 2026-06-18 | G117: https://www.aljazeera.com/news/2026/6/18/us-military-says-it-has-lifted-naval-blockade-of-iranian-ports | H117: full text | J117: 0.8 | K117: 1 | L117: 0.8
A118: R0117 | B118: 52 | C118: Reuters (wire text read on Al-Monitor) | D118: Independent outlet | E118: Israel, Hezbollah agree to ceasefire starting on Friday - US official | F118: 2026-06-19 | G118: https://www.al-monitor.com/originals/2026/06/israeli-hezbollah-agree-ceasefire-starting-friday-us-official | H118: full text | J118: 0.8 | K118: 1 | L118: 0.8
A119: R0118 | B119: 52 | C119: AFP (wire text read on Aaj News) | D119: Independent outlet | E119: Iran closes Strait of Hormuz over Lebanon strikes | F119: 2026-06-20 | G119: https://english.aaj.tv/news/330460549 | H119: full text | J119: 0.8 | K119: 1 | L119: 0.8
A120: R0119 | B120: 52 | C120: Reuters (wire text read on Al-Monitor) | D120: Independent outlet | E120: Israeli strikes kill at least 20 in Lebanon hours after ceasefire | F120: 2026-06-20 | G120: https://www.al-monitor.com/originals/2026/06/israeli-strikes-kill-least-20-lebanon-hours-after-ceasefire | H120: full text | J120: 0.8 | K120: 1 | L120: 0.8
A121: R0120 | B121: 53 | C121: AFP (wire text read on Aaj News) | D121: Independent outlet | E121: Iran closes Strait of Hormuz over Lebanon strikes | F121: 2026-06-20 | G121: https://english.aaj.tv/news/330460549 | H121: full text | J121: 0.8 | K121: 1 | L121: 0.8
A122: R0121 | B122: 53 | C122: Al Jazeera | D122: Independent outlet | E122: Iran war live: Tehran says US must ensure Israel ends attacks on Lebanon (live blog; page text not extractable, headline/video titles 'Tehran shuts Hormuz' seen) | F122: 2026-06-20 | G122: https://www.aljazeera.com/news/liveblog/2026/6/20/iran-war-live-tehran-says-us-must-ensure-israel-ends-attacks-on-lebanon | H122: snippet | J122: 0.8 | K122: 0.8 | L122: 0.64
A123: R0122 | B123: 54 | C123: Al Jazeera | D123: Independent outlet | E123: US strikes Iran in response to drone strike on commercial ship | F123: 2026-06-26 | G123: https://aljazeera.com/news/2026/6/26/us-strikes-iran-in-response-to-drone-strike-on-commercial-ship | H123: full text | J123: 0.8 | K123: 1 | L123: 0.8
A124: R0123 | B124: 55 | C124: CENTCOM (official release, mirrored on iranwatch.org) | D124: Official statement | E124: U.S. Forces Conduct Additional Strikes After Iran's Latest Commercial Ship Attack | F124: 2026-06-27 | G124: https://www.iranwatch.org/library/governments/united-states/executive-branch/department-defense/us-forces-conduct-additional-strikes-after-irans-latest-commercial-ship-attack | H124: full text | J124: 0.8 | K124: 1 | L124: 0.8
... A151: R0150 | B151: 71 | C151: Al Jazeera | D151: Independent outlet | E151: Iran attacks US bases in Jordan after US strikes Larak Island | F151: 2026-08-30 | G151: https://aljazeera.com/news/2026/8/30/us-strikes-irans-lark-island-in-first-attack-in-weeks | H151: full text | J151: 0.8 | K151: 1 | L151: 0.8
A152: R0151 | B152: 71 | C152: CBS News | D152: Independent outlet | E152: Jordan and Bahrain face Iranian missiles and drones as hostilities flare (live updates; page date not visible, covers Aug 30-31) | G152: https://www.cbsnews.com/live-updates/iran-war-us-strikes-strait-of-hormuz-larak-island/ | H152: full text | J152: 0.8 | K152: 1 | L152: 0.8
A153: R0152 | B153: 72 | C153: Bloomberg (syndicated copy on World Oil, credited to Bloomberg) | D153: Independent outlet | E153: Two oil tankers reportedly struck as Strait of Hormuz hostilities resume | F153: 2026-09-01 | G153: https://www.worldoil.com/news/2026/9/1/two-oil-tankers-reportedly-struck-as-strait-of-hormuz-hostilities-resume/ | H153: full text | J153: 0.8 | K153: 1 | L153: 0.8
A154: R0153 | B154: 72 | C154: AFP (copy on Ahram Online) | D154: Independent outlet | E154: Two dead after Monday attack on Saudi oil tanker in Hormuz: shipping firm | F154: 2026-09-02 | G154: https://english.ahram.org.eg/News/575814.aspx | H154: full text | J154: 0.8 | K154: 1 | L154: 0.8
A155: R0154 | B155: 72 | C155: CBS News | D155: Independent outlet | E155: Jordan and Bahrain face Iranian missiles and drones as hostilities flare (live updates; page date not visible, covers Aug 30-31) | G155: https://www.cbsnews.com/live-updates/iran-war-us-strikes-strait-of-hormuz-larak-island/ | H155: full text | J155: 0.8 | K155: 1 | L155: 0.8
A156: R0155 | B156: 73 | C156: Al Jazeera | D156: Independent outlet | E156: Iran claims attacks on Bahrain, Jordan, Iraq after US strikes kill 11 | F156: 2026-09-01 | G156: https://www.aljazeera.com/news/2026/9/1/us-military-says-launching-new-attacks-on-iran | H156: full text | J156: 0.8 | K156: 1 | L156: 0.8
A157: R0156 | B157: 73 | C157: CENTCOM (official release) | D157: Official statement | E157: CENTCOM completes strikes on IRGC targets in Iran | F157: 2026-09-01 | G157: https://www.centcom.mil/MEDIA/PUBLIC-RELEASES/Article/4588389/centcom-completes-strikes-on-irgc-targets-in-iran/ | H157: full text | J157: 0.8 | K157: 1 | L157: 0.8
A158: R0157 | B158: 73 | C158: CBS News | D158: Independent outlet | E158: Vance 'extremely skeptical' U.S. strike hit Iran wedding party, says he wouldn't call conflict a war (live updates, Sept 2-4) | F158: 2026-09-02 | G158: https://www.cbsnews.com/live-updates/us-iran-war-trump-dismisses-diplomacy-tehran-says-wedding-hit-in-strike/ | H158: full text | J158: 0.8 | K158: 1 | L158: 0.8
A159: R0158 | B159: 74 | C159: AFP (copy on Ahram Online) | D159: Independent outlet | E159: US strike on a wedding ceremony kills 4, including a child, wounds 50 in Iran | F159: 2026-09-02 | G159: https://english.ahram.org.eg/News/575804.aspx | H159: full text | J159: 0.8 | K159: 1 | L159: 0.8
A160: R0159 | B160: 74 | C160: Al Jazeera | D160: Independent outlet | E160: Iran says US bombed a wedding party in Sirik, killing five | F160: 2026-09-02 | G160: https://www.aljazeera.com/amp/news/2026/9/2/iran-says-us-strikes-hit-a-wedding-party-in-sirik-killing-five | H160: full text | J160: 0.8 | K160: 1 | L160: 0.8
A161: R0160 | B161: 74 | C161: CBS News | D161: Independent outlet | E161: Vance 'extremely skeptical' U.S. strike hit Iran wedding party, says he wouldn't call conflict a war (live updates, Sept 2-4) | F161: 2026-09-02 | G161: https://www.cbsnews.com/live-updates/us-iran-war-trump-dismisses-diplomacy-tehran-says-wedding-hit-in-strike/ | H161: full text | J161: 0.8 | K161: 1 | L161: 0.8
A162: R0161 | B162: 75 | C162: Al Jazeera | D162: Independent outlet | E162: Iran claims attacks on Bahrain, Jordan, Iraq after US strikes kill 11 | F162: 2026-09-01 | G162: https://www.aljazeera.com/news/2026/9/1/us-military-says-launching-new-attacks-on-iran | H162: full text | J162: 0.8 | K162: 1 | L162: 0.8
A163: R0162 | B163: 75 | C163: Al Jazeera | D163: Independent outlet | E163: Iran claims attacks on Bahrain, Jordan, Iraq after US strikes kill 11 | F163: 2026-09-01 | G163: https://www.aljazeera.com/news/2026/9/1/us-military-says-launching-new-attacks-on-iran | H163: full text | I163: 76 | J163: 0.8 | K163: 1 | L163: 0.8
A164: R0163 | B164: 75 | C164: Al Jazeera | D164: Independent outlet | E164: Iran, US exchange new attacks: Who was hit in latest strikes? | F164: 2026-09-02 | G164: https://www.aljazeera.com/news/2026/9/2/iran-us-exchange-new-attacks-who-was-hit-in-latest-strikes | H164: full text | J164: 0.8 | K164: 1 | L164: 0.8
A165: R0164 | B165: 75 | C165: Times of Israel (Reuters-based) | D165: Independent outlet | E165: US strikes Iranian sites around Hormuz, IRGC says it retaliated against base in Jordan | F165: 2026-09-02 | G165: https://www.timesofisrael.com/us-strikes-iranian-sites-around-hormuz-irgc-says-it-retaliated-against-base-in-jordan/ | H165: full text | J165: 0.8 | K165: 1 | L165: 0.8
A166: R0165 | B166: 75 | C166: Al Jazeera | D166: Independent outlet | E166: Iran, US exchange new attacks: Who was hit in latest strikes? | F166: 2026-09-02 | G166: https://www.aljazeera.com/news/2026/9/2/iran-us-exchange-new-attacks-who-was-hit-in-latest-strikes | H166: full text | I166: 76 | J166: 0.8 | K166: 1 | L166: 0.8
A167: R0166 | B167: 75 | C167: Times of Israel (Reuters-based) | D167: Independent outlet | E167: US strikes Iranian sites around Hormuz, IRGC says it retaliated against base in Jordan | F167: 2026-09-02 | G167: https://www.timesofisrael.com/us-strikes-iranian-sites-around-hormuz-irgc-says-it-retaliated-against-base-in-jordan/ | H167: full text | I167: 76 | J167: 0.8 | K167: 1 | L167: 0.8
A168: R0167 | B168: 77 | C168: CENTCOM (press release) | D168: Official statement | E168: CENTCOM Destroys 3 IRGC Oil Tankers After Iran Targets 2 US Navy Warships (headline per URL) | F168: 2026-09-05 | G168: https://www.centcom.mil/MEDIA/PUBLIC-RELEASES/Article/4591744/centcom-destroys-3-irgc-oil-tankers-after-iran-targets-2-us-navy-warships/ | H168: full text | J168: 0.8 | K168: 1 | L168: 0.8
A169: R0168 | B169: 78 | C169: CENTCOM (official release) | D169: Official statement | E169: U.S. Destroys 5 IRGC Tankers After Iran Targets Another American Warship | F169: 2026-09-08 | G169: https://www.centcom.mil/MEDIA/PUBLIC-RELEASES/Article/4593050/us-destroys-5-irgc-tankers-after-iran-targets-another-american-warship/ | H169: full text | J169: 0.8 | K169: 1 | L169: 0.8
A170: R0169 | B170: 78 | C170: Al Jazeera | D170: Independent outlet | E170: US strikes five Iranian oil tankers, as Iran attacks 10 ships, Jordan base | F170: 2026-09-09 | G170: https://www.aljazeera.com/news/2026/9/9/us-destroys-five-iranian-tankers-iran-retaliates-with-attacks-on-jordan-base | H170: full text | J170: 0.8 | K170: 1 | L170: 0.8
A171: R0170 | B171: 78 | C171: Reuters (via Al-Monitor; lede only) | D171: Independent outlet | E171: US military says it destroyed five Iranian oil carriers after attempted missile attacks | F171: 2026-09-09 | G171: https://al-monitor.com/originals/2026/09/us-military-says-it-destroyed-five-iranian-oil-carriers-after-attempted-missile | H171: snippet | J171: 0.8 | K171: 0.8 | L171: 0.64
A172: R0171 | B172: 79 | C172: CENTCOM (official release) | D172: Official statement | E172: U.S. Destroys 5 IRGC Tankers After Iran Targets Another American Warship | F172: 2026-09-08 | G172: https://www.centcom.mil/MEDIA/PUBLIC-RELEASES/Article/4593050/us-destroys-5-irgc-tankers-after-iran-targets-another-american-warship/ | H172: full text | J172: 0.8 | K172: 1 | L172: 0.8
A173: R0172 | B173: 79 | C173: Al Jazeera | D173: Independent outlet | E173: US strikes five Iranian oil tankers, as Iran attacks 10 ships, Jordan base | F173: 2026-09-09 | G173: https://www.aljazeera.com/news/2026/9/9/us-destroys-five-iranian-tankers-iran-retaliates-with-attacks-on-jordan-base | H173: full text | J173: 0.8 | K173: 1 | L173: 0.8
A174: R0173 | B174: 79 | C174: CBS News (live updates) | D174: Independent outlet | E174: Trump says war to end "immediately" after midterms as Iran damages U.S. jets in strikes | F174: 2026-09-09 | G174: https://www.cbsnews.com/live-updates/iran-war-us-tankers-attacks-strikes-strait-of-hormuz-oil-price/ | H174: full text | J174: 0.8 | K174: 1 | L174: 0.8
A175: R0174 | B175: 79 | C175: Reuters (via Al-Monitor; lede only) | D175: Independent outlet | E175: US military says it destroyed five Iranian oil carriers after attempted missile attacks | F175: 2026-09-09 | G175: https://al-monitor.com/originals/2026/09/us-military-says-it-destroyed-five-iranian-oil-carriers-after-attempted-missile | H175: snippet | J175: 0.8 | K175: 0.8 | L175: 0.64
A176: R0175 | B176: 80 | C176: Al Jazeera | D176: Independent outlet | E176: US strikes five Iranian oil tankers, as Iran attacks 10 ships, Jordan base | F176: 2026-09-09 | G176: https://www.aljazeera.com/news/2026/9/9/us-destroys-five-iranian-tankers-iran-retaliates-with-attacks-on-jordan-base | H176: full text | J176: 0.8 | K176: 1 | L176: 0.8
A177: R0176 | B177: 80 | C177: CBS News (live updates) | D177: Independent outlet | E177: Trump says war to end "immediately" after midterms as Iran damages U.S. jets in strikes | F177: 2026-09-09 | G177: https://www.cbsnews.com/live-updates/iran-war-us-tankers-attacks-strikes-strait-of-hormuz-oil-price/ | H177: full text | J177: 0.8 | K177: 1 | L177: 0.8
A178: R0177 | B178: 80 | C178: CBS News | D178: Independent outlet | E178: Multiple U.S. military aircraft damaged in Iranian strikes on military base in Jordan, sources say | F178: 2026-09-10 | G178: https://www.cbsnews.com/news/multiple-us-military-aircraft-damaged-iran-strikes-military-base-jordan/ | H178: full text | J178: 0.8 | K178: 1 | L178: 0.8
A179: R0178 | B179: 80 | C179: Times of Israel (liveblog, Reuters-bylined, cites CBS) | D179: Independent outlet | E179: Several US warplanes reportedly damaged in Iranian attack on airbase in Jordan | F179: 2026-09-10 | G179: https://www.timesofisrael.com/liveblog_entry/several-us-warplanes-reportedly-damaged-in-iranian-attack-on-airbase-in-jordan/ | H179: full text | J179: 0.8 | K179: 1 | L179: 0.8
... A184: R0183 | B184: 83 | C184: Stars and Stripes | D184: Independent outlet | E184: Iran involvement in RAF Fairford incident (headline per URL) | F184: 2026-09-30 | G184: https://www.stripes.com/theaters/europe/2026-09-30/iran-involvement-raf-fairford-incident-23016502.html | H184: full text | J184: 0.8 | K184: 1 | L184: 0.8
A185: R0184 | B185: 84 | C185: Al Jazeera (named in original row) | D185: Independent outlet | E185: (not recorded) | H185: name only - not re-checked | J185: 0.8 | K185: 0.65 | L185: 0.52
A186: R0185 | B186: 85 | C186: AP (via PBS NewsHour) | D186: Independent outlet | E186: U.S. targets Iran's military supply chain as diplomatic talks remain uncertain | F186: 2026-09-29 | G186: https://pbs.org/newshour/world/u-s-targets-irans-military-supply-chain-as-diplomatic-talks-remain-uncertain | H186: full text | J186: 0.8 | K186: 1 | L186: 0.8
A187: R0186 | B187: 85 | C187: Al Jazeera | D187: Independent outlet | E187: US sanctions 10 entities for allegedly supporting Iran's military | F187: 2026-09-29 | G187: https://www.aljazeera.com/news/2026/9/29/us-sanctions-10-entities-for-allegedly-supporting-irans-military | H187: full text | J187: 0.8 | K187: 1 | L187: 0.8
A188: R0187 | B188: 86 | C188: Al Jazeera (named in original row) | D188: Independent outlet | E188: (not recorded) | H188: name only - not re-checked | J188: 0.8 | K188: 0.65 | L188: 0.52
A189: R0188 | B189: 86 | C189: CBS News (named in original row) | D189: Independent outlet | E189: (not recorded) | H189: name only - not re-checked | J189: 0.8 | K189: 0.65 | L189: 0.52
A190: R0189 | B190: 87 | C190: Treasury (press release) | D190: Official statement | E190: Operation Economic Outcast Targets Iran's Remaining Industrial Lifelines | F190: 2026-10-01 | G190: https://content.govdelivery.com/accounts/USTREAS/bulletins/42d6fab | H190: full text | J190: 0.8 | K190: 1 | L190: 0.8
A191: R0190 | B191: 88 | C191: CBS News (named in original row) | D191: Independent outlet | E191: (not recorded) | H191: name only - not re-checked | J191: 0.8 | K191: 0.65 | L191: 0.52
A192: R0191 | B192: 88 | C192: TIME (named in original row) | D192: Independent outlet | E192: (not recorded) | H192: name only - not re-checked | J192: 0.8 | K192: 0.65 | L192: 0.52
A193: R0192 | B193: 89 | C193: CBS News (named in original row) | D193: Independent outlet | E193: (not recorded) | H193: name only - not re-checked | J193: 0.8 | K193: 0.65 | L193: 0.52
A194: R0193 | B194: 90 | C194: Reuters (wire copy republished by The Star) | D194: Independent outlet | E194: Attacks on tankers in Hormuz hit highest of any week since start of Iran war, sources say | F194: 2026-10-07 | G194: https://www.thestar.com.my/news/world/2026/10/07/attacks-on-tankers-in-hormuz-hit-highest-of-any-week-since-start-of-iran-war-sources-say | H194: full text | J194: 0.8 | K194: 1 | L194: 0.8
A195: R0194 | B195: 90 | C195: USNI News | D195: Independent outlet | E195: October Sees Near Daily Strikes on Ships in Hormuz | F195: 2026-10-09 | G195: https://news.usni.org/2026/10/09/october-sees-near-daily-strikes-on-ships-in-hormuz | H195: full text | J195: 0.8 | K195: 1 | L195: 0.8
A196: R0195 | B196: 91 | C196: Reuters (wire copy republished by The Star) | D196: Independent outlet | E196: UK police make further arrest over suspected Fairford airbase plot | F196: 2026-10-06 | G196: https://www.thestar.com.my/news/world/2026/10/06/uk-police-make-further-arrest-over-suspected-fairford-airbase-plot | H196: full text | J196: 0.8 | K196: 1 | L196: 0.8
A197: R0196 | B197: 92 | C197: The War Zone | D197: Independent outlet | E197: Where are the aircraft carriers, October 6, 2026 (title as given in URL slug) | F197: 2026-10-06 | G197: https://www.twz.com/sea/where-are-the-aircraft-carriers-october-6-2026.md | H197: full text | J197: 0.8 | K197: 1 | L197: 0.8
A198: R0197 | B198: 93 | C198: Al Jazeera | D198: Independent outlet | E198: US sets new demands for Iran deal: What are they? | F198: 2026-10-07 | G198: https://www.aljazeera.com/news/2026/10/7/us-sets-new-demands-for-iran-deal-what-are-they | H198: full text | J198: 0.8 | K198: 1 | L198: 0.8
A199: R0198 | B199: 93 | C199: Al Jazeera | D199: Independent outlet | E199: Trump says US will not strike Iran before midterm elections | F199: 2026-10-09 | G199: https://www.aljazeera.com/news/2026/10/9/trump-says-us-will-not-strike-iran-before-midterm-elections | H199: full text | J199: 0.8 | K199: 1 | L199: 0.8
A200: R0199 | B200: 94 | C200: AFP (wire copy republished by The Star) | D200: Independent outlet | E200: India says 12 injured after tanker attacked off Oman | F200: 2026-10-06 | G200: https://www.thestar.com.my/aseanplus/aseanplus-news/2026/10/06/india-says-12-injured-after-tanker-attacked-off-oman | H200: full text | J200: 0.8 | K200: 1 | L200: 0.8
A201: R0200 | B201: 94 | C201: Al Jazeera | D201: Independent outlet | E201: US sets new demands for Iran deal: What are they? | F201: 2026-10-07 | G201: https://www.aljazeera.com/news/2026/10/7/us-sets-new-demands-for-iran-deal-what-are-they | H201: full text | J201: 0.8 | K201: 1 | L201: 0.8
A202: R0201 | B202: 94 | C202: Reuters (wire copy republished by The Star) | D202: Independent outlet | E202: Attacks on tankers in Hormuz hit highest of any week since start of Iran war, sources say | F202: 2026-10-07 | G202: https://www.thestar.com.my/news/world/2026/10/07/attacks-on-tankers-in-hormuz-hit-highest-of-any-week-since-start-of-iran-war-sources-say | H202: full text | J202: 0.8 | K202: 1 | L202: 0.8
A203: R0202 | B203: 95 | C203: Al Jazeera | D203: Independent outlet | E203: US sets new demands for Iran deal: What are they? | F203: 2026-10-07 | G203: https://www.aljazeera.com/news/2026/10/7/us-sets-new-demands-for-iran-deal-what-are-they | H203: full text | J203: 0.8 | K203: 1 | L203: 0.8
A204: R0203 | B204: 95 | C204: Al Jazeera | D204: Independent outlet | E204: Trump says US will not strike Iran before midterm elections | F204: 2026-10-09 | G204: https://www.aljazeera.com/news/2026/10/9/trump-says-us-will-not-strike-iran-before-midterm-elections | H204: full text | J204: 0.8 | K204: 1 | L204: 0.8
A205: R0204 | B205: 96 | C205: Reuters (wire copy republished by Arab News) | D205: Independent outlet | E205: Oil tanker struck by projectile off UAE coast amid surge in attacks | F205: 2026-10-09 | G205: https://www.arabnews.com/middle-east/oil-tanker-struck-by-projectile-off-uae-coast-amid-surge-in-attacks-3005496 | H205: full text | J205: 0.8 | K205: 1 | L205: 0.8
... A359: R0358 | B359: 265 | C359: NAVCENT (official release) | D359: Official statement | E359: U.S. Navy Intercepts More Than 2,000 Assault Rifles Shipped from Iran | F359: 2023-01-10 | G359: https://www.cusnc.navy.mil/Media/News/Display/Article/3263172/us-navy-intercepts-more-than-2000-assault-rifles-shipped-from-iran/ | H359: full text | J359: 0.8 | K359: 1 | L359: 0.8
A361: Evidence behind Trigger Census re-checks (not event reports)
B362: Census #14 | C362: Times of Israel | D362: Independent outlet | E362: US says it destroyed minelayers near Hormuz after Trump warns Iran not to mine strait | F362: 2026-03-11 | G362: https://www.timesofisrael.com/us-says-it-destroyed-minelayers-near-hormuz-after-trump-warns-iran-not-to-mine-strait/amp/ | H362: full text
...

Sheet Chains & Phases
A1: War phases
A2: People act differently in open war than in a ceasefire or a quiet spell, so NAPOR counts risk numbers within the right phase. Boundaries are judgement calls; each names the event that marks it.
A4: Phase | B4: From | C4: To | D4: What marks it | E4: Events in log
A5: Maximum-pressure crisis | B5: 43590 | C5: 43921 | D5: #201 carrier and bombers sent; tanker attacks, drone shootdown, Abqaiq, Soleimani (#215) and Iran's missile revenge (#216) | E5: 21
A6: Shadow conflict | B6: 43922 | C6: 45820 | D6: Sanctions, tanker seizures and tit-for-tat strikes with Iran-backed militias in Iraq and Syria; talks in 2023 and 2025 | E6: 34
A7: Twelve-day war | B7: 45821 | C7: 45832 | D7: #253 Israel strikes Iran; #255 US bombs nuclear sites; #256 Iran hits Al Udeid; #257 ceasefire | E7: 5
A8: Pre-war standoff | B8: 45833 | C8: 46080 | D8: Sanctions, a US buildup (#259, #261) and talks (#260, #262) before the 2026 war | E8: 6
A9: Open war | B9: 46081 | C9: 46119 | D9: #2 Operation Epic Fury opens the war | E9: 27
A10: Fragile ceasefire | B10: 46120 | C10: 46210 | D10: #28 two-week ceasefire (Apr 7-8); renewed Jun 8 (#43); interim deal Jun 17 (#50) | E10: 30
A11: Open war | B11: 46211 | C11: 46228 | D11: #59 Trump declares the ceasefire over; #60 90-target strike wave | E11: 8
A12: Low-intensity war | B12: 46229 | C12: 46274 | D12: End of the nightly US campaign; no ceasefire, occasional exchanges (#70-#80) | E12: 12
A13: Holding pattern | B13: 46275 | C13: 46321 | D13: No direct US-Iran strikes since Sep 9; talks (#81-#99); Trump: no strikes before Nov 3 (#97) | E13: 47
A15: Chance of any reply within ~5 days, by phase (census, best estimate; Open war rows are mostly excluded by the continuous-fighting rule)
A16: Phase | B16: Got a reply | C16: Counted | D16: Share
A17: Open war | B17: 2 | C17: 2 | D17: =IF(C17>0,B17/C17,"-") -> 1
A18: Fragile ceasefire | B18: 15 | C18: 17 | D18: =IF(C18>0,B18/C18,"-") -> 0.88235294
A19: Low-intensity war | B19: 6 | C19: 7 | D19: =IF(C19>0,B19/C19,"-") -> 0.85714286
A20: Holding pattern | B20: 0 | C20: 2 | D20: =IF(C20>0,B20/C20,"-") -> 0
A21: Backtest (backtest.py): predicting with the reply rate in the same phase scored a Brier score of 0.159, better than the overall rate (0.170) and the rate by type of act (0.183); on the last 6 cases 0.20 vs 0.38. Caveat: the phase boundaries were drawn with hindsight, and in real time you only know a quiet spell has started after some days.
A24: Chains (back-and-forths)
A25: Each chain links events where one is a reply to another. Across 27 chains with a hostile act: on average 1.59 side-switches, longest 5; 63% stopped after one reply; average length 3.5 days. Caveat: July's nightly US strikes are under-logged, so chain T13 looks shorter than it was.
A27: Thread ID | B27: Chain | C27: Start | D27: End | E27: Days | F27: Events | G27: Side-switches | H27: Hostile acts | I27: Phase | J27: Event IDs
A28: P01 | B28: Tanker attacks -> more US troops | C28: 43629 | D28: 43633 | E28: 4 | F28: 2 | G28: 1 | H28: 1 | I28: Maximum-pressure crisis | J28: #203, #204
A29: P02 | B29: Drone shootdown -> Khamenei sanctions | C29: 43636 | D29: 43640 | E29: 4 | F29: 2 | G29: 1 | H29: 1 | I29: Maximum-pressure crisis | J29: #205, #206
A30: P03 | B30: Abqaiq attack -> sanctions and troops for Saudi Arabia | C30: 43722 | D30: 43728 | E30: 6 | F30: 3 | G30: 1 | H30: 1 | I30: Maximum-pressure crisis | J30: #209, #210, #211
A31: P04 | B31: K-1 attack -> strikes -> embassy -> Soleimani -> Iran's missile revenge -> sanctions | C31: 43826 | D31: 43840 | E31: 14 | F31: 6 | G31: 5 | H31: 5 | I31: Maximum-pressure crisis | J31: #212, #213, #214, #215, #216, #217
A32: P05 | B32: Taji attack -> US strikes -> Taji hit again | C32: 43901 | D32: 43904 | E32: 3 | F32: 3 | G32: 2 | H32: 3 | I32: Maximum-pressure crisis | J32: #218, #219, #220
A33: P06 | B33: Border strikes -> rockets in Syria | C33: 44374 | D33: 44375 | E33: 1 | F33: 2 | G33: 1 | H33: 2 | I33: Shadow conflict | J33: #223, #224
A34: P07 | B34: Deir ez-Zor strikes -> rockets at US bases | C34: 44797 | D34: 44797 | E34: 0 | F34: 2 | G34: 1 | H34: 2 | I34: Shadow conflict | J34: #225, #226
A35: P08 | B35: Contractor killed -> US strikes -> more rockets | C35: 45008 | D35: 45009 | E35: 1 | F35: 3 | G35: 2 | H35: 3 | I35: Shadow conflict | J35: #227, #228, #229
A36: P09 | B36: Erbil drone attack -> US strikes (militia campaign, context) | C36: 45285 | D36: 45286 | E36: 1 | F36: 2 | G36: 1 | H36: 2 | I36: Shadow conflict | J36: #235, #236
A37: P10 | B37: Tower 22 -> pause announced -> 85 targets -> al-Omar drone | C37: 45319 | D37: 45326 | E37: 7 | F37: 4 | G37: 2 | H37: 3 | I37: Shadow conflict | J37: #238, #239, #240, #241
A38: P11 | B38: Iran's first direct attack on Israel -> drone-program sanctions | C38: 45395 | D38: 45400 | E38: 5 | F38: 2 | G38: 1 | H38: 1 | I38: Shadow conflict | J38: #243, #244
A39: P12 | B39: Iran's missiles at Israel -> THAAD to Israel | C39: 45566 | D39: 45578 | E39: 12 | F39: 2 | G39: 1 | H39: 1 | I39: Shadow conflict | J39: #245, #246
... A59: T19 | B59: Houthi missile strikes on Riyadh (separate front, context) | C59: 46303 | D59: 46305 | E59: 2 | F59: 2 | G59: 0 | H59: 2 | I59: Holding pattern | J59: #98, #102
A62: War intensity, week by week
A63: Points per week: 2 for each direct strike between the US/Israel and Iran, 1 for each attack on shipping / seizure / blockade move, +2 if it killed someone. The 14-day band (Quiet 0, Low 1-5, Medium 6-11, High 12+) uses only earlier events, so it works in real time. Backtest: using this band to predict replies did NOT help (Brier 0.197 vs 0.170 for the plain overall rate): replies came even after quiet weeks, as on Jun 9. So it is shown as a gauge, not used in the numbers. Caveat: it counts logged rows, so big campaigns logged as one row look smaller than they were.
A65: Week starting | B65: Week ending | C65: Direct strikes | D65: Shipping/blockade acts | E65: Deadly events | F65: Points this week | G65: 14-day band at week end
A66: 43584 | B66: 43590 | C66: 0 | D66: 0 | E66: 0 | F66: 0 | G66: Quiet
A67: 43591 | B67: 43597 | C67: 0 | D67: 1 | E67: 0 | F67: 1 | G67: Low
A68: 43598 | B68: 43604 | C68: 0 | D68: 0 | E68: 0 | F68: 0 | G68: Low
A69: 43605 | B69: 43611 | C69: 0 | D69: 0 | E69: 0 | F69: 0 | G69: Quiet
A70: 43612 | B70: 43618 | C70: 0 | D70: 0 | E70: 0 | F70: 0 | G70: Quiet
A71: 43619 | B71: 43625 | C71: 0 | D71: 0 | E71: 0 | F71: 0 | G71: Quiet
A72: 43626 | B72: 43632 | C72: 0 | D72: 1 | E72: 0 | F72: 1 | G72: Low
A73: 43633 | B73: 43639 | C73: 1 | D73: 0 | E73: 0 | F73: 2 | G73: Low
A74: 43640 | B74: 43646 | C74: 0 | D74: 0 | E74: 0 | F74: 0 | G74: Low
A75: 43647 | B75: 43653 | C75: 0 | D75: 0 | E75: 0 | F75: 0 | G75: Quiet
A76: 43654 | B76: 43660 | C76: 0 | D76: 0 | E76: 0 | F76: 0 | G76: Quiet
A77: 43661 | B77: 43667 | C77: 1 | D77: 0 | E77: 0 | F77: 2 | G77: Low
... A457: 46321 | B457: 46327 | C457: 0 | D457: 0 | E457: 0 | F457: 0 | G457: Low

Sheet Forecast Log
A1: Forecast Log - the report card
A2: Each forecast is written down BEFORE the outcome is known and never edited afterwards. After the deadline it is resolved YES/NO from credible sources and scored with the Brier score: (probability - outcome)^2, 0 = perfect, 0.25 = coin flip. Over time this shows whether NAPOR's risk numbers can be trusted.
A3: Made: 6 Resolved: 3 Open: 3 Average Brier score so far: 0.034
A5: ID | B5: Made on | C5: News known up to | D5: Question | E5: Counts as YES if | F5: Deadline | G5: Probability | H5: Where the number came from | I5: Option | J5: Outcome | K5: Resolved on | L5: Brier score | M5: Resolution note
A6: F001 | B6: 2026-10-14 | C6: 2026-10-11 | D6: Will Iran hit back for the US strike that disabled a blockade runner in the Gulf of Oman (Oct 10-11, event #104)? | E6: Between Oct 11 and Oct 16 (inclusive), Iran (IRGC or Iranian state forces) carries out, or officially claims, a strike or attack on US forces, a US base, or a US-flagged or US-escorted ship, as reported by an allowed outlet or official statement. Attacks on other commercial shipping by unknown attackers do not count. | F6: 2026-10-16 | G6: 0.25 | H6: Phase model (best in backtest): in the current holding pattern 0 of 2 hostile acts drew a reply -> (0+1)/(2+2) = 25%. For comparison, naval-pressure moves in ALL phases drew a reply 2 of 3 (67%). Also: Trump says no US strikes before Nov 3; Iran is reviewing the US counter-offer. | I6: D | J6: NO | K6: 2026-10-19 | L6: 0.062 | M6: NO. No allowed outlet or official statement reports an Iranian (IRGC or state) strike or attack on US forces, a US base, or a US-flagged or US-escorted ship during Oct 11-16. Al Jazeera (Oct 17) lists the week's attacks as all on commercial ships and says the US had not responded to them. Close call to note: Iran's security chief said (Oct 11) Iran was striking ships in the 'US-backed' oil shuttle, and the IRGC said one tanker hit on Oct 17-18 was crossing 'with US support'; no outlet says any ship hit Oct 11-16 was US-flagged or under US warship escort, and the Oct 17-18 claim falls after the deadline. CENTCOM's Oct 14 statement about a dhow 'targeting' US ships refers to Oct 6 surveillance, before the window.
A7: F002 | B7: 2026-10-14 | C7: 2026-10-11 | D7: Will there be at least one new attack on a commercial ship in or near the Strait of Hormuz / Gulf (by Iran or an unidentified attacker) during Oct 12-18? | E7: An allowed outlet, UKMTO or CENTCOM reports at least one new projectile, drone, mine or boarding attack on a commercial vessel in the Gulf, Strait of Hormuz or Gulf of Oman dated Oct 12-18, not attributed to the US. Houthi attacks in the Red Sea do not count. | F7: 2026-10-18 | G7: 0.83 | H7: Baseline: 8 such acts in 4.6 weeks of the current phase = 1.8 per week. Chance of at least one in a week (Poisson) = 1 - e^-1.8 = 83%. | I7: A | J7: YES | K7: 2026-10-19 | L7: 0.029 | M7: YES. On Oct 13 the Singapore-flagged container ship GFS Pride was hit by a projectile in the Strait of Hormuz and sank (Reuters, citing Singapore's MPA; all 21 crew safe), and UKMTO reported a tanker hit the same day (Al Jazeera). CENTCOM said an IRGC projectile hit GFS Pride. More attacks followed (Oct 16-17 off Saudi Arabia; UKMTO counted 10-12 in the week to Oct 16).
A8: F003 | B8: 2026-10-19 | C8: 2026-10-18 | D8: Will the US strike a target on Iranian land or in Iranian territorial waters between Oct 20 and Nov 3 (inclusive)? | E8: An allowed outlet or an official US statement reports a US strike (air, missile, drone or naval gunfire) on a target on Iranian soil, an Iranian island, or in an Iranian port or territorial waters, dated Oct 20-Nov 3. Blockade enforcement against ships at sea outside Iranian territorial waters, seizures, and strikes by Israel alone do not count. | F8: 2026-11-03 | G8: 0.28 | H8: Phase base rate: in the holding pattern (since Sep 10) there have been 0 US strikes on Iranian land in 5 full weeks -> weekly chance (0+1)/(5+2) = 14%; over 15 days 1-(1-0.14)^(15/7) = 28%. Not in the model: Trump's public pledge of no strikes before Nov 3 (#97) and reported strike plans (#111). | I8: F | J8: OPEN
A9: F004 | B9: 2026-10-19 | C9: 2026-10-18 | D9: Will there be at least one new attack on a commercial ship in or near the Strait of Hormuz / Gulf (by Iran or an unidentified attacker) during Oct 19-25? | E9: An allowed outlet, UKMTO or CENTCOM reports at least one new projectile, drone, mine or boarding attack on a commercial vessel in the Gulf, Strait of Hormuz or Gulf of Oman dated Oct 19-25, not attributed to the US. Houthi attacks in the Red Sea do not count. | F9: 2026-10-25 | G9: 0.89 | H9: Baseline: 12 logged attack rows in 5.6 weeks of the current phase = 2.2 per week; chance of at least one in a week (Poisson) = 1 - e^-2.2 = 89%. Logged rows under-count single attacks (UKMTO counted 10-12 in the week to Oct 16), so this is likely conservative. Same method as F002. | I9: A | J9: YES | K9: 2026-10-26 | L9: 0.012 | M9: YES. UKMTO reported an unknown projectile hitting a tanker about 30 nm southeast of Iraq's Faw port on Oct 20 (no damage, crew safe; Reuters) and a tanker hit and set on fire 11 nm off Bukha, Oman, at the Strait of Hormuz on Oct 21 (crew safe; AFP via Times of Israel). The IRGC also claimed seven tankers hit on Oct 22 and two on Oct 23 (Al Jazeera); those are unverified claims and are not needed for the YES.
A10: F005 | B10: 2026-10-19 | C10: 2026-10-18 | D10: Will Iran attack US forces, a US base, or a US-flagged or US Navy-escorted ship between Oct 19 and Nov 3 (inclusive)? | E10: Iran (IRGC or Iranian state forces) carries out, or officially claims, a strike or attack on US forces, a US base, a US-flagged ship, or a ship that an allowed outlet or CENTCOM says was under US Navy escort at the time, dated Oct 19-Nov 3. Attacks on other commercial ships (including ships only 'coordinating with' or 'supported by' the US), surveillance or warnings, and Houthi attacks do not count. | F10: 2026-11-03 | G10: 0.3 | H10: Phase base rate: 0 Iranian attacks on US forces in 5 full weeks of the holding pattern (last one: Jordan base, Sep 8-9, #80) -> weekly chance 14%; over 16 days = 30%. Not in the model: Iran's stated wish to hurt the US before the midterms through shipping and oil prices, rather than direct attacks. | I10: A | J10: OPEN
A11: F006 | B11: 2026-10-26 | C11: 2026-10-26 | D11: Will there be at least one new attack on a commercial ship in or near the Strait of Hormuz / Gulf (by Iran or an unidentified attacker) during Oct 26-Nov 1? | E11: An allowed outlet, UKMTO or CENTCOM reports at least one new projectile, drone, mine or boarding attack on a commercial vessel in the Gulf, Strait of Hormuz or Gulf of Oman dated Oct 26-Nov 1, not attributed to the US. IRGC claims alone (not confirmed by UKMTO, CENTCOM or an allowed outlet's own reporting) do not count. Houthi attacks in the Red Sea do not count. | F11: 2026-11-01 | G11: 0.91 | H11: Baseline: 16 logged attack rows in 6.6 weeks of the current phase (Sep 10-Oct 25) = 2.4 per week; chance of at least one in a week (Poisson) = 1 - e^-2.4 = 91%. Same method as F002/F004. Caution: UKMTO-confirmed hits this week (2) were fewer than the record week to Oct 16, and some logged rows are IRGC claims, so the true rate of confirmed attacks may be lower. | I11: A | J11: OPEN

Sheet Review Queue
A1: Review Queue - a person decides these
A2: Part 1: event pairs that look alike (same few days, same place, same side). Many are two parts of one attack wave, or a claim and the real event, rather than true duplicates. Check each and either merge it or mark it 'different events'.
A4: Similarity (0-1) | B4: Event A | C4: Date A | D4: Event A detail | E4: Event B | F4: Date B | G4: Event B detail | H4: Decision
A5: 0.894 | B5: 43 | C5: 2026-06-08 | D5: Iran agrees to halt attacks on Israel after the two traded fire on Jun 6-7, the first exchange since the April ceasefire | E5: 116 | F5: 2026-06-07 | G5: Iran and Israel trade fire over the weekend of Jun 6-7, the first exchange since the April ceasefire; Iran then agrees to halt attacks (see #43) | H5: to check
A6: 0.751 | B6: 212 | C6: 2019-12-27 | D6: Rocket attack on the K-1 base near Kirkuk kills a US contractor; the US blames Kataib Hezbollah | E6: 213 | F6: 2019-12-29 | G6: US strikes five Kataib Hezbollah sites in Iraq and Syria in retaliation for the K-1 attack | H6: to check
A7: 0.668 | B7: 210 | C7: 2019-09-20 | D7: Treasury sanctions Iran's central bank and national development fund after the Saudi oil attack | E7: 211 | F7: 2019-09-20 | G7: Pentagon announces troops and air-defense equipment for Saudi Arabia and the UAE after the oil attack | H7: to check
A8: 0.651 | B8: 98 | C8: 2026-10-08 | D8: Houthis fire a ballistic missile at Riyadh's King Khalid airport, citing Saudi strikes on Sanaa and Hodeidah; part of the separate Saudi-Houthi front | E8: 102 | F8: 2026-10-10 | G8: Second, deadlier missile attack shuts Riyadh airport; Trump calls it 'terrible' and says he is weighing a response | H8: Different events: two separate Houthi attacks on Riyadh (Oct 8 and Oct 10).
A9: 0.642 | B9: 118 | C9: 2026-10-21 | D9: UKMTO: a tanker 11 nautical miles off Bukha, Oman, at the Strait of Hormuz, is hit by an unknown projectile and catches fire; now at anchor | E9: 121 | F9: 2026-10-22 | G9: IRGC CLAIMS seven tankers were hit overnight into Oct 22 (four struck while transferring oil, three by mines) and warns the conflict 'will extend to' US bases if the US keeps helping tankers through; Trump says Iran is 'making up fake hits, mines'; CENTCOM says the mine claims are incorrect and Iran is using missiles and drones | H9: to check
A10: 0.637 | B10: 101 | C10: 2026-10-09 | D10: IRGC Navy CLAIMS it hit the LPG carrier NV Sunshine on an 'illegal route' and warns ships using unauthorised passages | E10: 103 | F10: 2026-10-10 | G10: IRGC Navy CLAIMS an unnamed supertanker on an unauthorised route hit a naval mine and caught fire, and threatens other tankers | H10: Different events: two separate IRGC claims (NV Sunshine Oct 9; mine strike Oct 10).
A11: 0.633 | B11: 235 | C11: 2023-12-25 | D11: Drone attack on Erbil air base wounds three US service members | E11: 236 | F11: 2023-12-26 | G11: US strikes three sites used by Kataib Hezbollah after the Erbil drone attack | H11: to check
A12: 0.623 | B12: 66 | C12: 2026-07-19 | D12: IRGC says ballistic missiles hit US aircraft at Aqaba airport (Jul 19); Jordan says it shot down 3 missiles and a 4th fell in open ground | E12: 67 | F12: 2026-07-20 | G12: IRGC claims it destroyed a missile-defense radar and an F-15 at a US base in Jordan (Jul 21). No US or Jordanian confirmation | H12: Different events: separate IRGC claims (Aqaba Jul 19; radar and F-15 Jul 21).
A13: 0.61 | B13: 3 | C13: 2026-02-28 | D13: US strikes hit Iran's navy from the first hours: drone carrier Shahid Bagheri attacked (CENTCOM); Bayandor and Naghdi reported sunk at Konarak (The War Zone) | E13: 8 | F13: 2026-02-28 | G13: CENTCOM says the Iranian frigate Jamaran was struck at Chabahar at the start of Epic Fury and is 'sinking'; Makran struck at Bandar Abbas (USNI imagery), sinking not confirmed | H13: Keep both: same opening wave, but different ships hit.
A14: 0.601 | B14: 73 | C14: 2026-09-01 | D14: New strike wave: Kenerak, Bandar Abbas, Qeshm Island | E14: 74 | F14: 2026-09-01 | G14: Kuhestak/Sirik wedding strike, part of the same wave as #73 | H14: Keep both, linked: #74 is one strike inside the #73 wave, logged separately because it caused casualties.
A15: Already resolved: #76 merged into #75 (one attack reported over two days); #49 merged into #50 (same Jun 17 deal signing); #29 merged into #28 (same Apr 7-8 ceasefire).
A17: Part 2: new stories waiting to be filed (from napor_ids.intake). Empty means nothing is waiting.
A18: Report ID | B18: Published | C18: Outlet | D18: Headline | E18: Matcher's call | F18: Best match (event) | G18: Status
A19: R0219 | B19: 2026-10-14 | C19: Times of Israel (Reuters liveblog) | D19: US says it destroyed Iranian-affiliated vessel conducting surveillance last week | E19: NEW EVENT | F19: 106 | G19: confirmed by weekly agent 2026-10-19: logged as new event #106 (sources in audit_sources.py)
A20: R0220 | B20: 2026-10-08 | C20: Treasury | D20: Operation Economic Outcast Neutralizes Iranian Regime's Remaining Shadow Fleet Network | E20: NEW EVENT | F20: 106 | G20: confirmed by weekly agent 2026-10-19: logged as new event #107 (sources in audit_sources.py)
A21: R0221 | B21: 2026-10-11 | C21: Times of Israel (Reuters liveblog) | D21: Iran says US response to its proposal to reopen Hormuz was 'insufficient' | E21: POSSIBLE MATCH - human should check | F21: 103 | G21: confirmed by weekly agent 2026-10-19: logged as new event #108 (sources in audit_sources.py)
A22: R0222 | B22: 2026-10-12 | C22: Al Jazeera | D22: Iran sets crosshairs on 'US-UAE' oil shuttle out of Strait of Hormuz | E22: POSSIBLE MATCH - human should check | F22: 103 | G22: needs human check: IRGC claims of tanker strikes overnight Oct 11-12 (one near Sohar; three 'mine' hits over the weekend) may be the same incidents as #103 (Oct 10 IRGC mine claim) and/or #105 (Oct 11 UKMTO tanker hit). Not logged.
A23: R0223 | B23: 2026-10-14 | C23: Reuters via Internazionale | D23: Container ship sinks near Hormuz after being hit by projectile, sources say | E23: NEW EVENT | F23: 106 | G23: confirmed by weekly agent 2026-10-19: logged as new event #109 (sources in audit_sources.py)
A24: R0224 | B24: 2026-10-15 | C24: Treasury | D24: Operation Economic Outcast Targets Iran's International Financial Networks and Shadow Banking Architecture | E24: NEW EVENT | F24: 106 | G24: confirmed by weekly agent 2026-10-19: logged as new event #110 (sources in audit_sources.py)
A25: R0225 | B25: 2026-10-16 | C25: CBS News | D25: Iran says Strait of Hormuz reopening, seven-day ceasefire conditions still on the table | E25: NEW EVENT | F25: 106 | G25: confirmed by weekly agent 2026-10-19: logged as new event #111 (sources in audit_sources.py)
A26: R0226 | B26: 2026-10-17 | C26: Al Jazeera | D26: US and Iran both claim control of Strait of Hormuz amid attacks on vessels | E26: NEW EVENT | F26: 106 | G26: confirmed by weekly agent 2026-10-19: logged as new event #112 (sources in audit_sources.py)
A27: R0227 | B27: 2026-10-18 | C27: Al Jazeera | D27: Iran says two tankers catch fire after hitting mines in Strait of Hormuz | E27: NEW EVENT | F27: 106 | G27: confirmed by weekly agent 2026-10-19: logged as new event #113 (sources in audit_sources.py)
A28: R0228 | B28: 2026-10-18 | C28: CBS News | D28: Iran says Strait of Hormuz reopening, seven-day ceasefire conditions still on the table | E28: NEW EVENT | F28: 106 | G28: confirmed by weekly agent 2026-10-19: logged as new event #114 (sources in audit_sources.py)
A29: R0229 | B29: 2026-10-18 | C29: CBS News | D29: Iran says Strait of Hormuz reopening, seven-day ceasefire conditions still on the table | E29: NEW EVENT | F29: 106 | G29: confirmed by weekly agent 2026-10-19: logged as new event #115 (sources in audit_sources.py)
A30: R0252 | B30: 2026-10-18 | C30: Al Jazeera (with AFP) | D30: Iran says two tankers catch fire after hitting mines in Strait of Hormuz | E30: SAME EVENT | F30: 113 | G30: needs human check: Iranian army claim only, no ship names; could overlap #112 (tankers hit off Saudi Arabia Oct 16-17) or be separate Gulf of Oman incidents. Not logged.
... A40: R0361 | B40: 2026-10-22 | C40: Al Jazeera | D40: Iran says seven ships hit in Hormuz Strait, warns US of wider response | E40: POSSIBLE OVERLAP | F40: 118 | G40: needs human check: the IRGC's claim of seven tankers hit overnight into Oct 22 (#121) may include the UKMTO-confirmed tanker hit off Bukha on Oct 21 (#118); duplicate_watch scores the pair 0.64. Both kept as separate rows; not merged.
